Workbook

Sheet Sheet1
B2: Today's deliverable | C2: 45762
B4: NEW KPI-Done & Aligned, shared with NML as per below email. | C4: Done
B5: Supplement KPI - Done & Aligned, shared with NML as per below email. | C5: Done
B7: VA – To be sent today, COB. WIP
B8: Actual
B9: Vs 2+1 corrected version | C9: Done
B10: VS PY YTD (ROP)
B11: VS 0+3 QTD (New KPI) | C11: Done
B13: BP
B14: BP25 Q1 vs FY24 Q4
B15: BP25 FY vs FY24 FY

Sheet Summary month
E2: Apr | F2: Select Month
B4: CMP-I + Fixed Cost
B5: M EUR | F5: Actual | K5: BP | O5: Act vs BP | T5: FC 2+10 | X5: Act vs FC2+10 | AC5: OL (1+2) | AG5: Act vs OL | AL5: LY | AP5: Act vs LY | AU5: Previous month | AV5: MoM M09 vs M08 | AX5: FC 5+7 | BB5: Act vs FC 5+7 | BG5: OL (1+2) | BK5: Act vs OL (0+3) | BP5: OL (2+1) | BT5: OL(2+1)vs OL (0+3) | BY5: Jun MTD vs OL(2+1) | CA5: Q2 FC 2+10 | CC5: Q2(2+10) vs Jun FY25 Q1 | CE5: FC 7+5 | CI5: Act vs FC 7+5 | CM5: 7+5 Q4 | CN5: Q3 Actual vs 7+5 Q4
F6: =Act!S5 -> M01 | G6: =Act!T5 -> M02 | H6: =Act!U5 -> M03 | I6: Q4 | K6: =F6 -> M01 | L6: =G6 -> M02 | M6: =H6 -> M03 | N6: =I6 -> Q4 | O6: =K6 -> M01 | P6: =L6 -> M02 | Q6: =M6 -> M03 | R6: =N6 -> Q4 | T6: =F6 -> M01 | U6: =G6 -> M02 | V6: =H6 -> M03 | W6: =I6 -> Q4 | X6: =F6 -> M01 | Y6: =G6 -> M02 | Z6: =H6 -> M03 | AA6: =W6 -> Q4 | AC6: =O6 -> M01 | AD6: =P6 -> M02 | AE6: =Q6 -> M03 | AF6: =R6 -> Q4 | AG6: =O6 -> M01 | AH6: =P6 -> M02 | AI6: =Q6 -> M03 | AJ6: =AF6 -> Q4 | AL6: =X6 -> M01 | AM6: =Y6 -> M02 | AN6: =Z6 -> M03 | AO6: =AA6 -> Q4 | AP6: =X6 -> M01 | AQ6: =Y6 -> M02 | AR6: =Z6 -> M03 | AS6: =AO6 -> Q4 | AU6: M08 | AV6: M09 | AX6: =AL6 -> M01 | AY6: =AM6 -> M02 | AZ6: =AN6 -> M03 | BA6: =AO6 -> Q4 | BB6: =AP6 -> M01 | BC6: =AQ6 -> M02 | BD6: =AR6 -> M03 | BE6: =AS6 -> Q4 | BG6: =F6 -> M01 | BH6: =G6 -> M02 | BI6: =H6 -> M03 | BJ6: =I6 -> Q4 | BK6: =BG6 -> M01 | BL6: =BH6 -> M02 | BM6: =BI6 -> M03 | BN6: =BJ6 -> Q4 | BP6: =O6 -> M01 | BQ6: =P6 -> M02 | BR6: =Q6 -> M03 | BS6: =R6 -> Q4 | BT6: =BP6 -> M01 | BU6: =BQ6 -> M02 | BV6: =BR6 -> M03 | BW6: =BS6 -> Q4 | BY6: =BV6 -> M03 | CA6: Q2 | CC6: Q1 | CE6: =AX6 -> M01 | CF6: =AY6 -> M02 | CG6: =AZ6 -> M03 | CH6: =I6 -> Q4 | CI6: =CE6 -> M01 | CJ6: =CF6 -> M02 | CK6: =CG6 -> M03 | CL6: =CH6 -> Q4
C7: TIV | F7: =IF(Act!S$3=1,Act!S6,"") -> 1356.722 | G7: =IF(Act!T$3=1,Act!T6,"") | H7: =IF(Act!U$3=1,Act!U6,"") | I7: =SUM(F7:H7) -> 1356.722 | K7: =IF(BP!S$3=1,BP!S6,"") -> 1306.0789 | L7: =IF(BP!T$3=1,BP!T6,"") | M7: =IF(BP!U$3=1,BP!U6,"") | N7: =SUM(K7:M7) -> 1306.0789 | O7: =IFERROR(F7-K7,0) -> 50.643078 | P7: =IFERROR(G7-L7,0) -> 0 | Q7: =IFERROR(H7-M7,0) -> 0 | R7: =I7-N7 -> 50.643078 | T7: =IF('FC2+10'!S$3=1,'FC2+10'!S6,"") -> 1356.721 | U7: =IF('FC2+10'!T$3=1,'FC2+10'!T6,"") | V7: =IF('FC2+10'!U$3=1,'FC2+10'!U6,"") | W7: =SUM(T7:V7) -> 1356.721 | X7: =IFERROR(F7-T7,0) -> 0.001 | Y7: =IFERROR(G7-U7,0) -> 0 | Z7: =IFERROR(H7-V7,0) -> 0 | AA7: =I7-W7 -> 0.001 | AC7: =IF(OL!S$3=1,OL!S6,"") -> 1238.3779 | AD7: =IF(OL!T$3=1,OL!T6,"") -> 1315.161 | AE7: =IF(OL!U$3=1,OL!U6,"") | AF7: =SUM(AC7:AE7) -> 2553.5389 | AG7: =IFERROR(F7-AC7,0) -> 118.3441 | AH7: =IFERROR(G7-AD7,0) -> 0 | AI7: =IFERROR(H7-AE7,0) -> 0 | AJ7: =IFERROR(I7-AF7,0) -> -1196.8169 | AL7: =IF(LY!S$3=1,LY!S6,"") -> 1354.65 | AM7: =IF(LY!T$3=1,LY!T6,"") | AN7: =IF(LY!U$3=1,LY!U6,"") | AO7: =SUM(AL7:AN7) -> 1354.65 | AP7: =IFERROR(F7-AL7,0) -> 2.072 | AQ7: =IFERROR(G7-AM7,0) -> 0 | AR7: =IFERROR(H7-AN7,0) -> 0 | AS7: =IFERROR(I7-AO7,0) -> 2.072 | AU7: =Act!L6 -> 1406.473 | AV7: =H7-AU7 -> #VALUE! | AX7: =IF('FC5+7'!S$3=1,'FC5+7'!S6,"") -> 1356.721 | AY7: =IF('FC5+7'!T$3=1,'FC5+7'!T6,"") | AZ7: =IF('FC5+7'!U$3=1,'FC5+7'!U6,"") | BA7: =SUM(AX7:AZ7) -> 1356.721 | BB7: =IFERROR(F7-AX7,0) -> 0.001 | BC7: =IFERROR(G7-AY7,0) -> 0 | BD7: =IFERROR(H7-AZ7,0) -> 0 | BE7: =IFERROR(I7-BA7,0) -> 0.001 | BG7: =F7 -> 1356.722 | BH7: 1374.0032 | BI7: 1555.0535 | BJ7: =SUM(BG7:BI7) -> 4285.7787 | BK7: =IFERROR(F7-AC7,0) -> 118.3441 | BL7: =IFERROR(G7-AD7,0) -> 0 | BM7: =IFERROR(AL7-AE7,0) -> 0 | BN7: =IFERROR(I7-BJ7,0) -> -2929.0567 | BP7: =F7 -> 1356.722 | BQ7: =G7 | BR7: =#REF! -> #REF! | BS7: =SUM(BP7:BR7) -> #REF! | BT7: =BP7-AC7 -> 118.3441 | BU7: =BQ7-AD7 -> #VALUE! | BV7: =BR7-AE7 -> #REF! | BW7: =BS7-AF7 -> #REF! | BY7: =H7-BR7 -> #VALUE! | CA7: ='FC2+10'!AA6 -> 3738.528 | CC7: =CA7-I7 -> 2381.806 | CE7: =IF('FC7+5'!S$3=1,'FC7+5'!S6,"") -> 1356.721 | CF7: =IF('FC7+5'!T$3=1,'FC7+5'!T6,"") | CG7: =IF('FC7+5'!U$3=1,'FC7+5'!U6,"") | CH7: =SUM(CE7:CG7) -> 1356.721 | CI7: =IFERROR(F7-CE7,0) -> 0.001 | CJ7: =IFERROR(G7-CF7,0) -> 0 | CK7: =IFERROR(H7-CG7,0) -> 0 | CL7: =IFERROR(I7-CH7,0) -> 0.001 | CM7: =IF('FC7+5'!AC$3=1,'FC7+5'!AC6,"") -> 4279.805 | CN7: =I7-CM7 -> -2923.083
C8: Retail sales volume (K units) - NISSAN | F8: =IF(Act!S$3=1,Act!S7,"") -> 20.429 | G8: =IF(Act!T$3=1,Act!T7,"") | H8: =IF(Act!U$3=1,Act!U7,"") | I8: =SUM(F8:H8) -> 20.429 | K8: =IF(BP!S$3=1,BP!S7,"") -> 21.907 | L8: =IF(BP!T$3=1,BP!T7,"") | M8: =IF(BP!U$3=1,BP!U7,"") | N8: =SUM(K8:M8) -> 21.907 | O8: =IFERROR(F8-K8,0) -> -1.478 | P8: =IFERROR(G8-L8,0) -> 0 | Q8: =IFERROR(H8-M8,0) -> 0 | R8: =F8-K8 -> -1.478 | T8: =IF('FC2+10'!S$3=1,'FC2+10'!S7,"") -> 20.429 | U8: =IF('FC2+10'!T$3=1,'FC2+10'!T7,"") | V8: =IF('FC2+10'!U$3=1,'FC2+10'!U7,"") | W8: =SUM(T8:V8) -> 20.429 | X8: =IFERROR(F8-T8,0) -> 0 | Y8: =IFERROR(G8-U8,0) -> 0 | Z8: =IFERROR(H8-V8,0) -> 0 | AA8: =I8-W8 -> 0 | AC8: =IF(OL!S$3=1,OL!S7,"") -> 28.803 | AD8: =IF(OL!T$3=1,OL!T7,"") -> 23.689 | AE8: =IF(OL!U$3=1,OL!U7,"") | AF8: =SUM(AC8:AE8) -> 52.492 | AG8: =IFERROR(F8-AC8,0) -> -8.374 | AH8: =IFERROR(G8-AD8,0) -> 0 | AI8: =IFERROR(H8-AE8,0) -> 0 | AJ8: =IFERROR(I8-AF8,0) -> -32.063 | AL8: =IF(LY!S$3=1,LY!S7,"") -> 22.135 | AM8: =IF(LY!T$3=1,LY!T7,"") | AN8: =IF(LY!U$3=1,LY!U7,"") | AO8: =SUM(AL8:AN8) -> 22.135 | AP8: =IFERROR(F8-AL8,0) -> -1.706 | AQ8: =IFERROR(G8-AM8,0) -> 0 | AR8: =IFERROR(H8-AN8,0) -> 0 | AS8: =IFERROR(I8-AO8,0) -> -1.706 | AU8: =Act!L7 -> 28.564 | AV8: =H8-AU8 -> #VALUE! | AX8: =IF('FC5+7'!S$3=1,'FC5+7'!S7,"") -> 20.429 | AY8: =IF('FC5+7'!T$3=1,'FC5+7'!T7,"") | AZ8: =IF('FC5+7'!U$3=1,'FC5+7'!U7,"") | BA8: =SUM(AX8:AZ8) -> 20.429 | BB8: =IFERROR(F8-AX8,0) -> 0 | BC8: =IFERROR(G8-AY8,0) -> 0 | BD8: =IFERROR(H8-AZ8,0) -> 0 | BE8: =IFERROR(I8-BA8,0) -> 0 | BG8: =F8 -> 20.429 | BH8: 27.635 | BI8: 34.498 | BJ8: =SUM(BG8:BI8) -> 82.562 | BK8: =IFERROR(F8-AC8,0) -> -8.374 | BL8: =IFERROR(G8-AD8,0) -> 0 | BM8: =IFERROR(AL8-AE8,0) -> 0 | BN8: =IFERROR(I8-BJ8,0) -> -62.133 | BP8: =F8 -> 20.429 | BQ8: =G8 | BR8: =#REF! -> #REF! | BS8: =SUM(BP8:BR8) -> #REF! | BT8: =BP8-AC8 -> -8.374 | BU8: =BQ8-AD8 -> #VALUE! | BV8: =BR8-AE8 -> #REF! | BW8: =BS8-AF8 -> #REF! | BY8: =H8-BR8 -> #VALUE! | CA8: ='FC2+10'!AA7 -> 80.376 | CC8: =CA8-I8 -> 59.947 | CE8: =IF('FC7+5'!S$3=1,'FC7+5'!S7,"") -> 20.429 | CF8: =IF('FC7+5'!T$3=1,'FC7+5'!T7,"") | CG8: =IF('FC7+5'!U$3=1,'FC7+5'!U7,"") | CH8: =SUM(CE8:CG8) -> 20.429 | CI8: =IFERROR(F8-CE8,0) -> 0 | CJ8: =IFERROR(G8-CF8,0) -> 0 | CK8: =IFERROR(H8-CG8,0) -> 0 | CL8: =IFERROR(I8-CH8,0) -> 0 | CM8: =IF('FC7+5'!AC$3=1,'FC7+5'!AC7,"") -> 105.196 | CN8: =I8-CM8 -> -84.767
C9: Retail sales volume (K units) - INFINITI | F9: =IF(Act!S$3=1,Act!S8,"") -> 0 | G9: =IF(Act!T$3=1,Act!T8,"") | H9: =IF(Act!U$3=1,Act!U8,"") | I9: =SUM(F9:H9) -> 0 | K9: =IF(BP!S$3=1,BP!S8,"") -> 0 | L9: =IF(BP!T$3=1,BP!T8,"") | M9: =IF(BP!U$3=1,BP!U8,"") | N9: =SUM(K9:M9) -> 0 | O9: =IFERROR(F9-K9,0) -> 0 | P9: =IFERROR(G9-L9,0) -> 0 | Q9: =IFERROR(H9-M9,0) -> 0 | R9: =F9-K9 -> 0 | T9: =IF('FC2+10'!S$3=1,'FC2+10'!S8,"") -> 0 | U9: =IF('FC2+10'!T$3=1,'FC2+10'!T8,"") | V9: =IF('FC2+10'!U$3=1,'FC2+10'!U8,"") | W9: =SUM(T9:V9) -> 0 | X9: =IFERROR(F9-T9,0) -> 0 | Y9: =IFERROR(G9-U9,0) -> 0 | Z9: =IFERROR(H9-V9,0) -> 0 | AA9: =I9-W9 -> 0 | AC9: =IF(OL!S$3=1,OL!S8,"") -> 0 | AD9: =IF(OL!T$3=1,OL!T8,"") -> 0 | AE9: =IF(OL!U$3=1,OL!U8,"") | AF9: =SUM(AC9:AE9) -> 0 | AG9: =IFERROR(F9-AC9,0) -> 0 | AH9: =IFERROR(G9-AD9,0) -> 0 | AI9: =IFERROR(H9-AE9,0) -> 0 | AJ9: =IFERROR(I9-AF9,0) -> 0 | AL9: =IF(LY!S$3=1,LY!S8,"") -> 0 | AM9: =IF(LY!T$3=1,LY!T8,"") | AN9: =IF(LY!U$3=1,LY!U8,"") | AO9: =SUM(AL9:AN9) -> 0 | AP9: =IFERROR(F9-AL9,0) -> 0 | AQ9: =IFERROR(G9-AM9,0) -> 0 | AR9: =IFERROR(H9-AN9,0) -> 0 | AS9: =IFERROR(I9-AO9,0) -> 0 | AU9: =Act!L8 -> 0 | AV9: =H9-AU9 -> #VALUE! | AX9: =IF('FC5+7'!S$3=1,'FC5+7'!S8,"") -> 0 | AY9: =IF('FC5+7'!T$3=1,'FC5+7'!T8,"") | AZ9: =IF('FC5+7'!U$3=1,'FC5+7'!U8,"") | BA9: =SUM(AX9:AZ9) -> 0 | BB9: =IFERROR(F9-AX9,0) -> 0 | BC9: =IFERROR(G9-AY9,0) -> 0 | BD9: =IFERROR(H9-AZ9,0) -> 0 | BE9: =IFERROR(I9-BA9,0) -> 0 | BG9: =F9 -> 0 | BH9: 0 | BI9: 0 | BJ9: =SUM(BG9:BI9) -> 0 | BK9: =IFERROR(F9-AC9,0) -> 0 | BL9: =IFERROR(G9-AD9,0) -> 0 | BM9: =IFERROR(AL9-AE9,0) -> 0 | BN9: =IFERROR(I9-BJ9,0) -> 0 | BP9: =F9 -> 0 | BQ9: =G9 | BR9: =#REF! -> #REF! | BS9: =SUM(BP9:BR9) -> #REF! | BT9: =BP9-AC9 -> 0 | BU9: =BQ9-AD9 -> #VALUE! | BV9: =BR9-AE9 -> #REF! | BW9: =BS9-AF9 -> #REF! | BY9: =H9-BR9 -> #VALUE! | CA9: ='FC2+10'!AA8 -> 0 | CC9: =CA9-I9 -> 0 | CE9: =IF('FC7+5'!S$3=1,'FC7+5'!S8,"") -> 0 | CF9: =IF('FC7+5'!T$3=1,'FC7+5'!T8,"") | CG9: =IF('FC7+5'!U$3=1,'FC7+5'!U8,"") | CH9: =SUM(CE9:CG9) -> 0 | CI9: =IFERROR(F9-CE9,0) -> 0 | CJ9: =IFERROR(G9-CF9,0) -> 0 | CK9: =IFERROR(H9-CG9,0) -> 0 | CL9: =IFERROR(I9-CH9,0) -> 0 | CM9: =IF('FC7+5'!AC$3=1,'FC7+5'!AC8,"") -> 0 | CN9: =I9-CM9 -> 0
C10: Retail sales volume (K units) - DATSUN | F10: =IF(Act!S$3=1,Act!S9,"") -> 0 | G10: =IF(Act!T$3=1,Act!T9,"") | H10: =IF(Act!U$3=1,Act!U9,"") | I10: =SUM(F10:H10) -> 0 | K10: =IF(BP!S$3=1,BP!S9,"") -> 0 | L10: =IF(BP!T$3=1,BP!T9,"") | M10: =IF(BP!U$3=1,BP!U9,"") | N10: =SUM(K10:M10) -> 0 | O10: =IFERROR(F10-K10,0) -> 0 | P10: =IFERROR(G10-L10,0) -> 0 | Q10: =IFERROR(H10-M10,0) -> 0 | R10: =F10-K10 -> 0 | T10: =IF('FC2+10'!S$3=1,'FC2+10'!S9,"") -> 0 | U10: =IF('FC2+10'!T$3=1,'FC2+10'!T9,"") | V10: =IF('FC2+10'!U$3=1,'FC2+10'!U9,"") | W10: =SUM(T10:V10) -> 0 | X10: =IFERROR(F10-T10,0) -> 0 | Y10: =IFERROR(G10-U10,0) -> 0 | Z10: =IFERROR(H10-V10,0) -> 0 | AA10: =I10-W10 -> 0 | AC10: =IF(OL!S$3=1,OL!S9,"") -> 0 | AD10: =IF(OL!T$3=1,OL!T9,"") -> 0 | AE10: =IF(OL!U$3=1,OL!U9,"") | AF10: =SUM(AC10:AE10) -> 0 | AG10: =IFERROR(F10-AC10,0) -> 0 | AH10: =IFERROR(G10-AD10,0) -> 0 | AI10: =IFERROR(H10-AE10,0) -> 0 | AJ10: =IFERROR(I10-AF10,0) -> 0 | AL10: =IF(LY!S$3=1,LY!S9,"") -> 0 | AM10: =IF(LY!T$3=1,LY!T9,"") | AN10: =IF(LY!U$3=1,LY!U9,"") | AO10: =SUM(AL10:AN10) -> 0 | AP10: =IFERROR(F10-AL10,0) -> 0 | AQ10: =IFERROR(G10-AM10,0) -> 0 | AR10: =IFERROR(H10-AN10,0) -> 0 | AS10: =IFERROR(I10-AO10,0) -> 0 | AU10: =Act!L9 -> 0 | AV10: =H10-AU10 -> #VALUE! | AX10: =IF('FC5+7'!S$3=1,'FC5+7'!S9,"") -> 0 | AY10: =IF('FC5+7'!T$3=1,'FC5+7'!T9,"") | AZ10: =IF('FC5+7'!U$3=1,'FC5+7'!U9,"") | BA10: =SUM(AX10:AZ10) -> 0 | BB10: =IFERROR(F10-AX10,0) -> 0 | BC10: =IFERROR(G10-AY10,0) -> 0 | BD10: =IFERROR(H10-AZ10,0) -> 0 | BE10: =IFERROR(I10-BA10,0) -> 0 | BG10: =F10 -> 0 | BH10: 0 | BI10: 0 | BJ10: =SUM(BG10:BI10) -> 0 | BK10: =IFERROR(F10-AC10,0) -> 0 | BL10: =IFERROR(G10-AD10,0) -> 0 | BM10: =IFERROR(AL10-AE10,0) -> 0 | BN10: =IFERROR(I10-BJ10,0) -> 0 | BP10: =F10 -> 0 | BQ10: =G10 | BR10: =#REF! -> #REF! | BS10: =SUM(BP10:BR10) -> #REF! | BT10: =BP10-AC10 -> 0 | BU10: =BQ10-AD10 -> #VALUE! | BV10: =BR10-AE10 -> #REF! | BW10: =BS10-AF10 -> #REF! | BY10: =H10-BR10 -> #VALUE! | CA10: ='FC2+10'!AA9 -> 0 | CC10: =CA10-I10 -> 0 | CE10: =IF('FC7+5'!S$3=1,'FC7+5'!S9,"") -> 0 | CF10: =IF('FC7+5'!T$3=1,'FC7+5'!T9,"") | CG10: =IF('FC7+5'!U$3=1,'FC7+5'!U9,"") | CH10: =SUM(CE10:CG10) -> 0 | CI10: =IFERROR(F10-CE10,0) -> 0 | CJ10: =IFERROR(G10-CF10,0) -> 0 | CK10: =IFERROR(H10-CG10,0) -> 0 | CL10: =IFERROR(I10-CH10,0) -> 0 | CM10: =IF('FC7+5'!AC$3=1,'FC7+5'!AC9,"") -> 0 | CN10: =I10-CM10 -> 0
C11: Wholesale volume (K units) To third party (Domestic) - NISSAN | F11: =IF(Act!S$3=1,Act!S10,"") -> 16.118 | G11: =IF(Act!T$3=1,Act!T10,"") | H11: =IF(Act!U$3=1,Act!U10,"") | I11: =SUM(F11:H11) -> 16.118 | K11: =IF(BP!S$3=1,BP!S10,"") -> 15.357 | L11: =IF(BP!T$3=1,BP!T10,"") | M11: =IF(BP!U$3=1,BP!U10,"") | N11: =SUM(K11:M11) -> 15.357 | O11: =IFERROR(F11-K11,0) -> 0.761 | P11: =IFERROR(G11-L11,0) -> 0 | Q11: =IFERROR(H11-M11,0) -> 0 | R11: =F11-K11 -> 0.761 | T11: =IF('FC2+10'!S$3=1,'FC2+10'!S10,"") -> 16.118 | U11: =IF('FC2+10'!T$3=1,'FC2+10'!T10,"") | V11: =IF('FC2+10'!U$3=1,'FC2+10'!U10,"") | W11: =SUM(T11:V11) -> 16.118 | X11: =IFERROR(F11-T11,0) -> 0 | Y11: =IFERROR(G11-U11,0) -> 0 | Z11: =IFERROR(H11-V11,0) -> 0 | AA11: =I11-W11 -> 0 | AC11: =IF(OL!S$3=1,OL!S10,"") -> 28.884 | AD11: =IF(OL!T$3=1,OL!T10,"") -> 32.724 | AE11: =IF(OL!U$3=1,OL!U10,"") | AF11: =SUM(AC11:AE11) -> 61.608 | AG11: =IFERROR(F11-AC11,0) -> -12.766 | AH11: =IFERROR(G11-AD11,0) -> 0 | AI11: =IFERROR(H11-AE11,0) -> 0 | AJ11: =IFERROR(I11-AF11,0) -> -45.49 | AL11: =IF(LY!S$3=1,LY!S10,"") -> 21.245 | AM11: =IF(LY!T$3=1,LY!T10,"") | AN11: =IF(LY!U$3=1,LY!U10,"") | AO11: =SUM(AL11:AN11) -> 21.245 | AP11: =IFERROR(F11-AL11,0) -> -5.127 | AQ11: =IFERROR(G11-AM11,0) -> 0 | AR11: =IFERROR(H11-AN11,0) -> 0 | AS11: =IFERROR(I11-AO11,0) -> -5.127 | AU11: =Act!L10 -> 31.667 | AV11: =H11-AU11 -> #VALUE! | AX11: =IF('FC5+7'!S$3=1,'FC5+7'!S10,"") -> 16.118 | AY11: =IF('FC5+7'!T$3=1,'FC5+7'!T10,"") | AZ11: =IF('FC5+7'!U$3=1,'FC5+7'!U10,"") | BA11: =SUM(AX11:AZ11) -> 16.118 | BB11: =IFERROR(F11-AX11,0) -> 0 | BC11: =IFERROR(G11-AY11,0) -> 0 | BD11: =IFERROR(H11-AZ11,0) -> 0 | BE11: =IFERROR(I11-BA11,0) -> 0 | BG11: =F11 -> 16.118 | BH11: 20.752 | BI11: 33.695 | BJ11: =SUM(BG11:BI11) -> 70.565 | BK11: =IFERROR(F11-AC11,0) -> -12.766 | BL11: =IFERROR(G11-AD11,0) -> 0 | BM11: =IFERROR(AL11-AE11,0) -> 0 | BN11: =IFERROR(I11-BJ11,0) -> -54.447 | BP11: =F11 -> 16.118 | BQ11: =G11 | BR11: =#REF! -> #REF! | BS11: =SUM(BP11:BR11) -> #REF! | BT11: =BP11-AC11 -> -12.766 | BU11: =BQ11-AD11 -> #VALUE! | BV11: =BR11-AE11 -> #REF! | BW11: =BS11-AF11 -> #REF! | BY11: =H11-BR11 -> #VALUE! | CA11: ='FC2+10'!AA10 -> 76.488 | CC11: =CA11-I11 -> 60.37 | CE11: =IF('FC7+5'!S$3=1,'FC7+5'!S10,"") -> 16.118 | CF11: =IF('FC7+5'!T$3=1,'FC7+5'!T10,"") | CG11: =IF('FC7+5'!U$3=1,'FC7+5'!U10,"") | CH11: =SUM(CE11:CG11) -> 16.118 | CI11: =IFERROR(F11-CE11,0) -> 0 | CJ11: =IFERROR(G11-CF11,0) -> 0 | CK11: =IFERROR(H11-CG11,0) -> 0 | CL11: =IFERROR(I11-CH11,0) -> 0 | CM11: =IF('FC7+5'!AC$3=1,'FC7+5'!AC10,"") -> 107.634 | CN11: =I11-CM11 -> -91.516
C12: Wholesale volume (K units) To third party (Domestic) - INFINITI | F12: =IF(Act!S$3=1,Act!S11,"") -> 0.007 | G12: =IF(Act!T$3=1,Act!T11,"") | H12: =IF(Act!U$3=1,Act!U11,"") | I12: =SUM(F12:H12) -> 0.007 | K12: =IF(BP!S$3=1,BP!S11,"") -> 0.009 | L12: =IF(BP!T$3=1,BP!T11,"") | M12: =IF(BP!U$3=1,BP!U11,"") | N12: =SUM(K12:M12) -> 0.009 | O12: =IFERROR(F12-K12,0) -> -0.002 | P12: =IFERROR(G12-L12,0) -> 0 | Q12: =IFERROR(H12-M12,0) -> 0 | R12: =F12-K12 -> -0.002 | T12: =IF('FC2+10'!S$3=1,'FC2+10'!S11,"") -> 0.007 | U12: =IF('FC2+10'!T$3=1,'FC2+10'!T11,"") | V12: =IF('FC2+10'!U$3=1,'FC2+10'!U11,"") | W12: =SUM(T12:V12) -> 0.007 | X12: =IFERROR(F12-T12,0) -> 0 | Y12: =IFERROR(G12-U12,0) -> 0 | Z12: =IFERROR(H12-V12,0) -> 0 | AA12: =I12-W12 -> 0 | AC12: =IF(OL!S$3=1,OL!S11,"") -> 0.002 | AD12: =IF(OL!T$3=1,OL!T11,"") -> 0 | AE12: =IF(OL!U$3=1,OL!U11,"") | AF12: =SUM(AC12:AE12) -> 0.002 | AG12: =IFERROR(F12-AC12,0) -> 0.005 | AH12: =IFERROR(G12-AD12,0) -> 0 | AI12: =IFERROR(H12-AE12,0) -> 0 | AJ12: =IFERROR(I12-AF12,0) -> 0.005 | AL12: =IF(LY!S$3=1,LY!S11,"") -> 0.008 | AM12: =IF(LY!T$3=1,LY!T11,"") | AN12: =IF(LY!U$3=1,LY!U11,"") | AO12: =SUM(AL12:AN12) -> 0.008 | AP12: =IFERROR(F12-AL12,0) -> -0.001 | AQ12: =IFERROR(G12-AM12,0) -> 0 | AR12: =IFERROR(H12-AN12,0) -> 0 | AS12: =IFERROR(I12-AO12,0) -> -0.001 | AU12: =Act!L11 -> 0 | AV12: =H12-AU12 -> #VALUE! | AX12: =IF('FC5+7'!S$3=1,'FC5+7'!S11,"") -> 0.007 | AY12: =IF('FC5+7'!T$3=1,'FC5+7'!T11,"") | AZ12: =IF('FC5+7'!U$3=1,'FC5+7'!U11,"") | BA12: =SUM(AX12:AZ12) -> 0.007 | BB12: =IFERROR(F12-AX12,0) -> 0 | BC12: =IFERROR(G12-AY12,0) -> 0 | BD12: =IFERROR(H12-AZ12,0) -> 0 | BE12: =IFERROR(I12-BA12,0) -> 0 | BG12: =F12 -> 0.007 | BH12: 0 | BI12: 0 | BJ12: =SUM(BG12:BI12) -> 0.007 | BK12: =IFERROR(F12-AC12,0) -> 0.005 | BL12: =IFERROR(G12-AD12,0) -> 0 | BM12: =IFERROR(AL12-AE12,0) -> 0 | BN12: =IFERROR(I12-BJ12,0) -> 0 | BP12: =F12 -> 0.007 | BQ12: =G12 | BR12: =#REF! -> #REF! | BS12: =SUM(BP12:BR12) -> #REF! | BT12: =BP12-AC12 -> 0.005 | BU12: =BQ12-AD12 -> #VALUE! | BV12: =BR12-AE12 -> #REF! | BW12: =BS12-AF12 -> #REF! | BY12: =H12-BR12 -> #VALUE! | CA12: ='FC2+10'!AA11 -> 0.032 | CC12: =CA12-I12 -> 0.025 | CE12: =IF('FC7+5'!S$3=1,'FC7+5'!S11,"") -> 0.007 | CF12: =IF('FC7+5'!T$3=1,'FC7+5'!T11,"") | CG12: =IF('FC7+5'!U$3=1,'FC7+5'!U11,"") | CH12: =SUM(CE12:CG12) -> 0.007 | CI12: =IFERROR(F12-CE12,0) -> 0 | CJ12: =IFERROR(G12-CF12,0) -> 0 | CK12: =IFERROR(H12-CG12,0) -> 0 | CL12: =IFERROR(I12-CH12,0) -> 0 | CM12: =IF('FC7+5'!AC$3=1,'FC7+5'!AC11,"") -> 0.061 | CN12: =I12-CM12 -> -0.054
C13: Wholesale volume (K units) To third party (Domestic) - DATSUN | F13: =IF(Act!S$3=1,Act!S12,"") -> 0 | G13: =IF(Act!T$3=1,Act!T12,"") | H13: =IF(Act!U$3=1,Act!U12,"") | I13: =SUM(F13:H13) -> 0 | K13: =IF(BP!S$3=1,BP!S12,"") -> 0 | L13: =IF(BP!T$3=1,BP!T12,"") | M13: =IF(BP!U$3=1,BP!U12,"") | N13: =SUM(K13:M13) -> 0 | O13: =IFERROR(F13-K13,0) -> 0 | P13: =IFERROR(G13-L13,0) -> 0 | Q13: =IFERROR(H13-M13,0) -> 0 | R13: =F13-K13 -> 0 | T13: =IF('FC2+10'!S$3=1,'FC2+10'!S12,"") -> 0 | U13: =IF('FC2+10'!T$3=1,'FC2+10'!T12,"") | V13: =IF('FC2+10'!U$3=1,'FC2+10'!U12,"") | W13: =SUM(T13:V13) -> 0 | X13: =IFERROR(F13-T13,0) -> 0 | Y13: =IFERROR(G13-U13,0) -> 0 | Z13: =IFERROR(H13-V13,0) -> 0 | AA13: =I13-W13 -> 0 | AC13: =IF(OL!S$3=1,OL!S12,"") -> 0 | AD13: =IF(OL!T$3=1,OL!T12,"") -> 0 | AE13: =IF(OL!U$3=1,OL!U12,"") | AF13: =SUM(AC13:AE13) -> 0 | AG13: =IFERROR(F13-AC13,0) -> 0 | AH13: =IFERROR(G13-AD13,0) -> 0 | AI13: =IFERROR(H13-AE13,0) -> 0 | AJ13: =IFERROR(I13-AF13,0) -> 0 | AL13: =IF(LY!S$3=1,LY!S12,"") -> 0 | AM13: =IF(LY!T$3=1,LY!T12,"") | AN13: =IF(LY!U$3=1,LY!U12,"") | AO13: =SUM(AL13:AN13) -> 0 | AP13: =IFERROR(F13-AL13,0) -> 0 | AQ13: =IFERROR(G13-AM13,0) -> 0 | AR13: =IFERROR(H13-AN13,0) -> 0 | AS13: =IFERROR(I13-AO13,0) -> 0 | AU13: =Act!L12 -> 0 | AV13: =H13-AU13 -> #VALUE! | AX13: =IF('FC5+7'!S$3=1,'FC5+7'!S12,"") -> 0 | AY13: =IF('FC5+7'!T$3=1,'FC5+7'!T12,"") | AZ13: =IF('FC5+7'!U$3=1,'FC5+7'!U12,"") | BA13: =SUM(AX13:AZ13) -> 0 | BB13: =IFERROR(F13-AX13,0) -> 0 | BC13: =IFERROR(G13-AY13,0) -> 0 | BD13: =IFERROR(H13-AZ13,0) -> 0 | BE13: =IFERROR(I13-BA13,0) -> 0 | BG13: =F13 -> 0 | BH13: 0 | BI13: 0 | BJ13: =SUM(BG13:BI13) -> 0 | BK13: =IFERROR(F13-AC13,0) -> 0 | BL13: =IFERROR(G13-AD13,0) -> 0 | BM13: =IFERROR(AL13-AE13,0) -> 0 | BN13: =IFERROR(I13-BJ13,0) -> 0 | BP13: =F13 -> 0 | BQ13: =G13 | BR13: =#REF! -> #REF! | BS13: =SUM(BP13:BR13) -> #REF! | BT13: =BP13-AC13 -> 0 | BU13: =BQ13-AD13 -> #VALUE! | BV13: =BR13-AE13 -> #REF! | BW13: =BS13-AF13 -> #REF! | BY13: =H13-BR13 -> #VALUE! | CA13: ='FC2+10'!AA12 -> 0 | CC13: =CA13-I13 -> 0 | CE13: =IF('FC7+5'!S$3=1,'FC7+5'!S12,"") -> 0 | CF13: =IF('FC7+5'!T$3=1,'FC7+5'!T12,"") | CG13: =IF('FC7+5'!U$3=1,'FC7+5'!U12,"") | CH13: =SUM(CE13:CG13) -> 0 | CI13: =IFERROR(F13-CE13,0) -> 0 | CJ13: =IFERROR(G13-CF13,0) -> 0 | CK13: =IFERROR(H13-CG13,0) -> 0 | CL13: =IFERROR(I13-CH13,0) -> 0 | CM13: =IF('FC7+5'!AC$3=1,'FC7+5'!AC12,"") -> 0 | CN13: =I13-CM13 -> 0
C14: Wholesale volume (K units) To third party (Export) | F14: =IF(Act!S$3=1,Act!S13,"") -> 0.481 | G14: =IF(Act!T$3=1,Act!T13,"") | H14: =IF(Act!U$3=1,Act!U13,"") | I14: =SUM(F14:H14) -> 0.481 | K14: =IF(BP!S$3=1,BP!S13,"") -> 1.062 | L14: =IF(BP!T$3=1,BP!T13,"") | M14: =IF(BP!U$3=1,BP!U13,"") | N14: =SUM(K14:M14) -> 1.062 | O14: =IFERROR(F14-K14,0) -> -0.581 | P14: =IFERROR(G14-L14,0) -> 0 | Q14: =IFERROR(H14-M14,0) -> 0 | R14: =F14-K14 -> -0.581 | T14: =IF('FC2+10'!S$3=1,'FC2+10'!S13,"") -> 0.481 | U14: =IF('FC2+10'!T$3=1,'FC2+10'!T13,"") | V14: =IF('FC2+10'!U$3=1,'FC2+10'!U13,"") | W14: =SUM(T14:V14) -> 0.481 | X14: =IFERROR(F14-T14,0) -> 0 | Y14: =IFERROR(G14-U14,0) -> 0 | Z14: =IFERROR(H14-V14,0) -> 0 | AA14: =I14-W14 -> 0 | AC14: =IF(OL!S$3=1,OL!S13,"") -> 0.349 | AD14: =IF(OL!T$3=1,OL!T13,"") -> 0.867 | AE14: =IF(OL!U$3=1,OL!U13,"") | AF14: =SUM(AC14:AE14) -> 1.216 | AG14: =IFERROR(F14-AC14,0) -> 0.132 | AH14: =IFERROR(G14-AD14,0) -> 0 | AI14: =IFERROR(H14-AE14,0) -> 0 | AJ14: =IFERROR(I14-AF14,0) -> -0.735 | AL14: =IF(LY!S$3=1,LY!S13,"") -> 1.903 | AM14: =IF(LY!T$3=1,LY!T13,"") | AN14: =IF(LY!U$3=1,LY!U13,"") | AO14: =SUM(AL14:AN14) -> 1.903 | AP14: =IFERROR(F14-AL14,0) -> -1.422 | AQ14: =IFERROR(G14-AM14,0) -> 0 | AR14: =IFERROR(H14-AN14,0) -> 0 | AS14: =IFERROR(I14-AO14,0) -> -1.422 | AU14: =Act!L13 -> 0.625 | AV14: =H14-AU14 -> #VALUE! | AX14: =IF('FC5+7'!S$3=1,'FC5+7'!S13,"") -> 0.481 | AY14: =IF('FC5+7'!T$3=1,'FC5+7'!T13,"") | AZ14: =IF('FC5+7'!U$3=1,'FC5+7'!U13,"") | BA14: =SUM(AX14:AZ14) -> 0.481 | BB14: =IFERROR(F14-AX14,0) -> 0 | BC14: =IFERROR(G14-AY14,0) -> 0 | BD14: =IFERROR(H14-AZ14,0) -> 0 | BE14: =IFERROR(I14-BA14,0) -> 0 | BG14: =F14 -> 0.481 | BH14: 0.867 | BI14: 1.045 | BJ14: =SUM(BG14:BI14) -> 2.393 | BK14: =IFERROR(F14-AC14,0) -> 0.132 | BL14: =IFERROR(G14-AD14,0) -> 0 | BM14: =IFERROR(AL14-AE14,0) -> 0 | BN14: =IFERROR(I14-BJ14,0) -> -1.912 | BP14: =F14 -> 0.481 | BQ14: =G14 | BR14: =#REF! -> #REF! | BS14: =SUM(BP14:BR14) -> #REF! | BT14: =BP14-AC14 -> 0.132 | BU14: =BQ14-AD14 -> #VALUE! | BV14: =BR14-AE14 -> #REF! | BW14: =BS14-AF14 -> #REF! | BY14: =H14-BR14 -> #VALUE! | CA14: ='FC2+10'!AA13 -> 2.686 | CC14: =CA14-I14 -> 2.205 | CE14: =IF('FC7+5'!S$3=1,'FC7+5'!S13,"") -> 0.481 | CF14: =IF('FC7+5'!T$3=1,'FC7+5'!T13,"") | CG14: =IF('FC7+5'!U$3=1,'FC7+5'!U13,"") | CH14: =SUM(CE14:CG14) -> 0.481 | CI14: =IFERROR(F14-CE14,0) -> 0 | CJ14: =IFERROR(G14-CF14,0) -> 0 | CK14: =IFERROR(H14-CG14,0) -> 0 | CL14: =IFERROR(I14-CH14,0) -> 0 | CM14: =IF('FC7+5'!AC$3=1,'FC7+5'!AC13,"") -> 2.384 | CN14: =I14-CM14 -> -1.903
BT15: =BP15-AC15 -> 0 | BU15: =BQ15-AD15 -> 0 | BV15: =BR15-AE15 -> 0 | BW15: =BS15-AF15 -> 0 | CC15: =CA15-I15 -> 0
BT16: =BP16-AC16 -> 0 | BU16: =BQ16-AD16 -> 0 | BV16: =BR16-AE16 -> 0 | BW16: =BS16-AF16 -> 0 | CC16: =CA16-I16 -> 0
D17: Gross Sales - New Vehicle (M&S function scope) | O17: =IFERROR(F17-K17,0) -> 0 | P17: =IFERROR(G17-L17,0) -> 0 | Q17: =IFERROR(H17-M17,0) -> 0 | R17: =I17-N17 -> 0 | X17: =IFERROR(F17-T17,0) -> 0 | Y17: =IFERROR(G17-U17,0) -> 0 | Z17: =IFERROR(H17-V17,0) -> 0 | AA17: =I17-W17 -> 0 | AE17: 0 | AG17: =IFERROR(F17-AC17,0) -> 0 | AH17: =IFERROR(G17-AD17,0) -> 0 | AI17: =IFERROR(H17-AE17,0) -> 0 | AJ17: =IFERROR(I17-AF17,0) -> 0 | AP17: =IFERROR(F17-AL17,0) -> 0 | AQ17: =IFERROR(G17-AM17,0) -> 0 | AR17: =IFERROR(H17-AN17,0) -> 0 | AS17: =IFERROR(I17-AO17,0) -> 0 | AU17: =Act!L16 -> 0 | AV17: =H17-AU17 -> 0 | BB17: =IFERROR(F17-AX17,0) -> 0 | BC17: =IFERROR(G17-AY17,0) -> 0 | BD17: =IFERROR(H17-AZ17,0) -> 0 | BE17: =IFERROR(I17-BA17,0) -> 0 | BG17: =F17 -> 0 | BK17: =IFERROR(F17-AC17,0) -> 0 | BL17: =IFERROR(G17-AD17,0) -> 0 | BM17: =IFERROR(AL17-AE17,0) -> 0 | BN17: =IFERROR(I17-BJ17,0) -> 0 | BP17: =F17 -> 0 | BQ17: =G17 -> 0 | BR17: =#REF! -> #REF! | BT17: =BP17-AC17 -> 0 | BU17: =BQ17-AD17 -> 0 | BV17: =BR17-AE17 -> #REF! | BW17: =BS17-AF17 -> 0 | BY17: =H17-BR17 -> #REF! | CA17: ='FC2+10'!AA16 -> 0 | CC17: =CA17-I17 -> 0 | CI17: =IFERROR(F17-CE17,0) -> 0 | CJ17: =IFERROR(G17-CF17,0) -> 0 | CK17: =IFERROR(H17-CG17,0) -> 0 | CL17: =IFERROR(I17-CH17,0) -> 0 | CN17: =I17-CM17 -> 0
D18: Gross Sales - Other External sales | O18: =IFERROR(F18-K18,0) -> 0 | P18: =IFERROR(G18-L18,0) -> 0 | Q18: =IFERROR(H18-M18,0) -> 0 | R18: =I18-N18 -> 0 | X18: =IFERROR(F18-T18,0) -> 0 | Y18: =IFERROR(G18-U18,0) -> 0 | Z18: =IFERROR(H18-V18,0) -> 0 | AA18: =I18-W18 -> 0 | AE18: 0 | AG18: =IFERROR(F18-AC18,0) -> 0 | AH18: =IFERROR(G18-AD18,0) -> 0 | AI18: =IFERROR(H18-AE18,0) -> 0 | AJ18: =IFERROR(I18-AF18,0) -> 0 | AP18: =IFERROR(F18-AL18,0) -> 0 | AQ18: =IFERROR(G18-AM18,0) -> 0 | AR18: =IFERROR(H18-AN18,0) -> 0 | AS18: =IFERROR(I18-AO18,0) -> 0 | AU18: =Act!L17 -> 0 | AV18: =H18-AU18 -> 0 | BB18: =IFERROR(F18-AX18,0) -> 0 | BC18: =IFERROR(G18-AY18,0) -> 0 | BD18: =IFERROR(H18-AZ18,0) -> 0 | BE18: =IFERROR(I18-BA18,0) -> 0 | BG18: =F18 -> 0 | BK18: =IFERROR(F18-AC18,0) -> 0 | BL18: =IFERROR(G18-AD18,0) -> 0 | BM18: =IFERROR(AL18-AE18,0) -> 0 | BN18: =IFERROR(I18-BJ18,0) -> 0 | BP18: =F18 -> 0 | BQ18: =G18 -> 0 | BR18: =#REF! -> #REF! | BT18: =BP18-AC18 -> 0 | BU18: =BQ18-AD18 -> 0 | BV18: =BR18-AE18 -> #REF! | BW18: =BS18-AF18 -> 0 | BY18: =H18-BR18 -> #REF! | CA18: ='FC2+10'!AA17 -> 0 | CC18: =CA18-I18 -> 0 | CI18: =IFERROR(F18-CE18,0) -> 0 | CJ18: =IFERROR(G18-CF18,0) -> 0 | CK18: =IFERROR(H18-CG18,0) -> 0 | CL18: =IFERROR(I18-CH18,0) -> 0 | CN18: =I18-CM18 -> 0
B19: Gross Sales | F19: =IF(Act!S$3=1,Act!S18,"") -> 612.22646 | G19: =IF(Act!T$3=1,Act!T18,"") | H19: =IF(Act!U$3=1,Act!U18,"") | I19: =SUM(F19:H19) -> 612.22646 | K19: =IF(BP!S$3=1,BP!S18,"") -> 647.19888 | L19: =IF(BP!T$3=1,BP!T18,"") | M19: =IF(BP!U$3=1,BP!U18,"") | N19: =SUM(K19:M19) -> 647.19888 | O19: =IFERROR(F19-K19,0) -> -34.972416 | P19: =IFERROR(G19-L19,0) -> 0 | Q19: =IFERROR(H19-M19,0) -> 0 | R19: =I19-N19 -> -34.972416 | T19: =IF('FC2+10'!S$3=1,'FC2+10'!S18,"") -> 612.22646 | U19: =IF('FC2+10'!T$3=1,'FC2+10'!T18,"") | V19: =IF('FC2+10'!U$3=1,'FC2+10'!U18,"") | W19: =SUM(T19:V19) -> 612.22646 | X19: =IFERROR(F19-T19,0) -> 0 | Y19: =IFERROR(G19-U19,0) -> 0 | Z19: =IFERROR(H19-V19,0) -> 0 | AA19: =I19-W19 -> 0 | AC19: =IF(OL!S$3=1,OL!S18,"") -> 867.43498 | AD19: =IF(OL!T$3=1,OL!T18,"") -> 998.88562 | AE19: =IF(OL!U$3=1,OL!U18,"") | AF19: =SUM(AC19:AE19) -> 1866.3206 | AG19: =IFERROR(F19-AC19,0) -> -255.20852 | AH19: =IFERROR(G19-AD19,0) -> 0 | AI19: =IFERROR(H19-AE19,0) -> 0 | AJ19: =IFERROR(I19-AF19,0) -> -1254.0941 | AL19: =IF(LY!S$3=1,LY!S18,"") -> 750.84895 | AM19: =IF(LY!T$3=1,LY!T18,"") | AN19: =IF(LY!U$3=1,LY!U18,"") | AO19: =SUM(AL19:AN19) -> 750.84895 | AP19: =IFERROR(F19-AL19,0) -> -138.62249 | AQ19: =IFERROR(G19-AM19,0) -> 0 | AR19: =IFERROR(H19-AN19,0) -> 0 | AS19: =IFERROR(I19-AO19,0) -> -138.62249 | AU19: =Act!L18 -> 972.88696 | AV19: =H19-AU19 -> #VALUE! | AX19: =IF('FC5+7'!S$3=1,'FC5+7'!S18,"") -> 612.22646 | AY19: =IF('FC5+7'!T$3=1,'FC5+7'!T18,"") | AZ19: =IF('FC5+7'!U$3=1,'FC5+7'!U18,"") | BA19: =SUM(AX19:AZ19) -> 612.22646 | BB19: =IFERROR(F19-AX19,0) -> 0 | BC19: =IFERROR(G19-AY19,0) -> 0 | BD19: =IFERROR(H19-AZ19,0) -> 0 | BE19: =IFERROR(I19-BA19,0) -> 0 | BG19: =F19 -> 612.22646 | BH19: 710.14442 | BI19: 1097.4923 | BJ19: =SUM(BG19:BI19) -> 2419.8632 | BK19: =IFERROR(F19-AC19,0) -> -255.20852 | BL19: =IFERROR(G19-AD19,0) -> 0 | BM19: =IFERROR(AL19-AE19,0) -> 0 | BN19: =IFERROR(I19-BJ19,0) -> -1807.6367 | BP19: =F19 -> 612.22646 | BQ19: =G19 | BR19: =#REF! -> #REF! | BS19: =SUM(BP19:BR19) -> #REF! | BT19: =BP19-AC19 -> -255.20852 | BU19: =BQ19-AD19 -> #VALUE! | BV19: =BR19-AE19 -> #REF! | BW19: =BS19-AF19 -> #REF! | BY19: =H19-BR19 -> #VALUE! | CA19: ='FC2+10'!AA18 -> 2654.6861 | CC19: =CA19-I19 -> 2042.4597 | CE19: =IF('FC7+5'!S$3=1,'FC7+5'!S18,"") -> 612.22646 | CF19: =IF('FC7+5'!T$3=1,'FC7+5'!T18,"") | CG19: =IF('FC7+5'!U$3=1,'FC7+5'!U18,"") | CH19: =SUM(CE19:CG19) -> 612.22646 | CI19: =IFERROR(F19-CE19,0) -> 0 | CJ19: =IFERROR(G19-CF19,0) -> 0 | CK19: =IFERROR(H19-CG19,0) -> 0 | CL19: =IFERROR(I19-CH19,0) -> 0 | CM19: =IF('FC7+5'!AC$3=1,'FC7+5'!AC18,"") -> 3313.6771 | CN19: =I19-CM19 -> -2701.4507
D20: VME - New Vehicle (M&S function scope) | O20: =IFERROR(F20-K20,0) -> 0 | P20: =IFERROR(G20-L20,0) -> 0 | Q20: =IFERROR(H20-M20,0) -> 0 | R20: =I20-N20 -> 0 | X20: =IFERROR(F20-T20,0) -> 0 | Y20: =IFERROR(G20-U20,0) -> 0 | Z20: =IFERROR(H20-V20,0) -> 0 | AA20: =I20-W20 -> 0 | AE20: 0 | AG20: =IFERROR(F20-AC20,0) -> 0 | AH20: =IFERROR(G20-AD20,0) -> 0 | AI20: =IFERROR(H20-AE20,0) -> 0 | AJ20: =IFERROR(I20-AF20,0) -> 0 | AP20: =IFERROR(F20-AL20,0) -> 0 | AQ20: =IFERROR(G20-AM20,0) -> 0 | AR20: =IFERROR(H20-AN20,0) -> 0 | AS20: =IFERROR(I20-AO20,0) -> 0 | AU20: =Act!L19 -> 0 | AV20: =H20-AU20 -> 0 | BB20: =IFERROR(F20-AX20,0) -> 0 | BC20: =IFERROR(G20-AY20,0) -> 0 | BD20: =IFERROR(H20-AZ20,0) -> 0 | BE20: =IFERROR(I20-BA20,0) -> 0 | BG20: =F20 -> 0 | BK20: =IFERROR(F20-AC20,0) -> 0 | BN20: =IFERROR(I20-BJ20,0) -> 0 | BT20: =BP20-AC20 -> 0 | BU20: =BQ20-AD20 -> 0 | BV20: =BR20-AE20 -> 0 | BW20: =BS20-AF20 -> 0 | BY20: =H20-BR20 -> 0 | CA20: ='FC2+10'!AA19 -> 0 | CC20: =CA20-I20 -> 0 | CI20: =IFERROR(F20-CE20,0) -> 0 | CJ20: =IFERROR(G20-CF20,0) -> 0 | CK20: =IFERROR(H20-CG20,0) -> 0 | CL20: =IFERROR(I20-CH20,0) -> 0 | CN20: =I20-CM20 -> 0
D21: VME - Other | O21: =IFERROR(F21-K21,0) -> 0 | P21: =IFERROR(G21-L21,0) -> 0 | Q21: =IFERROR(H21-M21,0) -> 0 | R21: =I21-N21 -> 0 | X21: =IFERROR(F21-T21,0) -> 0 | Y21: =IFERROR(G21-U21,0) -> 0 | Z21: =IFERROR(H21-V21,0) -> 0 | AA21: =I21-W21 -> 0 | AE21: 0 | AG21: =IFERROR(F21-AC21,0) -> 0 | AH21: =IFERROR(G21-AD21,0) -> 0 | AI21: =IFERROR(H21-AE21,0) -> 0 | AJ21: =IFERROR(I21-AF21,0) -> 0 | AP21: =IFERROR(F21-AL21,0) -> 0 | AQ21: =IFERROR(G21-AM21,0) -> 0 | AR21: =IFERROR(H21-AN21,0) -> 0 | AS21: =IFERROR(I21-AO21,0) -> 0 | AU21: =Act!L20 -> 0 | AV21: =H21-AU21 -> 0 | BB21: =IFERROR(F21-AX21,0) -> 0 | BC21: =IFERROR(G21-AY21,0) -> 0 | BD21: =IFERROR(H21-AZ21,0) -> 0 | BE21: =IFERROR(I21-BA21,0) -> 0 | BG21: =F21 -> 0 | BK21: =IFERROR(F21-AC21,0) -> 0 | BN21: =IFERROR(I21-BJ21,0) -> 0 | BT21: =BP21-AC21 -> 0 | BU21: =BQ21-AD21 -> 0 | BV21: =BR21-AE21 -> 0 | BW21: =BS21-AF21 -> 0 | BY21: =H21-BR21 -> 0 | CA21: ='FC2+10'!AA20 -> 0 | CC21: =CA21-I21 -> 0 | CI21: =IFERROR(F21-CE21,0) -> 0 | CJ21: =IFERROR(G21-CF21,0) -> 0 | CK21: =IFERROR(H21-CG21,0) -> 0 | CL21: =IFERROR(I21-CH21,0) -> 0 | CN21: =I21-CM21 -> 0
C22: VME Total | F22: =IF(Act!S$3=1,Act!S21,"") -> -85.285283 | G22: =IF(Act!T$3=1,Act!T21,"") | H22: =IF(Act!U$3=1,Act!U21,"") | I22: =SUM(F22:H22) -> -85.285283 | K22: =IF(BP!S$3=1,BP!S21,"") -> -76.406511 | L22: =IF(BP!T$3=1,BP!T21,"") | M22: =IF(BP!U$3=1,BP!U21,"") | N22: =SUM(K22:M22) -> -76.406511 | O22: =IFERROR(F22-K22,0) -> -8.8787725 | P22: =IFERROR(G22-L22,0) -> 0 | Q22: =IFERROR(H22-M22,0) -> 0 | R22: =I22-N22 -> -8.8787725 | T22: =IF('FC2+10'!S$3=1,'FC2+10'!S21,"") -> -85.285283 | U22: =IF('FC2+10'!T$3=1,'FC2+10'!T21,"") | V22: =IF('FC2+10'!U$3=1,'FC2+10'!U21,"") | W22: =SUM(T22:V22) -> -85.285283 | X22: =IFERROR(F22-T22,0) -> 0 | Y22: =IFERROR(G22-U22,0) -> 0 | Z22: =IFERROR(H22-V22,0) -> 0 | AA22: =I22-W22 -> 0 | AC22: =IF(OL!S$3=1,OL!S21,"") -> -134.42478 | AD22: =IF(OL!T$3=1,OL!T21,"") -> -142.08356 | AE22: =IF(OL!U$3=1,OL!U21,"") | AF22: =SUM(AC22:AE22) -> -276.50834 | AG22: =IFERROR(F22-AC22,0) -> 49.139495 | AH22: =IFERROR(G22-AD22,0) -> 0 | AI22: =IFERROR(H22-AE22,0) -> 0 | AJ22: =IFERROR(I22-AF22,0) -> 191.22306 | AL22: =IF(LY!S$3=1,LY!S21,"") -> -97.808222 | AM22: =IF(LY!T$3=1,LY!T21,"") | AN22: =IF(LY!U$3=1,LY!U21,"") | AO22: =SUM(AL22:AN22) -> -97.808222 | AP22: =IFERROR(F22-AL22,0) -> 12.522939 | AQ22: =IFERROR(G22-AM22,0) -> 0 | AR22: =IFERROR(H22-AN22,0) -> 0 | AS22: =IFERROR(I22-AO22,0) -> 12.522939 | AU22: =Act!L21 -> -142.95643 | AV22: =H22-AU22 -> #VALUE! | AX22: =IF('FC5+7'!S$3=1,'FC5+7'!S21,"") -> -85.285283 | AY22: =IF('FC5+7'!T$3=1,'FC5+7'!T21,"") | AZ22: =IF('FC5+7'!U$3=1,'FC5+7'!U21,"") | BA22: =SUM(AX22:AZ22) -> -85.285283 | BB22: =IFERROR(F22-AX22,0) -> 0 | BC22: =IFERROR(G22-AY22,0) -> 0 | BD22: =IFERROR(H22-AZ22,0) -> 0 | BE22: =IFERROR(I22-BA22,0) -> 0 | BG22: =F22 -> -85.285283 | BH22: -95.106208 | BI22: -169.78057 | BJ22: =SUM(BG22:BI22) -> -350.17207 | BK22: =IFERROR(F22-AC22,0) -> 49.139495 | BL22: =IFERROR(G22-AD22,0) -> 0 | BM22: =IFERROR(AL22-AE22,0) -> 0 | BN22: =IFERROR(I22-BJ22,0) -> 264.88678 | BP22: =F22 -> -85.285283 | BQ22: =G22 | BR22: =#REF! -> #REF! | BS22: =SUM(BP22:BR22) -> #REF! | BT22: =BP22-AC22 -> 49.139495 | BU22: =BQ22-AD22 -> #VALUE! | BV22: =BR22-AE22 -> #REF! | BW22: =BS22-AF22 -> #REF! | BY22: =H22-BR22 -> #VALUE! | CA22: ='FC2+10'!AA21 -> -372.76108 | CC22: =CA22-I22 -> -287.4758 | CE22: =IF('FC7+5'!S$3=1,'FC7+5'!S21,"") -> -85.285283 | CF22: =IF('FC7+5'!T$3=1,'FC7+5'!T21,"") | CG22: =IF('FC7+5'!U$3=1,'FC7+5'!U21,"") | CH22: =SUM(CE22:CG22) -> -85.285283 | CI22: =IFERROR(F22-CE22,0) -> 0 | CJ22: =IFERROR(G22-CF22,0) -> 0 | CK22: =IFERROR(H22-CG22,0) -> 0 | CL22: =IFERROR(I22-CH22,0) -> 0 | CM22: =IF('FC7+5'!AC$3=1,'FC7+5'!AC21,"") -> -481.20338 | CN22: =I22-CM22 -> 395.9181
B23: Net Sales | F23: =SUM(F19,F22) -> 526.94118 | G23: =SUM(G19,G22) -> 0 | H23: =SUM(H19,H22) -> 0 | I23: =SUM(F23:H23) -> 526.94118 | K23: =SUM(K19,K22) -> 570.79237 | L23: =SUM(L19,L22) -> 0 | M23: =SUM(M19,M22) -> 0 | N23: =SUM(K23:M23) -> 570.79237 | O23: =IFERROR(F23-K23,0) -> -43.851189 | P23: =IFERROR(G23-L23,0) -> 0 | Q23: =IFERROR(H23-M23,0) -> 0 | R23: =I23-N23 -> -43.851189 | T23: =SUM(T19,T22) -> 526.94118 | U23: =SUM(U19,U22) -> 0 | V23: =SUM(V19,V22) -> 0 | W23: =SUM(T23:V23) -> 526.94118 | X23: =IFERROR(F23-T23,0) -> 0 | Y23: =IFERROR(G23-U23,0) -> 0 | Z23: =IFERROR(H23-V23,0) -> 0 | AA23: =I23-W23 -> 0 | AC23: =SUM(AC19,AC22) -> 733.0102 | AD23: =SUM(AD19,AD22) -> 856.80206 | AE23: =SUM(AE19,AE22) -> 0 | AF23: =SUM(AC23:AE23) -> 1589.8123 | AG23: =IFERROR(F23-AC23,0) -> -206.06903 | AH23: =IFERROR(G23-AD23,0) -> -856.80206 | AI23: =IFERROR(H23-AE23,0) -> 0 | AJ23: =IFERROR(I23-AF23,0) -> -1062.8711 | AL23: =SUM(AL19,AL22) -> 653.04073 | AM23: =SUM(AM19,AM22) -> 0 | AN23: =SUM(AN19,AN22) -> 0 | AO23: =SUM(AL23:AN23) -> 653.04073 | AP23: =IFERROR(F23-AL23,0) -> -126.09955 | AQ23: =IFERROR(G23-AM23,0) -> 0 | AR23: =IFERROR(H23-AN23,0) -> 0 | AS23: =IFERROR(I23-AO23,0) -> -126.09955 | AU23: =Act!L22 -> 829.93053 | AV23: =H23-AU23 -> -829.93053 | AX23: =SUM(AX19,AX22) -> 526.94118 | AY23: =SUM(AY19,AY22) -> 0 | AZ23: =SUM(AZ19,AZ22) -> 0 | BA23: =SUM(AX23:AZ23) -> 526.94118 | BB23: =IFERROR(F23-AX23,0) -> 0 | BC23: =IFERROR(G23-AY23,0) -> 0 | BD23: =IFERROR(H23-AZ23,0) -> 0 | BE23: =IFERROR(I23-BA23,0) -> 0 | BG23: =F23 -> 526.94118 | BH23: 615.03821 | BI23: 927.71175 | BJ23: =SUM(BG23:BI23) -> 2069.6911 | BK23: =IFERROR(F23-AC23,0) -> -206.06903 | BL23: =IFERROR(G23-AD23,0) -> -856.80206 | BM23: =IFERROR(AL23-AE23,0) -> 653.04073 | BN23: =IFERROR(I23-BJ23,0) -> -1542.75 | BP23: =F23 -> 526.94118 | BQ23: =G23 -> 0 | BR23: =#REF! -> #REF! | BS23: =SUM(BP23:BR23) -> #REF! | BT23: =BP23-AC23 -> -206.06903 | BU23: =BQ23-AD23 -> -856.80206 | BV23: =BR23-AE23 -> #REF! | BW23: =BS23-AF23 -> #REF! | BY23: =H23-BR23 -> #REF! | CA23: ='FC2+10'!AA22 -> 2281.9251 | CC23: =CA23-I23 -> 1754.9839 | CE23: =SUM(CE19,CE22) -> 526.94118 | CF23: =SUM(CF19,CF22) -> 0 | CG23: =SUM(CG19,CG22) -> 0 | CH23: =SUM(CE23:CG23) -> 526.94118 | CI23: =IFERROR(F23-CE23,0) -> 0 | CJ23: =IFERROR(G23-CF23,0) -> 0 | CK23: =IFERROR(H23-CG23,0) -> 0 | CL23: =IFERROR(I23-CH23,0) -> 0 | CM23: =SUM(CM19,CM22) -> 2832.4737 | CN23: =I23-CM23 -> -2305.5326
D24: @Std. Cost | O24: =IFERROR(F24-K24,0) -> 0 | P24: =IFERROR(G24-L24,0) -> 0 | Q24: =IFERROR(H24-M24,0) -> 0 | R24: =I24-N24 -> 0 | X24: =IFERROR(F24-T24,0) -> 0 | Y24: =IFERROR(G24-U24,0) -> 0 | Z24: =IFERROR(H24-V24,0) -> 0 | AA24: =I24-W24 -> 0 | AE24: 0 | AG24: =IFERROR(F24-AC24,0) -> 0 | AH24: =IFERROR(G24-AD24,0) -> 0 | AI24: =IFERROR(H24-AE24,0) -> 0 | AJ24: =IFERROR(I24-AF24,0) -> 0 | AP24: =IFERROR(F24-AL24,0) -> 0 | AQ24: =IFERROR(G24-AM24,0) -> 0 | AR24: =IFERROR(H24-AN24,0) -> 0 | AS24: =IFERROR(I24-AO24,0) -> 0 | AU24: =Act!L23 -> 0 | AV24: =H24-AU24 -> 0 | BN24: =IFERROR(I24-BJ24,0) -> 0 | BT24: =BP24-AC24 -> 0 | BU24: =BQ24-AD24 -> 0 | BV24: =BR24-AE24 -> 0 | BW24: =BS24-AF24 -> 0 | BY24: =H24-BR24 -> 0 | CA24: ='FC2+10'!AA23 -> 0 | CC24: =CA24-I24 -> 0 | CN24: =I24-CM24 -> 0
D25: Other MFG variable | O25: =IFERROR(F25-K25,0) -> 0 | P25: =IFERROR(G25-L25,0) -> 0 | Q25: =IFERROR(H25-M25,0) -> 0 | R25: =I25-N25 -> 0 | X25: =IFERROR(F25-T25,0) -> 0 | Y25: =IFERROR(G25-U25,0) -> 0 | Z25: =IFERROR(H25-V25,0) -> 0 | AA25: =I25-W25 -> 0 | AE25: 0 | AG25: =IFERROR(F25-AC25,0) -> 0 | AH25: =IFERROR(G25-AD25,0) -> 0 | AI25: =IFERROR(H25-AE25,0) -> 0 | AJ25: =IFERROR(I25-AF25,0) -> 0 | AP25: =IFERROR(F25-AL25,0) -> 0 | AQ25: =IFERROR(G25-AM25,0) -> 0 | AR25: =IFERROR(H25-AN25,0) -> 0 | AS25: =IFERROR(I25-AO25,0) -> 0 | AU25: =Act!L24 -> 0 | AV25: =H25-AU25 -> 0 | BN25: =IFERROR(I25-BJ25,0) -> 0 | BT25: =BP25-AC25 -> 0 | BU25: =BQ25-AD25 -> 0 | BV25: =BR25-AE25 -> 0 | BW25: =BS25-AF25 -> 0 | BY25: =H25-BR25 -> 0 | CA25: ='FC2+10'!AA24 -> 0 | CC25: =CA25-I25 -> 0 | CN25: =I25-CM25 -> 0
C26: Parts / Materials and Others | F26: =IF(Act!S$3=1,Act!S25,"") -> -440.85756 | G26: =IF(Act!T$3=1,Act!T25,"") | H26: =IF(Act!U$3=1,Act!U25,"") | I26: =SUM(F26:H26) -> -440.85756 | K26: =IF(BP!S$3=1,BP!S25,"") -> -483.27574 | L26: =IF(BP!T$3=1,BP!T25,"") | M26: =IF(BP!U$3=1,BP!U25,"") | N26: =SUM(K26:M26) -> -483.27574 | O26: =IFERROR(F26-K26,0) -> 42.418181 | P26: =IFERROR(G26-L26,0) -> 0 | Q26: =IFERROR(H26-M26,0) -> 0 | R26: =I26-N26 -> 42.418181 | T26: =IF('FC2+10'!S$3=1,'FC2+10'!S25,"") -> #VALUE! | U26: =IF('FC2+10'!T$3=1,'FC2+10'!T25,"") | V26: =IF('FC2+10'!U$3=1,'FC2+10'!U25,"") | W26: =SUM(T26:V26) -> #VALUE! | X26: =IFERROR(F26-T26,0) -> 0 | Y26: =IFERROR(G26-U26,0) -> 0 | Z26: =IFERROR(H26-V26,0) -> 0 | AA26: =I26-W26 -> #VALUE! | AC26: =IF(OL!S$3=1,OL!S25,"") -> -588.72719 | AD26: =IF(OL!T$3=1,OL!T25,"") -> -715.65292 | AE26: =IF(OL!U$3=1,OL!U25,"") | AF26: =SUM(AC26:AE26) -> -1304.3801 | AG26: =IFERROR(F26-AC26,0) -> 147.86963 | AH26: =IFERROR(G26-AD26,0) -> 0 | AI26: =IFERROR(H26-AE26,0) -> 0 | AJ26: =IFERROR(I26-AF26,0) -> 863.52256 | AL26: =IF(LY!S$3=1,LY!S25,"") -> -496.47291 | AM26: =IF(LY!T$3=1,LY!T25,"") | AN26: =IF(LY!U$3=1,LY!U25,"") | AO26: =SUM(AL26:AN26) -> -496.47291 | AP26: =IFERROR(F26-AL26,0) -> 55.615353 | AQ26: =IFERROR(G26-AM26,0) -> 0 | AR26: =IFERROR(H26-AN26,0) -> 0 | AS26: =IFERROR(I26-AO26,0) -> 55.615353 | AU26: =Act!L25 -> -693.35565 | AV26: =H26-AU26 -> #VALUE! | AX26: =IF('FC5+7'!S$3=1,'FC5+7'!S25,"") -> -440.85756 | AY26: =IF('FC5+7'!T$3=1,'FC5+7'!T25,"") | AZ26: =IF('FC5+7'!U$3=1,'FC5+7'!U25,"") | BA26: =SUM(AX26:AZ26) -> -440.85756 | BB26: =IFERROR(F26-AX26,0) -> 0 | BC26: =IFERROR(G26-AY26,0) -> 0 | BD26: =IFERROR(H26-AZ26,0) -> 0 | BE26: =IFERROR(I26-BA26,0) -> 0 | BG26: =F26 -> -440.85756 | BH26: -492.24093 | BI26: -857.4071 | BJ26: =SUM(BG26:BI26) -> -1790.5056 | BK26: =IFERROR(F26-AC26,0) -> 147.86963 | BL26: =IFERROR(G26-AD26,0) -> 0 | BM26: =IFERROR(AL26-AE26,0) -> 0 | BN26: =IFERROR(I26-BJ26,0) -> 1349.648 | BP26: =F26 -> -440.85756 | BQ26: =G26 | BR26: =#REF! -> #REF! | BS26: =SUM(BP26:BR26) -> #REF! | BT26: =BP26-AC26 -> 147.86963 | BU26: =BQ26-AD26 -> #VALUE! | BV26: =BR26-AE26 -> #REF! | BW26: =BS26-AF26 -> #REF! | BY26: =H26-BR26 -> #VALUE! | CA26: ='FC2+10'!AA25 -> #VALUE! | CC26: =CA26-I26 -> #VALUE! | CE26: =IF('FC7+5'!S$3=1,'FC7+5'!S25,"") -> -440.85756 | CF26: =IF('FC7+5'!T$3=1,'FC7+5'!T25,"") | CG26: =IF('FC7+5'!U$3=1,'FC7+5'!U25,"") | CH26: =SUM(CE26:CG26) -> -440.85756 | CI26: =IFERROR(F26-CE26,0) -> 0 | CJ26: =IFERROR(G26-CF26,0) -> 0 | CK26: =IFERROR(H26-CG26,0) -> 0 | CL26: =IFERROR(I26-CH26,0) -> 0 | CM26: =IF('FC7+5'!AC$3=1,'FC7+5'!AC25,"") -> -2272.6964 | CN26: =I26-CM26 -> 1831.8389
B27: CMP-I | F27: =SUM(F23,F26) -> 86.08362 | G27: =SUM(G23,G26) -> 0 | H27: =SUM(H23,H26) -> 0 | I27: =SUM(F27:H27) -> 86.08362 | K27: =K23+K26 -> 87.516627 | L27: =SUM(L23,L26) -> 0 | M27: =SUM(M23,M26) -> 0 | N27: =SUM(K27:M27) -> 87.516627 | O27: =IFERROR(F27-K27,0) -> -1.4330078 | P27: =IFERROR(G27-L27,0) -> 0 | Q27: =IFERROR(H27-M27,0) -> 0 | R27: =I27-N27 -> -1.4330078 | T27: =T23+T26 -> #VALUE! | U27: =SUM(U23,U26) -> 0 | V27: =SUM(V23,V26) -> 0 | W27: =SUM(T27:V27) -> #VALUE! | X27: =IFERROR(F27-T27,0) -> 0 | Y27: =IFERROR(G27-U27,0) -> 0 | Z27: =IFERROR(H27-V27,0) -> 0 | AA27: =I27-W27 -> #VALUE! | AC27: =AC23+AC26 -> 144.28301 | AD27: =SUM(AD23,AD26) -> 141.14914 | AE27: =SUM(AE23,AE26) -> 0 | AF27: =SUM(AC27:AE27) -> 285.43215 | AG27: =IFERROR(F27-AC27,0) -> -58.199392 | AH27: =IFERROR(G27-AD27,0) -> -141.14914 | AI27: =IFERROR(H27-AE27,0) -> 0 | AJ27: =IFERROR(I27-AF27,0) -> -199.34853 | AL27: =AL23+AL26 -> 156.56782 | AM27: =SUM(AM23,AM26) -> 0 | AN27: =SUM(AN23,AN26) -> 0 | AO27: =SUM(AL27:AN27) -> 156.56782 | AP27: =IFERROR(F27-AL27,0) -> -70.484198 | AQ27: =IFERROR(G27-AM27,0) -> 0 | AR27: =IFERROR(H27-AN27,0) -> 0 | AS27: =IFERROR(I27-AO27,0) -> -70.484198 | AU27: =Act!L26 -> 136.57489 | AV27: =H27-AU27 -> -136.57489 | AX27: =AX23+AX26 -> 86.08362 | AY27: =SUM(AY23,AY26) -> 0 | AZ27: =SUM(AZ23,AZ26) -> 0 | BA27: =SUM(AX27:AZ27) -> 86.08362 | BB27: =IFERROR(F27-AX27,0) -> 0 | BC27: =IFERROR(G27-AY27,0) -> 0 | BD27: =IFERROR(H27-AZ27,0) -> 0 | BE27: =IFERROR(I27-BA27,0) -> 0 | BG27: =F27 -> 86.08362 | BH27: 122.79728 | BI27: 70.304648 | BJ27: =SUM(BG27:BI27) -> 279.18555 | BK27: =IFERROR(F27-AC27,0) -> -58.199392 | BL27: =IFERROR(G27-AD27,0) -> -141.14914 | BM27: =IFERROR(AL27-AE27,0) -> 156.56782 | BN27: =IFERROR(I27-BJ27,0) -> -193.10193 | BP27: =F27 -> 86.08362 | BQ27: =G27 -> 0 | BR27: =#REF! -> #REF! | BS27: =SUM(BP27:BR27) -> #REF! | BT27: =BP27-AC27 -> -58.199392 | BU27: =BQ27-AD27 -> -141.14914 | BV27: =BR27-AE27 -> #REF! | BW27: =BS27-AF27 -> #REF! | BY27: =H27-BR27 -> #REF! | CA27: ='FC2+10'!AA26 -> #VALUE! | CC27: =CA27-I27 -> #VALUE! | CE27: =CE23+CE26 -> 86.08362 | CF27: =SUM(CF23,CF26) -> 0 | CG27: =SUM(CG23,CG26) -> 0 | CH27: =SUM(CE27:CG27) -> 86.08362 | CI27: =IFERROR(F27-CE27,0) -> 0 | CJ27: =IFERROR(G27-CF27,0) -> 0 | CK27: =IFERROR(H27-CG27,0) -> 0 | CL27: =IFERROR(I27-CH27,0) -> 0 | CM27: =CM23+CM26 -> 559.77731 | CN27: =I27-CM27 -> -473.69369
C28: % of Gross Sales | F28: =F27/F19 -> 0.14060748 | G28: =G27/G19 -> #VALUE! | H28: =H27/H19 -> #VALUE! | I28: =I27/I19 -> 0.14060748 | K28: =K27/K19 -> 0.1352237 | L28: =L27/L19 -> #VALUE! | M28: =M27/M19 -> #VALUE! | N28: =N27/N19 -> 0.1352237 | O28: =IFERROR(F28-K28,0) -> 0.0053837787 | P28: =IFERROR(G28-L28,0) -> 0 | Q28: =IFERROR(H28-M28,0) -> 0 | R28: =I28-N28 -> 0.0053837787 | T28: =T27/T19 -> #VALUE! | U28: =U27/U19 -> #VALUE! | V28: =V27/V19 -> #VALUE! | W28: =W27/W19 -> #VALUE! | X28: =IFERROR(F28-T28,0) -> 0 | Y28: =IFERROR(G28-U28,0) -> 0 | Z28: =IFERROR(H28-V28,0) -> 0 | AA28: =I28-W28 -> #VALUE! | AC28: =AC27/AC19 -> 0.16633294 | AD28: =AD27/AD19 -> 0.1413066 | AE28: =AE27/AE19 -> #VALUE! | AF28: =AF27/AF19 -> 0.15293843 | AG28: =IFERROR(F28-AC28,0) -> -0.025725461 | AH28: =IFERROR(G28-AD28,0) -> 0 | AI28: =IFERROR(H28-AE28,0) -> 0 | AJ28: =IFERROR(I28-AF28,0) -> -0.012330953 | AL28: =AL27/AL19 -> 0.20852106 | AM28: =AM27/AM19 -> #VALUE! | AN28: =AN27/AN19 -> #VALUE! | AO28: =AO27/AO19 -> 0.20852106 | AP28: =IFERROR(F28-AL28,0) -> -0.067913578 | AQ28: =IFERROR(G28-AM28,0) -> 0 | AR28: =IFERROR(H28-AN28,0) -> 0 | AS28: =IFERROR(I28-AO28,0) -> -0.067913578 | AU28: =Act!L27 -> 0.14038105 | AV28: =H28-AU28 -> #VALUE! | AX28: =AX27/AX19 -> 0.14060748 | AY28: =AY27/AY19 -> #VALUE! | AZ28: =AZ27/AZ19 -> #VALUE! | BA28: =BA27/BA19 -> 0.14060748 | BB28: =IFERROR(F28-AX28,0) -> 0 | BC28: =IFERROR(G28-AY28,0) -> 0 | BD28: =IFERROR(H28-AZ28,0) -> 0 | BE28: =IFERROR(I28-BA28,0) -> 0 | BG28: =F28 -> 0.14060748 | BH28: 0.17291874 | BI28: 0.064059353 | BJ28: =BJ27/BJ19 -> 0.11537245 | BK28: =IFERROR(F28-AC28,0) -> -0.025725461 | BL28: =IFERROR(G28-AD28,0) -> 0 | BM28: =IFERROR(AL28-AE28,0) -> 0 | BN28: =IFERROR(I28-BJ28,0) -> 0.025235029 | BP28: =F28 -> 0.14060748 | BQ28: =G28 -> #VALUE! | BR28: =#REF! -> #REF! | BS28: =BS27/BS19 -> #REF! | BT28: =BP28-AC28 -> -0.025725461 | BU28: =BQ28-AD28 -> #VALUE! | BV28: =BR28-AE28 -> #REF! | BW28: =BS28-AF28 -> #REF! | BY28: =H28-BR28 -> #VALUE! | CA28: ='FC2+10'!AA27 -> 0 | CC28: =CA28-I28 -> -0.14060748 | CE28: =CE27/CE19 -> 0.14060748 | CF28: =CF27/CF19 -> #VALUE! | CG28: =CG27/CG19 -> #VALUE! | CH28: =CH27/CH19 -> 0.14060748 | CI28: =IFERROR(F28-CE28,0) -> 0 | CJ28: =IFERROR(G28-CF28,0) -> 0 | CK28: =IFERROR(H28-CG28,0) -> 0 | CL28: =IFERROR(I28-CH28,0) -> 0 | CM28: =CM27/CM19 -> 0.16892935 | CN28: =I28-CM28 -> -0.028321868
D29: MFG | F29: =IF(Act!S$3=1,Act!S28,"") -> -29.170027 | G29: =IF(Act!T$3=1,Act!T28,"") | H29: =IF(Act!U$3=1,Act!U28,"") | I29: =SUM(F29:H29) -> -29.170027 | K29: =IF(BP!S$3=1,BP!S28,"") -> -30.77683 | L29: =IF(BP!T$3=1,BP!T28,"") | M29: =IF(BP!U$3=1,BP!U28,"") | N29: =SUM(K29:M29) -> -30.77683 | O29: =IFERROR(F29-K29,0) -> 1.6068029 | P29: =IFERROR(G29-L29,0) -> 0 | Q29: =IFERROR(H29-M29,0) -> 0 | R29: =I29-N29 -> 1.6068029 | T29: =IF('FC2+10'!S$3=1,'FC2+10'!S28,"") -> -29.170027 | U29: =IF('FC2+10'!T$3=1,'FC2+10'!T28,"") | V29: =IF('FC2+10'!U$3=1,'FC2+10'!U28,"") | W29: =SUM(T29:V29) -> -29.170027 | X29: =IFERROR(F29-T29,0) -> 0 | Y29: =IFERROR(G29-U29,0) -> 0 | Z29: =IFERROR(H29-V29,0) -> 0 | AA29: =I29-W29 -> 0 | AC29: =IF(OL!S$3=1,OL!S28,"") -> -26.61244 | AD29: =IF(OL!T$3=1,OL!T28,"") -> -27.002141 | AE29: =IF(OL!U$3=1,OL!U28,"") | AF29: =SUM(AC29:AE29) -> -53.614581 | AG29: =IFERROR(F29-AC29,0) -> -2.5575875 | AH29: =IFERROR(G29-AD29,0) -> 0 | AI29: =IFERROR(H29-AE29,0) -> 0 | AJ29: =IFERROR(I29-AF29,0) -> 24.444554 | AL29: =IF(LY!S$3=1,LY!S28,"") -> -28.523004 | AM29: =IF(LY!T$3=1,LY!T28,"") | AN29: =IF(LY!U$3=1,LY!U28,"") | AO29: =SUM(AL29:AN29) -> -28.523004 | AP29: =IFERROR(F29-AL29,0) -> -0.64702384 | AQ29: =IFERROR(G29-AM29,0) -> 0 | AR29: =IFERROR(H29-AN29,0) -> 0 | AS29: =IFERROR(I29-AO29,0) -> -0.64702384 | AU29: =Act!L28 -> -23.077292 | AV29: =H29-AU29 -> #VALUE! | AX29: =IF('FC5+7'!S$3=1,'FC5+7'!S28,"") -> -29.170027 | AY29: =IF('FC5+7'!T$3=1,'FC5+7'!T28,"") | AZ29: =IF('FC5+7'!U$3=1,'FC5+7'!U28,"") | BA29: =SUM(AX29:AZ29) -> -29.170027 | BB29: =IFERROR(F29-AX29,0) -> 0 | BC29: =IFERROR(G29-AY29,0) -> 0 | BD29: =IFERROR(H29-AZ29,0) -> 0 | BE29: =IFERROR(I29-BA29,0) -> 0 | BG29: =F29 -> -29.170027 | BH29: -28.299801 | BI29: -29.878045 | BJ29: =SUM(BG29:BI29) -> -87.347873 | BK29: =IFERROR(F29-AC29,0) -> -2.5575875 | BL29: =IFERROR(G29-AD29,0) -> 0 | BM29: =IFERROR(AL29-AE29,0) -> 0 | BN29: =IFERROR(I29-BJ29,0) -> 58.177846 | BP29: =F29 -> -29.170027 | BQ29: =G29 | BR29: =#REF! -> #REF! | BS29: =SUM(BP29:BR29) -> #REF! | BT29: =BP29-AC29 -> -2.5575875 | BU29: =BQ29-AD29 -> #VALUE! | BV29: =BR29-AE29 -> #REF! | BW29: =BS29-AF29 -> #REF! | BY29: =H29-BR29 -> #VALUE! | CA29: ='FC2+10'!AA28 -> -77.884931 | CC29: =CA29-I29 -> -48.714903 | CE29: =IF('FC7+5'!S$3=1,'FC7+5'!S28,"") -> -29.170027 | CF29: =IF('FC7+5'!T$3=1,'FC7+5'!T28,"") | CG29: =IF('FC7+5'!U$3=1,'FC7+5'!U28,"") | CH29: =SUM(CE29:CG29) -> -29.170027 | CI29: =IFERROR(F29-CE29,0) -> 0 | CJ29: =IFERROR(G29-CF29,0) -> 0 | CK29: =IFERROR(H29-CG29,0) -> 0 | CL29: =IFERROR(I29-CH29,0) -> 0 | CM29: =IF('FC7+5'!AC$3=1,'FC7+5'!AC28,"") -> -76.523763 | CN29: =I29-CM29 -> 47.353735
D30: VT | F30: =IF(Act!S$3=1,Act!S29,"") -> -5.2709534 | G30: =IF(Act!T$3=1,Act!T29,"") | H30: =IF(Act!U$3=1,Act!U29,"") | I30: =SUM(F30:H30) -> -5.2709534 | K30: =IF(BP!S$3=1,BP!S29,"") -> -5.1304774 | L30: =IF(BP!T$3=1,BP!T29,"") | M30: =IF(BP!U$3=1,BP!U29,"") | N30: =SUM(K30:M30) -> -5.1304774 | O30: =IFERROR(F30-K30,0) -> -0.14047596 | P30: =IFERROR(G30-L30,0) -> 0 | Q30: =IFERROR(H30-M30,0) -> 0 | R30: =I30-N30 -> -0.14047596 | T30: =IF('FC2+10'!S$3=1,'FC2+10'!S29,"") -> -5.2709534 | U30: =IF('FC2+10'!T$3=1,'FC2+10'!T29,"") | V30: =IF('FC2+10'!U$3=1,'FC2+10'!U29,"") | W30: =SUM(T30:V30) -> -5.2709534 | X30: =IFERROR(F30-T30,0) -> 0 | Y30: =IFERROR(G30-U30,0) -> 0 | Z30: =IFERROR(H30-V30,0) -> 0 | AA30: =I30-W30 -> 0 | AC30: =IF(OL!S$3=1,OL!S29,"") -> -1.244592 | AD30: =IF(OL!T$3=1,OL!T29,"") -> -0.42220004 | AE30: =IF(OL!U$3=1,OL!U29,"") | AF30: =SUM(AC30:AE30) -> -1.666792 | AG30: =IFERROR(F30-AC30,0) -> -4.0263614 | AH30: =IFERROR(G30-AD30,0) -> 0 | AI30: =IFERROR(H30-AE30,0) -> 0 | AJ30: =IFERROR(I30-AF30,0) -> -3.6041614 | AL30: =IF(LY!S$3=1,LY!S29,"") -> -6.6325747 | AM30: =IF(LY!T$3=1,LY!T29,"") | AN30: =IF(LY!U$3=1,LY!U29,"") | AO30: =SUM(AL30:AN30) -> -6.6325747 | AP30: =IFERROR(F30-AL30,0) -> 1.3616213 | AQ30: =IFERROR(G30-AM30,0) -> 0 | AR30: =IFERROR(H30-AN30,0) -> 0 | AS30: =IFERROR(I30-AO30,0) -> 1.3616213 | AU30: =Act!L29 -> -0.159096 | AV30: =H30-AU30 -> #VALUE! | AX30: =IF('FC5+7'!S$3=1,'FC5+7'!S29,"") -> -5.2709534 | AY30: =IF('FC5+7'!T$3=1,'FC5+7'!T29,"") | AZ30: =IF('FC5+7'!U$3=1,'FC5+7'!U29,"") | BA30: =SUM(AX30:AZ30) -> -5.2709534 | BB30: =IFERROR(F30-AX30,0) -> 0 | BC30: =IFERROR(G30-AY30,0) -> 0 | BD30: =IFERROR(H30-AZ30,0) -> 0 | BE30: =IFERROR(I30-BA30,0) -> 0 | BG30: =F30 -> -5.2709534 | BH30: -3.5255096 | BI30: -3.7706107 | BJ30: =SUM(BG30:BI30) -> -12.567074 | BK30: =IFERROR(F30-AC30,0) -> -4.0263614 | BL30: =IFERROR(G30-AD30,0) -> 0 | BM30: =IFERROR(AL30-AE30,0) -> 0 | BN30: =IFERROR(I30-BJ30,0) -> 7.2961203 | BP30: =F30 -> -5.2709534 | BQ30: =G30 | BR30: =#REF! -> #REF! | BS30: =SUM(BP30:BR30) -> #REF! | BT30: =BP30-AC30 -> -4.0263614 | BU30: =BQ30-AD30 -> #VALUE! | BV30: =BR30-AE30 -> #REF! | BW30: =BS30-AF30 -> #REF! | BY30: =H30-BR30 -> #VALUE! | CA30: ='FC2+10'!AA29 -> -0.44583333 | CC30: =CA30-I30 -> 4.8251201 | CE30: =IF('FC7+5'!S$3=1,'FC7+5'!S29,"") -> -5.2709534 | CF30: =IF('FC7+5'!T$3=1,'FC7+5'!T29,"") | CG30: =IF('FC7+5'!U$3=1,'FC7+5'!U29,"") | CH30: =SUM(CE30:CG30) -> -5.2709534 | CI30: =IFERROR(F30-CE30,0) -> 0 | CJ30: =IFERROR(G30-CF30,0) -> 0 | CK30: =IFERROR(H30-CG30,0) -> 0 | CL30: =IFERROR(I30-CH30,0) -> 0 | CM30: =IF('FC7+5'!AC$3=1,'FC7+5'!AC29,"") -> -3.5493798 | CN30: =I30-CM30 -> -1.7215736
D31: R&D *except for function | F31: =IF(Act!S$3=1,Act!S30,"") -> 0 | G31: =IF(Act!T$3=1,Act!T30,"") | H31: =IF(Act!U$3=1,Act!U30,"") | I31: =SUM(F31:H31) -> 0 | K31: =IF(BP!S$3=1,BP!S30,"") -> -0.010794793 | L31: =IF(BP!T$3=1,BP!T30,"") | M31: =IF(BP!U$3=1,BP!U30,"") | N31: =SUM(K31:M31) -> -0.010794793 | O31: =IFERROR(F31-K31,0) -> 0.010794793 | P31: =IFERROR(G31-L31,0) -> 0 | Q31: =IFERROR(H31-M31,0) -> 0 | R31: =I31-N31 -> 0.010794793 | T31: =IF('FC2+10'!S$3=1,'FC2+10'!S30,"") -> 0 | U31: =IF('FC2+10'!T$3=1,'FC2+10'!T30,"") | V31: =IF('FC2+10'!U$3=1,'FC2+10'!U30,"") | W31: =SUM(T31:V31) -> 0 | X31: =IFERROR(F31-T31,0) -> 0 | Y31: =IFERROR(G31-U31,0) -> 0 | Z31: =IFERROR(H31-V31,0) -> 0 | AA31: =I31-W31 -> 0 | AC31: =IF(OL!S$3=1,OL!S30,"") -> 0 | AD31: =IF(OL!T$3=1,OL!T30,"") -> 0 | AE31: =IF(OL!U$3=1,OL!U30,"") | AF31: =SUM(AC31:AE31) -> 0 | AG31: =IFERROR(F31-AC31,0) -> 0 | AH31: =IFERROR(G31-AD31,0) -> 0 | AI31: =IFERROR(H31-AE31,0) -> 0 | AJ31: =IFERROR(I31-AF31,0) -> 0 | AL31: =IF(LY!S$3=1,LY!S30,"") -> 0 | AM31: =IF(LY!T$3=1,LY!T30,"") | AN31: =IF(LY!U$3=1,LY!U30,"") | AO31: =SUM(AL31:AN31) -> 0 | AP31: =IFERROR(F31-AL31,0) -> 0 | AQ31: =IFERROR(G31-AM31,0) -> 0 | AR31: =IFERROR(H31-AN31,0) -> 0 | AS31: =IFERROR(I31-AO31,0) -> 0 | AU31: =Act!L30 -> 0 | AV31: =H31-AU31 -> #VALUE! | AX31: =IF('FC5+7'!S$3=1,'FC5+7'!S30,"") -> 0 | AY31: =IF('FC5+7'!T$3=1,'FC5+7'!T30,"") | AZ31: =IF('FC5+7'!U$3=1,'FC5+7'!U30,"") | BA31: =SUM(AX31:AZ31) -> 0 | BB31: =IFERROR(F31-AX31,0) -> 0 | BC31: =IFERROR(G31-AY31,0) -> 0 | BD31: =IFERROR(H31-AZ31,0) -> 0 | BE31: =IFERROR(I31-BA31,0) -> 0 | BG31: =F31 -> 0 | BH31: 0 | BI31: 0 | BJ31: =SUM(BG31:BI31) -> 0 | BK31: =IFERROR(F31-AC31,0) -> 0 | BL31: =IFERROR(G31-AD31,0) -> 0 | BM31: =IFERROR(AL31-AE31,0) -> 0 | BN31: =IFERROR(I31-BJ31,0) -> 0 | BP31: =F31 -> 0 | BQ31: =G31 | BR31: =#REF! -> #REF! | BS31: =SUM(BP31:BR31) -> #REF! | BT31: =BP31-AC31 -> 0 | BU31: =BQ31-AD31 -> #VALUE! | BV31: =BR31-AE31 -> #REF! | BW31: =BS31-AF31 -> #REF! | BY31: =H31-BR31 -> #VALUE! | CA31: ='FC2+10'!AA30 -> 0 | CC31: =CA31-I31 -> 0 | CE31: =IF('FC7+5'!S$3=1,'FC7+5'!S30,"") -> 0 | CF31: =IF('FC7+5'!T$3=1,'FC7+5'!T30,"") | CG31: =IF('FC7+5'!U$3=1,'FC7+5'!U30,"") | CH31: =SUM(CE31:CG31) -> 0 | CI31: =IFERROR(F31-CE31,0) -> 0 | CJ31: =IFERROR(G31-CF31,0) -> 0 | CK31: =IFERROR(H31-CG31,0) -> 0 | CL31: =IFERROR(I31-CH31,0) -> 0 | CM31: =IF('FC7+5'!AC$3=1,'FC7+5'!AC30,"") -> 0 | CN31: =I31-CM31 -> 0
D32: Warranty | F32: =IF(Act!S$3=1,Act!S31,"") -> -22.075094 | G32: =IF(Act!T$3=1,Act!T31,"") | H32: =IF(Act!U$3=1,Act!U31,"") | I32: =SUM(F32:H32) -> -22.075094 | K32: =IF(BP!S$3=1,BP!S31,"") -> -20.539579 | L32: =IF(BP!T$3=1,BP!T31,"") | M32: =IF(BP!U$3=1,BP!U31,"") | N32: =SUM(K32:M32) -> -20.539579 | O32: =IFERROR(F32-K32,0) -> -1.5355154 | P32: =IFERROR(G32-L32,0) -> 0 | Q32: =IFERROR(H32-M32,0) -> 0 | R32: =I32-N32 -> -1.5355154 | T32: =IF('FC2+10'!S$3=1,'FC2+10'!S31,"") -> -22.075094 | U32: =IF('FC2+10'!T$3=1,'FC2+10'!T31,"") | V32: =IF('FC2+10'!U$3=1,'FC2+10'!U31,"") | W32: =SUM(T32:V32) -> -22.075094 | X32: =IFERROR(F32-T32,0) -> 0 | Y32: =IFERROR(G32-U32,0) -> 0 | Z32: =IFERROR(H32-V32,0) -> 0 | AA32: =I32-W32 -> 0 | AC32: =IF(OL!S$3=1,OL!S31,"") -> -8.6311958 | AD32: =IF(OL!T$3=1,OL!T31,"") -> -5.8328414 | AE32: =IF(OL!U$3=1,OL!U31,"") | AF32: =SUM(AC32:AE32) -> -14.464037 | AG32: =IFERROR(F32-AC32,0) -> -13.443898 | AH32: =IFERROR(G32-AD32,0) -> 0 | AI32: =IFERROR(H32-AE32,0) -> 0 | AJ32: =IFERROR(I32-AF32,0) -> -7.611057 | AL32: =IF(LY!S$3=1,LY!S31,"") -> -7.1486413 | AM32: =IF(LY!T$3=1,LY!T31,"") | AN32: =IF(LY!U$3=1,LY!U31,"") | AO32: =SUM(AL32:AN32) -> -7.1486413 | AP32: =IFERROR(F32-AL32,0) -> -14.926453 | AQ32: =IFERROR(G32-AM32,0) -> 0 | AR32: =IFERROR(H32-AN32,0) -> 0 | AS32: =IFERROR(I32-AO32,0) -> -14.926453 | AU32: =Act!L31 -> -9.4293348 | AV32: =H32-AU32 -> #VALUE! | AX32: =IF('FC5+7'!S$3=1,'FC5+7'!S31,"") -> -22.075094 | AY32: =IF('FC5+7'!T$3=1,'FC5+7'!T31,"") | AZ32: =IF('FC5+7'!U$3=1,'FC5+7'!U31,"") | BA32: =SUM(AX32:AZ32) -> -22.075094 | BB32: =IFERROR(F32-AX32,0) -> 0 | BC32: =IFERROR(G32-AY32,0) -> 0 | BD32: =IFERROR(H32-AZ32,0) -> 0 | BE32: =IFERROR(I32-BA32,0) -> 0 | BG32: =F32 -> -22.075094 | BH32: -6.6139372 | BI32: -7.4965247 | BJ32: =SUM(BG32:BI32) -> -36.185556 | BK32: =IFERROR(F32-AC32,0) -> -13.443898 | BL32: =IFERROR(G32-AD32,0) -> 0 | BM32: =IFERROR(AL32-AE32,0) -> 0 | BN32: =IFERROR(I32-BJ32,0) -> 14.110462 | BP32: =F32 -> -22.075094 | BQ32: =G32 | BR32: =#REF! -> #REF! | BS32: =SUM(BP32:BR32) -> #REF! | BT32: =BP32-AC32 -> -13.443898 | BU32: =BQ32-AD32 -> #VALUE! | BV32: =BR32-AE32 -> #REF! | BW32: =BS32-AF32 -> #REF! | BY32: =H32-BR32 -> #VALUE! | CA32: ='FC2+10'!AA31 -> -25.760772 | CC32: =CA32-I32 -> -3.6856782 | CE32: =IF('FC7+5'!S$3=1,'FC7+5'!S31,"") -> -22.075094 | CF32: =IF('FC7+5'!T$3=1,'FC7+5'!T31,"") | CG32: =IF('FC7+5'!U$3=1,'FC7+5'!U31,"") | CH32: =SUM(CE32:CG32) -> -22.075094 | CI32: =IFERROR(F32-CE32,0) -> 0 | CJ32: =IFERROR(G32-CF32,0) -> 0 | CK32: =IFERROR(H32-CG32,0) -> 0 | CL32: =IFERROR(I32-CH32,0) -> 0 | CM32: =IF('FC7+5'!AC$3=1,'FC7+5'!AC31,"") -> -21.783653 | CN32: =I32-CM32 -> -0.29144123
D33: *RS (Global Function Cost) | F33: =IF(Act!S$3=1,Act!S32,"") -> 0 | G33: =IF(Act!T$3=1,Act!T32,"") | H33: =IF(Act!U$3=1,Act!U32,"") | I33: =SUM(F33:H33) -> 0 | K33: =IF(BP!S$3=1,BP!S32,"") -> 0 | L33: =IF(BP!T$3=1,BP!T32,"") | M33: =IF(BP!U$3=1,BP!U32,"") | N33: =SUM(K33:M33) -> 0 | O33: =IFERROR(F33-K33,0) -> 0 | P33: =IFERROR(G33-L33,0) -> 0 | Q33: =IFERROR(H33-M33,0) -> 0 | R33: =I33-N33 -> 0 | T33: =IF('FC2+10'!S$3=1,'FC2+10'!S32,"") -> 0 | U33: =IF('FC2+10'!T$3=1,'FC2+10'!T32,"") | V33: =IF('FC2+10'!U$3=1,'FC2+10'!U32,"") | W33: =SUM(T33:V33) -> 0 | X33: =IFERROR(F33-T33,0) -> 0 | Y33: =IFERROR(G33-U33,0) -> 0 | Z33: =IFERROR(H33-V33,0) -> 0 | AA33: =I33-W33 -> 0 | AC33: =IF(OL!S$3=1,OL!S32,"") -> 0 | AD33: =IF(OL!T$3=1,OL!T32,"") -> 0 | AE33: =IF(OL!U$3=1,OL!U32,"") | AF33: =SUM(AC33:AE33) -> 0 | AG33: =IFERROR(F33-AC33,0) -> 0 | AH33: =IFERROR(G33-AD33,0) -> 0 | AI33: =IFERROR(H33-AE33,0) -> 0 | AJ33: =IFERROR(I33-AF33,0) -> 0 | AL33: =IF(LY!S$3=1,LY!S32,"") -> 0 | AM33: =IF(LY!T$3=1,LY!T32,"") | AN33: =IF(LY!U$3=1,LY!U32,"") | AO33: =SUM(AL33:AN33) -> 0 | AP33: =IFERROR(F33-AL33,0) -> 0 | AQ33: =IFERROR(G33-AM33,0) -> 0 | AR33: =IFERROR(H33-AN33,0) -> 0 | AS33: =IFERROR(I33-AO33,0) -> 0 | AU33: =Act!L32 -> 0 | AV33: =H33-AU33 -> #VALUE! | AX33: =IF('FC5+7'!S$3=1,'FC5+7'!S32,"") -> 0 | AY33: =IF('FC5+7'!T$3=1,'FC5+7'!T32,"") | AZ33: =IF('FC5+7'!U$3=1,'FC5+7'!U32,"") | BA33: =SUM(AX33:AZ33) -> 0 | BB33: =IFERROR(F33-AX33,0) -> 0 | BC33: =IFERROR(G33-AY33,0) -> 0 | BD33: =IFERROR(H33-AZ33,0) -> 0 | BE33: =IFERROR(I33-BA33,0) -> 0 | BG33: =F33 -> 0 | BH33: 0 | BI33: 0 | BJ33: =SUM(BG33:BI33) -> 0 | BK33: =IFERROR(F33-AC33,0) -> 0 | BL33: =IFERROR(G33-AD33,0) -> 0 | BM33: =IFERROR(AL33-AE33,0) -> 0 | BN33: =IFERROR(I33-BJ33,0) -> 0 | BP33: =F33 -> 0 | BQ33: =G33 | BR33: =#REF! -> #REF! | BS33: =SUM(BP33:BR33) -> #REF! | BT33: =BP33-AC33 -> 0 | BU33: =BQ33-AD33 -> #VALUE! | BV33: =BR33-AE33 -> #REF! | BW33: =BS33-AF33 -> #REF! | BY33: =H33-BR33 -> #VALUE! | CA33: ='FC2+10'!AA32 -> 0 | CC33: =CA33-I33 -> 0 | CE33: =IF('FC5+7'!S$3=1,'FC5+7'!S32,"") -> 0 | CF33: =IF('FC5+7'!BA$3=1,'FC5+7'!BA32,"") | CG33: =IF('FC5+7'!BB$3=1,'FC5+7'!BB32,"") | CH33: =SUM(CE33:CG33) -> 0 | CI33: =IFERROR(F33-CE33,0) -> 0 | CJ33: =IFERROR(G33-CF33,0) -> 0 | CK33: =IFERROR(H33-CG33,0) -> 0 | CL33: =IFERROR(I33-CH33,0) -> 0 | CM33: =IF('FC5+7'!AC$3=1,'FC5+7'!AC32,"")
D34: MFG - out of function scope | F34: =IF(Act!S$3=1,Act!S33,"") -> -10.598456 | G34: =IF(Act!T$3=1,Act!T33,"") | H34: =IF(Act!U$3=1,Act!U33,"") | I34: =SUM(F34:H34) -> -10.598456 | K34: =IF(BP!S$3=1,BP!S33,"") -> -28.939301 | L34: =IF(BP!T$3=1,BP!T33,"") | M34: =IF(BP!U$3=1,BP!U33,"") | N34: =SUM(K34:M34) -> -28.939301 | O34: =IFERROR(F34-K34,0) -> 18.340846 | P34: =IFERROR(G34-L34,0) -> 0 | Q34: =IFERROR(H34-M34,0) -> 0 | R34: =I34-N34 -> 18.340846 | T34: =IF('FC2+10'!S$3=1,'FC2+10'!S33,"") -> -10.598456 | U34: =IF('FC2+10'!T$3=1,'FC2+10'!T33,"") | V34: =IF('FC2+10'!U$3=1,'FC2+10'!U33,"") | W34: =SUM(T34:V34) -> -10.598456 | X34: =IFERROR(F34-T34,0) -> 0 | Y34: =IFERROR(G34-U34,0) -> 0 | Z34: =IFERROR(H34-V34,0) -> 0 | AA34: =I34-W34 -> 0 | AC34: =IF(OL!S$3=1,OL!S33,"") -> -12.553722 | AD34: =IF(OL!T$3=1,OL!T33,"") -> -19.115941 | AE34: =IF(OL!U$3=1,OL!U33,"") | AF34: =SUM(AC34:AE34) -> -31.669662 | AG34: =IFERROR(F34-AC34,0) -> 1.955266 | AH34: =IFERROR(G34-AD34,0) -> 0 | AI34: =IFERROR(H34-AE34,0) -> 0 | AJ34: =IFERROR(I34-AF34,0) -> 21.071207 | AL34: =IF(LY!S$3=1,LY!S33,"") -> -10.486304 | AM34: =IF(LY!T$3=1,LY!T33,"") | AN34: =IF(LY!U$3=1,LY!U33,"") | AO34: =SUM(AL34:AN34) -> -10.486304 | AP34: =IFERROR(F34-AL34,0) -> -0.11215198 | AQ34: =IFERROR(G34-AM34,0) -> 0 | AR34: =IFERROR(H34-AN34,0) -> 0 | AS34: =IFERROR(I34-AO34,0) -> -0.11215198 | AU34: =Act!L33 -> -11.56958 | AV34: =H34-AU34 -> #VALUE! | AX34: =IF('FC5+7'!S$3=1,'FC5+7'!S33,"") -> -10.598456 | AY34: =IF('FC5+7'!T$3=1,'FC5+7'!T33,"") | AZ34: =IF('FC5+7'!U$3=1,'FC5+7'!U33,"") | BA34: =SUM(AX34:AZ34) -> -10.598456 | BB34: =IFERROR(F34-AX34,0) -> 0 | BC34: =IFERROR(G34-AY34,0) -> 0 | BD34: =IFERROR(H34-AZ34,0) -> 0 | BE34: =IFERROR(I34-BA34,0) -> 0 | BG34: =F34 -> -10.598456 | BH34: -10.654559 | BI34: -13.487015 | BJ34: =SUM(BG34:BI34) -> -34.74003 | BK34: =IFERROR(F34-AC34,0) -> 1.955266 | BL34: =IFERROR(G34-AD34,0) -> 0 | BM34: =IFERROR(AL34-AE34,0) -> 0 | BN34: =IFERROR(I34-BJ34,0) -> 24.141575 | BP34: =F34 -> -10.598456 | BQ34: =G34 | BR34: =#REF! -> #REF! | BS34: =SUM(BP34:BR34) -> #REF! | BT34: =BP34-AC34 -> 1.955266 | BU34: =BQ34-AD34 -> #VALUE! | BV34: =BR34-AE34 -> #REF! | BW34: =BS34-AF34 -> #REF! | BY34: =H34-BR34 -> #VALUE! | CA34: ='FC2+10'!AA33 -> -32.945411 | CC34: =CA34-I34 -> -22.346956 | CE34: =IF('FC7+5'!S$3=1,'FC7+5'!S33,"") -> -10.598456 | CF34: =IF('FC7+5'!T$3=1,'FC7+5'!T33,"") | CG34: =IF('FC7+5'!U$3=1,'FC7+5'!U33,"") | CH34: =SUM(CE34:CG34) -> -10.598456 | CI34: =IFERROR(F34-CE34,0) -> 0 | CJ34: =IFERROR(G34-CF34,0) -> 0 | CK34: =IFERROR(H34-CG34,0) -> 0 | CL34: =IFERROR(I34-CH34,0) -> 0 | CM34: =IF('FC7+5'!AC$3=1,'FC7+5'!AC33,"") -> -39.479261 | CN34: =I34-CM34 -> 28.880805
C35: MZK Total | F35: =SUM(F29:F31,F32:F34) -> -67.114531 | G35: =SUM(G29:G31,G32:G34) -> 0 | H35: =SUM(H29:H31,H32:H34) -> 0 | I35: =SUM(F35:H35) -> -67.114531 | K35: =SUM(K29:K31,K32:K34) -> -85.396983 | L35: =SUM(L29:L31,L32:L34) -> 0 | M35: =SUM(M29:M31,M32:M34) -> 0 | N35: =SUM(K35:M35) -> -85.396983 | O35: =IFERROR(F35-K35,0) -> 18.282452 | P35: =IFERROR(G35-L35,0) -> 0 | Q35: =IFERROR(H35-M35,0) -> 0 | R35: =I35-N35 -> 18.282452 | T35: =SUM(T29:T31,T32:T34) -> -67.114531 | U35: =SUM(U29:U31,U32:U34) -> 0 | V35: =SUM(V29:V31,V32:V34) -> 0 | W35: =SUM(T35:V35) -> -67.114531 | X35: =IFERROR(F35-T35,0) -> 0 | Y35: =IFERROR(G35-U35,0) -> 0 | Z35: =IFERROR(H35-V35,0) -> 0 | AA35: =I35-W35 -> 0 | AC35: =SUM(AC29:AC31,AC32:AC34) -> -49.041949 | AD35: =SUM(AD29:AD31,AD32:AD34) -> -52.373124 | AE35: =SUM(AE29:AE31,AE32:AE34) -> 0 | AF35: =SUM(AC35:AE35) -> -101.41507 | AG35: =IFERROR(F35-AC35,0) -> -18.072581 | AH35: =IFERROR(G35-AD35,0) -> 52.373124 | AI35: =IFERROR(H35-AE35,0) -> 0 | AJ35: =IFERROR(I35-AF35,0) -> 34.300542 | AL35: =SUM(AL29:AL31,AL32:AL34) -> -52.790523 | AM35: =SUM(AM29:AM31,AM32:AM34) -> 0 | AN35: =SUM(AN29:AN31,AN32:AN34) -> 0 | AO35: =SUM(AL35:AN35) -> -52.790523 | AP35: =IFERROR(F35-AL35,0) -> -14.324007 | AQ35: =IFERROR(G35-AM35,0) -> 0 | AR35: =IFERROR(H35-AN35,0) -> 0 | AS35: =IFERROR(I35-AO35,0) -> -14.324007 | AU35: =Act!L34 -> -44.235303 | AV35: =H35-AU35 -> 44.235303 | AX35: =SUM(AX29:AX31,AX32:AX34) -> -67.114531 | AY35: =SUM(AY29:AY31,AY32:AY34) -> 0 | AZ35: =SUM(AZ29:AZ31,AZ32:AZ34) -> 0 | BA35: =SUM(AX35:AZ35) -> -67.114531 | BB35: =IFERROR(F35-AX35,0) -> 0 | BC35: =IFERROR(G35-AY35,0) -> 0 | BD35: =IFERROR(H35-AZ35,0) -> 0 | BE35: =IFERROR(I35-BA35,0) -> 0 | BG35: =F35 -> -67.114531 | BH35: -49.093807 | BI35: -54.632196 | BJ35: =SUM(BG35:BI35) -> -170.84053 | BK35: =IFERROR(F35-AC35,0) -> -18.072581 | BL35: =IFERROR(G35-AD35,0) -> 52.373124 | BM35: =IFERROR(AL35-AE35,0) -> -52.790523 | BN35: =IFERROR(I35-BJ35,0) -> 103.726 | BP35: =F35 -> -67.114531 | BQ35: =G35 -> 0 | BR35: =#REF! -> #REF! | BS35: =SUM(BP35:BR35) -> #REF! | BT35: =BP35-AC35 -> -18.072581 | BU35: =BQ35-AD35 -> 52.373124 | BV35: =BR35-AE35 -> #REF! | BW35: =BS35-AF35 -> #REF! | BY35: =H35-BR35 -> #REF! | CA35: ='FC2+10'!AA34 -> -137.03695 | CC35: =CA35-I35 -> -69.922417 | CE35: =SUM(CE29:CE31,CE32:CE34) -> -67.114531 | CF35: =SUM(CF29:CF31,CF32:CF34) -> 0 | CG35: =SUM(CG29:CG31,CG32:CG34) -> 0 | CH35: =SUM(CE35:CG35) -> -67.114531 | CI35: =IFERROR(F35-CE35,0) -> 0 | CJ35: =IFERROR(G35-CF35,0) -> 0 | CK35: =IFERROR(H35-CG35,0) -> 0 | CL35: =IFERROR(I35-CH35,0) -> 0 | CM35: =SUM(CM29:CM31,CM32:CM34) -> -141.33606 | CN35: =I35-CM35 -> 74.221525
D36: FMI (M&S) | F36: =IF(Act!S$3=1,Act!S35,"") -> -21.268724 | G36: =IF(Act!T$3=1,Act!T35,"") | H36: =IF(Act!U$3=1,Act!U35,"") | I36: =SUM(F36:H36) -> -21.268724 | K36: =IF(BP!S$3=1,BP!S35,"") -> -24.460348 | L36: =IF(BP!T$3=1,BP!T35,"") | M36: =IF(BP!U$3=1,BP!U35,"") | N36: =SUM(K36:M36) -> -24.460348 | O36: =IFERROR(F36-K36,0) -> 3.1916236 | P36: =IFERROR(G36-L36,0) -> 0 | Q36: =IFERROR(H36-M36,0) -> 0 | R36: =I36-N36 -> 3.1916236 | T36: =IF('FC2+10'!S$3=1,'FC2+10'!S35,"") -> -21.268724 | U36: =IF('FC2+10'!T$3=1,'FC2+10'!T35,"") | V36: =IF('FC2+10'!U$3=1,'FC2+10'!U35,"") | W36: =SUM(T36:V36) -> -21.268724 | X36: =IFERROR(F36-T36,0) -> 0 | Y36: =IFERROR(G36-U36,0) -> 0 | Z36: =IFERROR(H36-V36,0) -> 0 | AA36: =I36-W36 -> 0 | AC36: =IF(OL!S$3=1,OL!S35,"") -> -26.036587 | AD36: =IF(OL!T$3=1,OL!T35,"") -> -29.103861 | AE36: =IF(OL!U$3=1,OL!U35,"") | AF36: =SUM(AC36:AE36) -> -55.140448 | AG36: =IFERROR(F36-AC36,0) -> 4.7678626 | AH36: =IFERROR(G36-AD36,0) -> 0 | AI36: =IFERROR(H36-AE36,0) -> 0 | AJ36: =IFERROR(I36-AF36,0) -> 33.871723 | AL36: =IF(LY!S$3=1,LY!S35,"") -> -29.814473 | AM36: =IF(LY!T$3=1,LY!T35,"") | AN36: =IF(LY!U$3=1,LY!U35,"") | AO36: =SUM(AL36:AN36) -> -29.814473 | AP36: =IFERROR(F36-AL36,0) -> 8.5457491 | AQ36: =IFERROR(G36-AM36,0) -> 0 | AR36: =IFERROR(H36-AN36,0) -> 0 | AS36: =IFERROR(I36-AO36,0) -> 8.5457491 | AU36: =Act!L35 -> -23.951744 | AV36: =H36-AU36 -> #VALUE! | AX36: =IF('FC5+7'!S$3=1,'FC5+7'!S35,"") -> -21.268724 | AY36: =IF('FC5+7'!T$3=1,'FC5+7'!T35,"") | AZ36: =IF('FC5+7'!U$3=1,'FC5+7'!U35,"") | BA36: =SUM(AX36:AZ36) -> -21.268724 | BB36: =IFERROR(F36-AX36,0) -> 0 | BC36: =IFERROR(G36-AY36,0) -> 0 | BD36: =IFERROR(H36-AZ36,0) -> 0 | BE36: =IFERROR(I36-BA36,0) -> 0 | BG36: =F36 -> -21.268724 | BH36: -27.71421 | BI36: -34.438521 | BJ36: =SUM(BG36:BI36) -> -83.421455 | BK36: =IFERROR(F36-AC36,0) -> 4.7678626 | BL36: =IFERROR(G36-AD36,0) -> 0 | BM36: =IFERROR(AL36-AE36,0) -> 0 | BN36: =IFERROR(I36-BJ36,0) -> 62.152731 | BP36: =F36 -> -21.268724 | BQ36: =G36 | BR36: =#REF! -> #REF! | BS36: =SUM(BP36:BR36) -> #REF! | BT36: =BP36-AC36 -> 4.7678626 | BU36: =BQ36-AD36 -> #VALUE! | BV36: =BR36-AE36 -> #REF! | BW36: =BS36-AF36 -> #REF! | BY36: =H36-BR36 -> #VALUE! | CA36: ='FC2+10'!AA35 -> -85.602171 | CC36: =CA36-I36 -> -64.333446 | CE36: =IF('FC7+5'!S$3=1,'FC7+5'!S35,"") -> -21.268724 | CF36: =IF('FC7+5'!T$3=1,'FC7+5'!T35,"") | CG36: =IF('FC7+5'!U$3=1,'FC7+5'!U35,"") | CH36: =SUM(CE36:CG36) -> -21.268724 | CI36: =IFERROR(F36-CE36,0) -> 0 | CJ36: =IFERROR(G36-CF36,0) -> 0 | CK36: =IFERROR(H36-CG36,0) -> 0 | CL36: =IFERROR(I36-CH36,0) -> 0 | CM36: =IF('FC7+5'!AC$3=1,'FC7+5'!AC35,"") -> -77.359347 | CN36: =I36-CM36 -> 56.090622
D37: Remarketing (USA/Canada/Infiniti) | F37: =IF(Act!S$3=1,Act!S36,"") -> 0 | G37: =IF(Act!T$3=1,Act!T36,"") | H37: =IF(Act!U$3=1,Act!U36,"") | I37: =SUM(F37:H37) -> 0 | K37: =IF(BP!S$3=1,BP!S36,"") -> 0 | L37: =IF(BP!T$3=1,BP!T36,"") | M37: =IF(BP!U$3=1,BP!U36,"") | N37: =SUM(K37:M37) -> 0 | O37: =IFERROR(F37-K37,0) -> 0 | P37: =IFERROR(G37-L37,0) -> 0 | Q37: =IFERROR(H37-M37,0) -> 0 | R37: =I37-N37 -> 0 | T37: =IF('FC2+10'!S$3=1,'FC2+10'!S36,"") -> 0 | U37: =IF('FC2+10'!T$3=1,'FC2+10'!T36,"") | V37: =IF('FC2+10'!U$3=1,'FC2+10'!U36,"") | W37: =SUM(T37:V37) -> 0 | X37: =IFERROR(F37-T37,0) -> 0 | Y37: =IFERROR(G37-U37,0) -> 0 | Z37: =IFERROR(H37-V37,0) -> 0 | AA37: =I37-W37 -> 0 | AC37: =IF(OL!S$3=1,OL!S36,"") -> 0 | AD37: =IF(OL!T$3=1,OL!T36,"") -> 0 | AE37: =IF(OL!U$3=1,OL!U36,"") | AF37: =SUM(AC37:AE37) -> 0 | AG37: =IFERROR(F37-AC37,0) -> 0 | AH37: =IFERROR(G37-AD37,0) -> 0 | AI37: =IFERROR(H37-AE37,0) -> 0 | AJ37: =IFERROR(I37-AF37,0) -> 0 | AL37: =IF(LY!S$3=1,LY!S36,"") -> 0 | AM37: =IF(LY!T$3=1,LY!T36,"") | AN37: =IF(LY!U$3=1,LY!U36,"") | AO37: =SUM(AL37:AN37) -> 0 | AP37: =IFERROR(F37-AL37,0) -> 0 | AQ37: =IFERROR(G37-AM37,0) -> 0 | AR37: =IFERROR(H37-AN37,0) -> 0 | AS37: =IFERROR(I37-AO37,0) -> 0 | AU37: =Act!L36 -> 0 | AV37: =H37-AU37 -> #VALUE! | AX37: =IF('FC5+7'!S$3=1,'FC5+7'!S36,"") -> 0 | AY37: =IF('FC5+7'!T$3=1,'FC5+7'!T36,"") | AZ37: =IF('FC5+7'!U$3=1,'FC5+7'!U36,"") | BA37: =SUM(AX37:AZ37) -> 0 | BB37: =IFERROR(F37-AX37,0) -> 0 | BC37: =IFERROR(G37-AY37,0) -> 0 | BD37: =IFERROR(H37-AZ37,0) -> 0 | BE37: =IFERROR(I37-BA37,0) -> 0 | BG37: =F37 -> 0 | BH37: 0 | BI37: 0 | BJ37: =SUM(BG37:BI37) -> 0 | BK37: =IFERROR(F37-AC37,0) -> 0 | BL37: =IFERROR(G37-AD37,0) -> 0 | BM37: =IFERROR(AL37-AE37,0) -> 0 | BN37: =IFERROR(I37-BJ37,0) -> 0 | BP37: =F37 -> 0 | BQ37: =G37 | BR37: =#REF! -> #REF! | BS37: =SUM(BP37:BR37) -> #REF! | BT37: =BP37-AC37 -> 0 | BU37: =BQ37-AD37 -> #VALUE! | BV37: =BR37-AE37 -> #REF! | BW37: =BS37-AF37 -> #REF! | BY37: =H37-BR37 -> #VALUE! | CA37: ='FC2+10'!AA36 -> 0 | CC37: =CA37-I37 -> 0 | CE37: =IF('FC7+5'!S$3=1,'FC7+5'!S36,"") -> 0 | CF37: =IF('FC7+5'!T$3=1,'FC7+5'!T36,"") | CG37: =IF('FC7+5'!U$3=1,'FC7+5'!U36,"") | CH37: =SUM(CE37:CG37) -> 0 | CI37: =IFERROR(F37-CE37,0) -> 0 | CJ37: =IFERROR(G37-CF37,0) -> 0 | CK37: =IFERROR(H37-CG37,0) -> 0 | CL37: =IFERROR(I37-CH37,0) -> 0 | CM37: =IF('FC7+5'!AC$3=1,'FC7+5'!AC36,"") -> 0 | CN37: =I37-CM37 -> 0
D38: *FMI- out of function scope (CFMI & Other) | F38: =IF(Act!S$3=1,Act!S37,"") -> -4.9093125 | G38: =IF(Act!T$3=1,Act!T37,"") | H38: =IF(Act!U$3=1,Act!U37,"") | I38: =SUM(F38:H38) -> -4.9093125 | K38: =IF(BP!S$3=1,BP!S37,"") -> -5.133438 | L38: =IF(BP!T$3=1,BP!T37,"") | M38: =IF(BP!U$3=1,BP!U37,"") | N38: =SUM(K38:M38) -> -5.133438 | O38: =IFERROR(F38-K38,0) -> 0.22412549 | P38: =IFERROR(G38-L38,0) -> 0 | Q38: =IFERROR(H38-M38,0) -> 0 | R38: =I38-N38 -> 0.22412549 | T38: =IF('FC2+10'!S$3=1,'FC2+10'!S37,"") -> -4.9093125 | U38: =IF('FC2+10'!T$3=1,'FC2+10'!T37,"") | V38: =IF('FC2+10'!U$3=1,'FC2+10'!U37,"") | W38: =SUM(T38:V38) -> -4.9093125 | X38: =IFERROR(F38-T38,0) -> 0 | Y38: =IFERROR(G38-U38,0) -> 0 | Z38: =IFERROR(H38-V38,0) -> 0 | AA38: =I38-W38 -> 0 | AC38: =IF(OL!S$3=1,OL!S37,"") -> -5.7556092 | AD38: =IF(OL!T$3=1,OL!T37,"") -> -5.8986338 | AE38: =IF(OL!U$3=1,OL!U37,"") | AF38: =SUM(AC38:AE38) -> -11.654243 | AG38: =IFERROR(F38-AC38,0) -> 0.84629667 | AH38: =IFERROR(G38-AD38,0) -> 0 | AI38: =IFERROR(H38-AE38,0) -> 0 | AJ38: =IFERROR(I38-AF38,0) -> 6.7449305 | AL38: =IF(LY!S$3=1,LY!S37,"") -> -4.2758629 | AM38: =IF(LY!T$3=1,LY!T37,"") | AN38: =IF(LY!U$3=1,LY!U37,"") | AO38: =SUM(AL38:AN38) -> -4.2758629 | AP38: =IFERROR(F38-AL38,0) -> -0.63344961 | AQ38: =IFERROR(G38-AM38,0) -> 0 | AR38: =IFERROR(H38-AN38,0) -> 0 | AS38: =IFERROR(I38-AO38,0) -> -0.63344961 | AU38: =Act!L37 -> -4.8106855 | AV38: =H38-AU38 -> #VALUE! | AX38: =IF('FC5+7'!S$3=1,'FC5+7'!S37,"") -> -4.9093125 | AY38: =IF('FC5+7'!T$3=1,'FC5+7'!T37,"") | AZ38: =IF('FC5+7'!U$3=1,'FC5+7'!U37,"") | BA38: =SUM(AX38:AZ38) -> -4.9093125 | BB38: =IFERROR(F38-AX38,0) -> 0 | BC38: =IFERROR(G38-AY38,0) -> 0 | BD38: =IFERROR(H38-AZ38,0) -> 0 | BE38: =IFERROR(I38-BA38,0) -> 0 | BG38: =F38 -> -4.9093125 | BH38: -3.9114145 | BI38: -7.7889689 | BJ38: =SUM(BG38:BI38) -> -16.609696 | BK38: =IFERROR(F38-AC38,0) -> 0.84629667 | BL38: =IFERROR(G38-AD38,0) -> 0 | BM38: =IFERROR(AL38-AE38,0) -> 0 | BN38: =IFERROR(I38-BJ38,0) -> 11.700383 | BP38: =F38 -> -4.9093125 | BQ38: =G38 | BR38: =#REF! -> #REF! | BS38: =SUM(BP38:BR38) -> #REF! | BT38: =BP38-AC38 -> 0.84629667 | BU38: =BQ38-AD38 -> #VALUE! | BV38: =BR38-AE38 -> #REF! | BW38: =BS38-AF38 -> #REF! | BY38: =H38-BR38 -> #VALUE! | CA38: ='FC2+10'!AA37 -> -22.866055 | CC38: =CA38-I38 -> -17.956743 | CE38: =IF('FC7+5'!S$3=1,'FC7+5'!S37,"") -> -4.9093125 | CF38: =IF('FC7+5'!T$3=1,'FC7+5'!T37,"") | CG38: =IF('FC7+5'!U$3=1,'FC7+5'!U37,"") | CH38: =SUM(CE38:CG38) -> -4.9093125 | CI38: =IFERROR(F38-CE38,0) -> 0 | CJ38: =IFERROR(G38-CF38,0) -> 0 | CK38: =IFERROR(H38-CG38,0) -> 0 | CL38: =IFERROR(I38-CH38,0) -> 0 | CM38: =IF('FC7+5'!AC$3=1,'FC7+5'!AC37,"") -> -21.949221 | CN38: =I38-CM38 -> 17.039908
C39: FMI Total | F39: =SUM(F36:F38) -> -26.178037 | G39: =SUM(G36:G38) -> 0 | H39: =SUM(H36:H38) -> 0 | I39: =SUM(F39:H39) -> -26.178037 | K39: =SUM(K36:K38) -> -29.593786 | L39: =SUM(L36:L38) -> 0 | M39: =SUM(M36:M38) -> 0 | N39: =SUM(K39:M39) -> -29.593786 | O39: =IFERROR(F39-K39,0) -> 3.4157491 | P39: =IFERROR(G39-L39,0) -> 0 | Q39: =IFERROR(H39-M39,0) -> 0 | R39: =I39-N39 -> 3.4157491 | T39: =SUM(T36:T38) -> -26.178037 | U39: =SUM(U36:U38) -> 0 | V39: =SUM(V36:V38) -> 0 | W39: =SUM(T39:V39) -> -26.178037 | X39: =IFERROR(F39-T39,0) -> 0 | Y39: =IFERROR(G39-U39,0) -> 0 | Z39: =IFERROR(H39-V39,0) -> 0 | AA39: =I39-W39 -> 0 | AC39: =SUM(AC36:AC38) -> -31.792196 | AD39: =SUM(AD36:AD38) -> -35.002495 | AE39: =SUM(AE36:AE38) -> 0 | AF39: =SUM(AC39:AE39) -> -66.794691 | AG39: =IFERROR(F39-AC39,0) -> 5.6141593 | AH39: =IFERROR(G39-AD39,0) -> 35.002495 | AI39: =IFERROR(H39-AE39,0) -> 0 | AJ39: =IFERROR(I39-AF39,0) -> 40.616654 | AL39: =SUM(AL36:AL38) -> -34.090336 | AM39: =SUM(AM36:AM38) -> 0 | AN39: =SUM(AN36:AN38) -> 0 | AO39: =SUM(AL39:AN39) -> -34.090336 | AP39: =IFERROR(F39-AL39,0) -> 7.9122995 | AQ39: =IFERROR(G39-AM39,0) -> 0 | AR39: =IFERROR(H39-AN39,0) -> 0 | AS39: =IFERROR(I39-AO39,0) -> 7.9122995 | AU39: =Act!L38 -> -28.762429 | AV39: =H39-AU39 -> 28.762429 | AX39: =SUM(AX36:AX38) -> -26.178037 | AY39: =SUM(AY36:AY38) -> 0 | AZ39: =SUM(AZ36:AZ38) -> 0 | BA39: =SUM(AX39:AZ39) -> -26.178037 | BB39: =IFERROR(F39-AX39,0) -> 0 | BC39: =IFERROR(G39-AY39,0) -> 0 | BD39: =IFERROR(H39-AZ39,0) -> 0 | BE39: =IFERROR(I39-BA39,0) -> 0 | BG39: =F39 -> -26.178037 | BH39: -31.625624 | BI39: -42.22749 | BJ39: =SUM(BG39:BI39) -> -100.03115 | BK39: =IFERROR(F39-AC39,0) -> 5.6141593 | BL39: =IFERROR(G39-AD39,0) -> 35.002495 | BM39: =IFERROR(AL39-AE39,0) -> -34.090336 | BN39: =IFERROR(I39-BJ39,0) -> 73.853114 | BP39: =F39 -> -26.178037 | BQ39: =G39 -> 0 | BR39: =#REF! -> #REF! | BS39: =SUM(BP39:BR39) -> #REF! | BT39: =BP39-AC39 -> 5.6141593 | BU39: =BQ39-AD39 -> 35.002495 | BV39: =BR39-AE39 -> #REF! | BW39: =BS39-AF39 -> #REF! | BY39: =H39-BR39 -> #REF! | CA39: ='FC2+10'!AA38 -> -108.46823 | CC39: =CA39-I39 -> -82.290189 | CE39: =SUM(CE36:CE38) -> -26.178037 | CF39: =SUM(CF36:CF38) -> 0 | CG39: =SUM(CG36:CG38) -> 0 | CH39: =SUM(CE39:CG39) -> -26.178037 | CI39: =IFERROR(F39-CE39,0) -> 0 | CJ39: =IFERROR(G39-CF39,0) -> 0 | CK39: =IFERROR(H39-CG39,0) -> 0 | CL39: =IFERROR(I39-CH39,0) -> 0 | CM39: =SUM(CM36:CM38) -> -99.308567 | CN39: =I39-CM39 -> 73.13053
D40: *GNX G&A (Global Function Cost) | AU40: =Act!L39 -> 0 | AV40: =H40-AU40 -> 0 | BY40: =H40-BR40 -> 0 | CA40: ='FC2+10'!AA39 -> 0 | CC40: =CA40-I40 -> 0 | CN40: =I40-CM40 -> 0
D41: Global AS | AU41: =Act!L40 -> 0 | AV41: =H41-AU41 -> 0 | BY41: =H41-BR41 -> 0 | CA41: ='FC2+10'!AA40 -> 0 | CC41: =CA41-I41 -> 0 | CN41: =I41-CM41 -> 0
D42: G&A (region) | F42: =IF(Act!S$3=1,Act!S41,"") -> -37.389421 | G42: =IF(Act!T$3=1,Act!T41,"") | H42: =IF(Act!U$3=1,Act!U41,"") | I42: =SUM(F42:H42) -> -37.389421 | K42: =IF(BP!S$3=1,BP!S41,"") -> -33.444606 | L42: =IF(BP!T$3=1,BP!T41,"") | M42: =IF(BP!U$3=1,BP!U41,"") | N42: =SUM(K42:M42) -> -33.444606 | O42: =IFERROR(F42-K42,0) -> -3.9448152 | P42: =IFERROR(G42-L42,0) -> 0 | Q42: =IFERROR(H42-M42,0) -> 0 | R42: =I42-N42 -> -3.9448152 | T42: =IF('FC2+10'!S$3=1,'FC2+10'!S41,"") -> -37.389421 | U42: =IF('FC2+10'!T$3=1,'FC2+10'!T41,"") | V42: =IF('FC2+10'!U$3=1,'FC2+10'!U41,"") | W42: =SUM(T42:V42) -> -37.389421 | X42: =IFERROR(F42-T42,0) -> 0 | Y42: =IFERROR(G42-U42,0) -> 0 | Z42: =IFERROR(H42-V42,0) -> 0 | AA42: =I42-W42 -> 0 | AC42: =IF(OL!S$3=1,OL!S41,"") -> -34.384496 | AD42: =IF(OL!T$3=1,OL!T41,"") -> -32.015299 | AE42: =IF(OL!U$3=1,OL!U41,"") | AF42: =SUM(AC42:AE42) -> -66.399796 | AG42: =IFERROR(F42-AC42,0) -> -3.0049245 | AH42: =IFERROR(G42-AD42,0) -> 0 | AI42: =IFERROR(H42-AE42,0) -> 0 | AJ42: =IFERROR(I42-AF42,0) -> 29.010375 | AL42: =IF(LY!S$3=1,LY!S41,"") -> -36.348637 | AM42: =IF(LY!T$3=1,LY!T41,"") | AN42: =IF(LY!U$3=1,LY!U41,"") | AO42: =SUM(AL42:AN42) -> -36.348637 | AP42: =IFERROR(F42-AL42,0) -> -1.0407835 | AQ42: =IFERROR(G42-AM42,0) -> 0 | AR42: =IFERROR(H42-AN42,0) -> 0 | AS42: =IFERROR(I42-AO42,0) -> -1.0407835 | AU42: =Act!L41 -> -33.939043 | AV42: =H42-AU42 -> #VALUE! | AX42: =IF('FC5+7'!S$3=1,'FC5+7'!S41,"") -> -37.389421 | AY42: =IF('FC5+7'!T$3=1,'FC5+7'!T41,"") | AZ42: =IF('FC5+7'!U$3=1,'FC5+7'!U41,"") | BA42: =SUM(AX42:AZ42) -> -37.389421 | BB42: =IFERROR(F42-AX42,0) -> 0 | BC42: =IFERROR(G42-AY42,0) -> 0 | BD42: =IFERROR(H42-AZ42,0) -> 0 | BE42: =IFERROR(I42-BA42,0) -> 0 | BG42: =F42 -> -37.389421 | BH42: -30.12 | BI42: -35.61 | BJ42: =SUM(BG42:BI42) -> -103.11942 | BK42: =IFERROR(F42-AC42,0) -> -3.0049245 | BL42: =IFERROR(G42-AD42,0) -> 0 | BM42: =IFERROR(AL42-AE42,0) -> 0 | BN42: =IFERROR(I42-BJ42,0) -> 65.73 | BP42: =F42 -> -37.389421 | BQ42: =G42 | BR42: =#REF! -> #REF! | BS42: =SUM(BP42:BR42) -> #REF! | BT42: =BP42-AC42 -> -3.0049245 | BU42: =BQ42-AD42 -> #VALUE! | BV42: =BR42-AE42 -> #REF! | BW42: =BS42-AF42 -> #REF! | BY42: =H42-BR42 -> #VALUE! | CA42: ='FC2+10'!AA41 -> -92.724438 | CC42: =CA42-I42 -> -55.335017 | CE42: =IF('FC7+5'!S$3=1,'FC7+5'!S41,"") -> -37.389421 | CF42: =IF('FC7+5'!T$3=1,'FC7+5'!T41,"") | CG42: =IF('FC7+5'!U$3=1,'FC7+5'!U41,"") | CH42: =SUM(CE42:CG42) -> -37.389421 | CI42: =IFERROR(F42-CE42,0) -> 0 | CJ42: =IFERROR(G42-CF42,0) -> 0 | CK42: =IFERROR(H42-CG42,0) -> 0 | CL42: =IFERROR(I42-CH42,0) -> 0 | CM42: =IF('FC7+5'!AC$3=1,'FC7+5'!AC41,"") -> -94.791248 | CN42: =I42-CM42 -> 57.401827
D43: Credit Loss / Provision | AC43: =IF(OL!S$3=1,OL!S42,"") -> 0 | AD43: =IF(OL!T$3=1,OL!T42,"") -> 0 | AE43: =IF(OL!U$3=1,OL!U42,"") | AU43: =Act!L42 -> 0 | AV43: =H43-AU43 -> 0 | BY43: =H43-BR43 -> 0 | CA43: ='FC2+10'!AA42 -> 0 | CC43: =CA43-I43 -> 0 | CN43: =I43-CM43 -> 0
D44: G&A out of function scope | F44: =IF(Act!S$3=1,Act!S43,"") -> 2.2106839 | G44: =IF(Act!T$3=1,Act!T43,"") | H44: =IF(Act!U$3=1,Act!U43,"") | I44: =SUM(F44:H44) -> 2.2106839 | K44: =IF(BP!S$3=1,BP!S43,"") -> 2.9672614 | L44: =IF(BP!T$3=1,BP!T43,"") | M44: =IF(BP!U$3=1,BP!U43,"") | N44: =SUM(K44:M44) -> 2.9672614 | O44: =IFERROR(F44-K44,0) -> -0.7565775 | P44: =IFERROR(G44-L44,0) -> 0 | Q44: =IFERROR(H44-M44,0) -> 0 | R44: =I44-N44 -> -0.7565775 | T44: =IF('FC2+10'!S$3=1,'FC2+10'!S43,"") -> 2.2106839 | U44: =IF('FC2+10'!T$3=1,'FC2+10'!T43,"") | V44: =IF('FC2+10'!U$3=1,'FC2+10'!U43,"") | W44: =SUM(T44:V44) -> 2.2106839 | X44: =IFERROR(F44-T44,0) -> 4.2632564e-14 | Y44: =IFERROR(G44-U44,0) -> 0 | Z44: =IFERROR(H44-V44,0) -> 0 | AA44: =I44-W44 -> 4.2632564e-14 | AC44: =IF(OL!S$3=1,OL!S43,"") -> 1.1941014 | AD44: =IF(OL!T$3=1,OL!T43,"") -> 1.5284343 | AE44: =IF(OL!U$3=1,OL!U43,"") | AF44: =SUM(AC44:AE44) -> 2.7225357 | AG44: =IFERROR(F44-AC44,0) -> 1.0165825 | AH44: =IFERROR(G44-AD44,0) -> 0 | AI44: =IFERROR(H44-AE44,0) -> 0 | AJ44: =IFERROR(I44-AF44,0) -> -0.51185178 | AL44: =IF(LY!S$3=1,LY!S43,"") -> 2.2319049 | AM44: =IF(LY!T$3=1,LY!T43,"") | AN44: =IF(LY!U$3=1,LY!U43,"") | AO44: =SUM(AL44:AN44) -> 2.2319049 | AP44: =IFERROR(F44-AL44,0) -> -0.021221002 | AQ44: =IFERROR(G44-AM44,0) -> 0 | AR44: =IFERROR(H44-AN44,0) -> 0 | AS44: =IFERROR(I44-AO44,0) -> -0.021221002 | AU44: =Act!L43 -> 1.0520793 | AV44: =H44-AU44 -> #VALUE! | AX44: =IF('FC5+7'!S$3=1,'FC5+7'!S43,"") -> 2.2106839 | AY44: =IF('FC5+7'!T$3=1,'FC5+7'!T43,"") | AZ44: =IF('FC5+7'!U$3=1,'FC5+7'!U43,"") | BA44: =SUM(AX44:AZ44) -> 2.2106839 | BB44: =IFERROR(F44-AX44,0) -> 4.2632564e-14 | BC44: =IFERROR(G44-AY44,0) -> 0 | BD44: =IFERROR(H44-AZ44,0) -> 0 | BE44: =IFERROR(I44-BA44,0) -> 4.2632564e-14 | BG44: =F44 -> 2.2106839 | BH44: 2.45 | BI44: 2.45 | BJ44: =SUM(BG44:BI44) -> 7.1106839 | BK44: =IFERROR(F44-AC44,0) -> 1.0165825 | BL44: =IFERROR(G44-AD44,0) -> 0 | BM44: =IFERROR(AL44-AE44,0) -> 0 | BN44: =IFERROR(I44-BJ44,0) -> -4.9 | BP44: =F44 -> 2.2106839 | BQ44: =G44 | BR44: =#REF! -> #REF! | BS44: =SUM(BP44:BR44) -> #REF! | BT44: =BP44-AC44 -> 1.0165825 | BU44: =BQ44-AD44 -> #VALUE! | BV44: =BR44-AE44 -> #REF! | BW44: =BS44-AF44 -> #REF! | BY44: =H44-BR44 -> #VALUE! | CA44: ='FC2+10'!AA43 -> 4.9453322 | CC44: =CA44-I44 -> 2.7346483 | CE44: =IF('FC7+5'!S$3=1,'FC7+5'!S43,"") -> 2.2106839 | CF44: =IF('FC7+5'!T$3=1,'FC7+5'!T43,"") | CG44: =IF('FC7+5'!U$3=1,'FC7+5'!U43,"") | CH44: =SUM(CE44:CG44) -> 2.2106839 | CI44: =IFERROR(F44-CE44,0) -> 0 | CJ44: =IFERROR(G44-CF44,0) -> 0 | CK44: =IFERROR(H44-CG44,0) -> 0 | CL44: =IFERROR(I44-CH44,0) -> 0 | CM44: =IF('FC7+5'!AC$3=1,'FC7+5'!AC43,"") -> 4.5390001 | CN44: =I44-CM44 -> -2.3283162
C45: G&A Total | F45: =SUM(F40:F44) -> -35.178737 | G45: =SUM(G40:G44) -> 0 | H45: =SUM(H40:H44) -> 0 | I45: =SUM(F45:H45) -> -35.178737 | K45: =SUM(K40:K44) -> -30.477344 | L45: =SUM(L40:L44) -> 0 | M45: =SUM(M40:M44) -> 0 | N45: =SUM(K45:M45) -> -30.477344 | O45: =IFERROR(F45-K45,0) -> -4.7013927 | P45: =IFERROR(G45-L45,0) -> 0 | Q45: =IFERROR(H45-M45,0) -> 0 | R45: =I45-N45 -> -4.7013927 | T45: =SUM(T40:T44) -> -35.178737 | U45: =SUM(U40:U44) -> 0 | V45: =SUM(V40:V44) -> 0 | W45: =SUM(T45:V45) -> -35.178737 | X45: =IFERROR(F45-T45,0) -> 4.2632564e-14 | Y45: =IFERROR(G45-U45,0) -> 0 | Z45: =IFERROR(H45-V45,0) -> 0 | AA45: =I45-W45 -> 0 | AC45: =SUM(AC40:AC44) -> -33.190395 | AD45: =SUM(AD40:AD44) -> -30.486865 | AE45: =SUM(AE40:AE44) -> 0 | AF45: =SUM(AC45:AE45) -> -63.67726 | AG45: =IFERROR(F45-AC45,0) -> -1.9883421 | AH45: =IFERROR(G45-AD45,0) -> 30.486865 | AI45: =IFERROR(H45-AE45,0) -> 0 | AJ45: =IFERROR(I45-AF45,0) -> 28.498523 | AL45: =SUM(AL40:AL44) -> -34.116733 | AM45: =SUM(AM40:AM44) -> 0 | AN45: =SUM(AN40:AN44) -> 0 | AO45: =SUM(AL45:AN45) -> -34.116733 | AP45: =IFERROR(F45-AL45,0) -> -1.0620045 | AQ45: =IFERROR(G45-AM45,0) -> 0 | AR45: =IFERROR(H45-AN45,0) -> 0 | AS45: =IFERROR(I45-AO45,0) -> -1.0620045 | AU45: =Act!L44 -> -32.886964 | AV45: =H45-AU45 -> 32.886964 | AX45: =SUM(AX40:AX44) -> -35.178737 | AY45: =SUM(AY40:AY44) -> 0 | AZ45: =SUM(AZ40:AZ44) -> 0 | BA45: =SUM(AX45:AZ45) -> -35.178737 | BB45: =IFERROR(F45-AX45,0) -> 4.2632564e-14 | BC45: =IFERROR(G45-AY45,0) -> 0 | BD45: =IFERROR(H45-AZ45,0) -> 0 | BE45: =IFERROR(I45-BA45,0) -> 4.2632564e-14 | BG45: =F45 -> -35.178737 | BH45: -27.67 | BI45: -33.16 | BJ45: =SUM(BG45:BI45) -> -96.008737 | BK45: =IFERROR(F45-AC45,0) -> -1.9883421 | BL45: =IFERROR(G45-AD45,0) -> 30.486865 | BM45: =IFERROR(AL45-AE45,0) -> -34.116733 | BN45: =IFERROR(I45-BJ45,0) -> 60.83 | BP45: =F45 -> -35.178737 | BQ45: =G45 -> 0 | BR45: =#REF! -> #REF! | BS45: =SUM(BP45:BR45) -> #REF! | BT45: =BP45-AC45 -> -1.9883421 | BU45: =BQ45-AD45 -> 30.486865 | BV45: =BR45-AE45 -> #REF! | BW45: =BS45-AF45 -> #REF! | BY45: =H45-BR45 -> #REF! | CA45: ='FC2+10'!AA44 -> -87.779106 | CC45: =CA45-I45 -> -52.600369 | CE45: =SUM(CE40:CE44) -> -35.178737 | CF45: =SUM(CF40:CF44) -> 0 | CG45: =SUM(CG40:CG44) -> 0 | CH45: =SUM(CE45:CG45) -> -35.178737 | CI45: =IFERROR(F45-CE45,0) -> 0 | CJ45: =IFERROR(G45-CF45,0) -> 0 | CK45: =IFERROR(H45-CG45,0) -> 0 | CL45: =IFERROR(I45-CH45,0) -> 0 | CM45: =SUM(CM40:CM44) -> -90.252248 | CN45: =I45-CM45 -> 55.073511
B46: Fixed Cost Total | F46: =SUM(F45,F39,F35) -> -128.4713 | G46: =SUM(G45,G39,G35) -> 0 | H46: =SUM(H45,H39,H35) -> 0 | I46: =SUM(F46:H46) -> -128.4713 | K46: =SUM(K45,K39,K35) -> -145.46811 | L46: =SUM(L45,L39,L35) -> 0 | M46: =SUM(M45,M39,M35) -> 0 | N46: =SUM(K46:M46) -> -145.46811 | O46: =IFERROR(F46-K46,0) -> 16.996808 | P46: =IFERROR(G46-L46,0) -> 0 | Q46: =IFERROR(H46-M46,0) -> 0 | R46: =I46-N46 -> 16.996808 | T46: =SUM(T45,T39,T35) -> -128.4713 | U46: =SUM(U45,U39,U35) -> 0 | V46: =SUM(V45,V39,V35) -> 0 | W46: =SUM(T46:V46) -> -128.4713 | X46: =IFERROR(F46-T46,0) -> 2.8421709e-14 | Y46: =IFERROR(G46-U46,0) -> 0 | Z46: =IFERROR(H46-V46,0) -> 0 | AA46: =I46-W46 -> 0 | AC46: =SUM(AC45,AC39,AC35) -> -114.02454 | AD46: =SUM(AD45,AD39,AD35) -> -117.86248 | AE46: =SUM(AE45,AE39,AE35) -> 0 | AF46: =SUM(AC46:AE46) -> -231.88702 | AG46: =IFERROR(F46-AC46,0) -> -14.446764 | AH46: =IFERROR(G46-AD46,0) -> 117.86248 | AI46: =IFERROR(H46-AE46,0) -> 0 | AJ46: =IFERROR(I46-AF46,0) -> 103.41572 | AL46: =SUM(AL45,AL39,AL35) -> -120.99759 | AM46: =SUM(AM45,AM39,AM35) -> 0 | AN46: =SUM(AN45,AN39,AN35) -> 0 | AO46: =SUM(AL46:AN46) -> -120.99759 | AP46: =IFERROR(F46-AL46,0) -> -7.4737124 | AQ46: =IFERROR(G46-AM46,0) -> 0 | AR46: =IFERROR(H46-AN46,0) -> 0 | AS46: =IFERROR(I46-AO46,0) -> -7.4737124 | AU46: =Act!L45 -> -105.8847 | AV46: =H46-AU46 -> 105.8847 | AX46: =SUM(AX45,AX39,AX35) -> -128.4713 | AY46: =SUM(AY45,AY39,AY35) -> 0 | AZ46: =SUM(AZ45,AZ39,AZ35) -> 0 | BA46: =SUM(AX46:AZ46) -> -128.4713 | BB46: =IFERROR(F46-AX46,0) -> 2.8421709e-14 | BC46: =IFERROR(G46-AY46,0) -> 0 | BD46: =IFERROR(H46-AZ46,0) -> 0 | BE46: =IFERROR(I46-BA46,0) -> 2.8421709e-14 | BG46: =F46 -> -128.4713 | BH46: -108.38943 | BI46: -130.01969 | BJ46: =SUM(BG46:BI46) -> -366.88042 | BK46: =IFERROR(F46-AC46,0) -> -14.446764 | BL46: =IFERROR(G46-AD46,0) -> 117.86248 | BM46: =IFERROR(AL46-AE46,0) -> -120.99759 | BN46: =IFERROR(I46-BJ46,0) -> 238.40912 | BP46: =F46 -> -128.4713 | BQ46: =G46 -> 0 | BR46: =#REF! -> #REF! | BS46: =SUM(BP46:BR46) -> #REF! | BT46: =BP46-AC46 -> -14.446764 | BU46: =BQ46-AD46 -> 117.86248 | BV46: =BR46-AE46 -> #REF! | BW46: =BS46-AF46 -> #REF! | BY46: =H46-BR46 -> #REF! | CA46: ='FC2+10'!AA45 -> -333.28428 | CC46: =CA46-I46 -> -204.81297 | CE46: =SUM(CE45,CE39,CE35) -> -128.4713 | CF46: =SUM(CF45,CF39,CF35) -> 0 | CG46: =SUM(CG45,CG39,CG35) -> 0 | CH46: =SUM(CE46:CG46) -> -128.4713 | CI46: =IFERROR(F46-CE46,0) -> 0 | CJ46: =IFERROR(G46-CF46,0) -> 0 | CK46: =IFERROR(H46-CG46,0) -> 0 | CL46: =IFERROR(I46-CH46,0) -> 0 | CM46: =SUM(CM45,CM39,CM35) -> -330.89687 | CN46: =I46-CM46 -> 202.42557
B47: CMP-I + Fixed Cost | F47: =F27+F46 -> -42.387685 | G47: =G27+G46 -> 0 | H47: =H27+H46 -> 0 | I47: =SUM(F47:H47) -> -42.387685 | K47: =K27+K46 -> -57.951486 | L47: =L27+L46 -> 0 | M47: =M27+M46 -> 0 | N47: =SUM(K47:M47) -> -57.951486 | O47: =IFERROR(F47-K47,0) -> 15.563801 | P47: =IFERROR(G47-L47,0) -> 0 | Q47: =IFERROR(H47-M47,0) -> 0 | R47: =I47-N47 -> 15.563801 | T47: =T27+T46 -> #VALUE! | U47: =U27+U46 -> 0 | V47: =V27+V46 -> 0 | W47: =SUM(T47:V47) -> #VALUE! | X47: =IFERROR(F47-T47,0) -> 0 | Y47: =IFERROR(G47-U47,0) -> 0 | Z47: =IFERROR(H47-V47,0) -> 0 | AA47: =I47-W47 -> #VALUE! | AC47: =AC27+AC46 -> 30.258471 | AD47: =AD27+AD46 -> 23.286652 | AE47: =AE27+AE46 -> 0 | AF47: =SUM(AC47:AE47) -> 53.545123 | AG47: =IFERROR(F47-AC47,0) -> -72.646156 | AH47: =IFERROR(G47-AD47,0) -> -23.286652 | AI47: =IFERROR(H47-AE47,0) -> 0 | AJ47: =IFERROR(I47-AF47,0) -> -95.932808 | AL47: =AL27+AL46 -> 35.570225 | AM47: =AM27+AM46 -> 0 | AN47: =AN27+AN46 -> 0 | AO47: =SUM(AL47:AN47) -> 35.570225 | AP47: =IFERROR(F47-AL47,0) -> -77.95791 | AQ47: =IFERROR(G47-AM47,0) -> 0 | AR47: =IFERROR(H47-AN47,0) -> 0 | AS47: =IFERROR(I47-AO47,0) -> -77.95791 | AU47: =Act!L46 -> 30.690192 | AV47: =H47-AU47 -> -30.690192 | AX47: =AX27+AX46 -> -42.387685 | AY47: =AY27+AY46 -> 0 | AZ47: =AZ27+AZ46 -> 0 | BA47: =SUM(AX47:AZ47) -> -42.387685 | BB47: =IFERROR(F47-AX47,0) -> 2.8421709e-14 | BC47: =IFERROR(G47-AY47,0) -> 0 | BD47: =IFERROR(H47-AZ47,0) -> 0 | BE47: =IFERROR(I47-BA47,0) -> 2.8421709e-14 | BG47: =F47 -> -42.387685 | BH47: 14.407849 | BI47: -59.715038 | BJ47: =SUM(BG47:BI47) -> -87.694873 | BK47: =IFERROR(F47-AC47,0) -> -72.646156 | BL47: =IFERROR(G47-AD47,0) -> -23.286652 | BM47: =IFERROR(AL47-AE47,0) -> 35.570225 | BN47: =IFERROR(I47-BJ47,0) -> 45.307189 | BP47: =F47 -> -42.387685 | BQ47: =G47 -> 0 | BR47: =#REF! -> #REF! | BS47: =SUM(BP47:BR47) -> #REF! | BT47: =BP47-AC47 -> -72.646156 | BU47: =BQ47-AD47 -> -23.286652 | BV47: =BR47-AE47 -> #REF! | BW47: =BS47-AF47 -> #REF! | BY47: =H47-BR47 -> #REF! | CA47: ='FC2+10'!AA46 -> #VALUE! | CC47: =CA47-I47 -> #VALUE! | CE47: =CE27+CE46 -> -42.387685 | CF47: =CF27+CF46 -> 0 | CG47: =CG27+CG46 -> 0 | CH47: =SUM(CE47:CG47) -> -42.387685 | CI47: =IFERROR(F47-CE47,0) -> 0 | CJ47: =IFERROR(G47-CF47,0) -> 0 | CK47: =IFERROR(H47-CG47,0) -> 0 | CL47: =IFERROR(I47-CH47,0) -> 0 | CM47: =CM27+CM46 -> 228.88044 | CN47: =I47-CM47 -> -271.26813
C48: % of Net Sales | F48: =F47/F23 -> -0.080441018 | G48: =G47/G23 -> #DIV/0! | H48: =H47/H23 -> #DIV/0! | I48: =I47/I23 -> -0.080441018 | K48: =K47/K23 -> -0.10152814 | L48: =L47/L23 -> #DIV/0! | M48: =M47/M23 -> #DIV/0! | N48: =N47/N23 -> -0.10152814 | O48: =IFERROR(F48-K48,0) -> 0.021087119 | P48: =IFERROR(G48-L48,0) -> 0 | Q48: =IFERROR(H48-M48,0) -> 0 | R48: =I48-N48 -> 0.021087119 | T48: =T47/T23 -> #VALUE! | U48: =U47/U23 -> #DIV/0! | V48: =V47/V23 -> #DIV/0! | W48: =W47/W23 -> #VALUE! | X48: =IFERROR(F48-T48,0) -> 0 | Y48: =IFERROR(G48-U48,0) -> 0 | Z48: =IFERROR(H48-V48,0) -> 0 | AA48: =I48-W48 -> #VALUE! | AC48: =AC47/AC23 -> 0.041279741 | AD48: =AD47/AD23 -> 0.027178567 | AE48: =AE47/AE23 -> #DIV/0! | AF48: =AF47/AF23 -> 0.033680155 | AG48: =IFERROR(F48-AC48,0) -> -0.12172076 | AH48: =IFERROR(G48-AD48,0) -> 0 | AI48: =IFERROR(H48-AE48,0) -> 0 | AJ48: =IFERROR(I48-AF48,0) -> -0.11412117 | AL48: =AL47/AL23 -> 0.054468617 | AM48: =AM47/AM23 -> #DIV/0! | AN48: =AN47/AN23 -> #DIV/0! | AO48: =AO47/AO23 -> 0.054468617 | AP48: =IFERROR(F48-AL48,0) -> -0.13490964 | AQ48: =IFERROR(G48-AM48,0) -> 0 | AR48: =IFERROR(H48-AN48,0) -> 0 | AS48: =IFERROR(I48-AO48,0) -> -0.13490964 | AU48: =Act!L47 -> 0.03697923 | AV48: =H48-AU48 -> #DIV/0! | AX48: =AX47/AX23 -> -0.080441018 | AY48: =AY47/AY23 -> #DIV/0! | AZ48: =AZ47/AZ23 -> #DIV/0! | BA48: =BA47/BA23 -> -0.080441018 | BB48: =IFERROR(F48-AX48,0) -> 5.5511151e-17 | BC48: =IFERROR(G48-AY48,0) -> 0 | BD48: =IFERROR(H48-AZ48,0) -> 0 | BE48: =IFERROR(I48-BA48,0) -> 5.5511151e-17 | BG48: =F48 -> -0.080441018 | BH48: 0.023425942 | BI48: -0.064368095 | BJ48: =BJ47/BJ23 -> -0.042370995 | BK48: =IFERROR(F48-AC48,0) -> -0.12172076 | BL48: =IFERROR(G48-AD48,0) -> 0 | BM48: =IFERROR(AL48-AE48,0) -> 0 | BN48: =IFERROR(I48-BJ48,0) -> -0.038070023 | BP48: =F48 -> -0.080441018 | BQ48: =G48 -> #DIV/0! | BR48: =#REF! -> #REF! | BS48: =BS47/BS23 -> #REF! | BT48: =BP48-AC48 -> -0.12172076 | BU48: =BQ48-AD48 -> #DIV/0! | BV48: =BR48-AE48 -> #REF! | BW48: =BS48-AF48 -> #REF! | BY48: =H48-BR48 -> #DIV/0! | CA48: ='FC2+10'!AA47 -> #VALUE! | CC48: =CA48-I48 -> #VALUE! | CE48: =CE47/CE23 -> -0.080441018 | CF48: =CF47/CF23 -> #DIV/0! | CG48: =CG47/CG23 -> #DIV/0! | CH48: =CH47/CH23 -> -0.080441018 | CI48: =IFERROR(F48-CE48,0) -> 0 | CJ48: =IFERROR(G48-CF48,0) -> 0 | CK48: =IFERROR(H48-CG48,0) -> 0 | CL48: =IFERROR(I48-CH48,0) -> 0 | CM48: =CM47/CM23 -> 0.080805848 | CN48: =I48-CM48 -> -0.16124687
AE49: 0 | AU49: =Act!L48 -> 0 | AV49: =H49-AU49 -> 0 | BG49: =F49 -> 0 | BK49: =IFERROR(F49-AC49,0) -> 0 | BL49: =IFERROR(G49-AD49,0) -> 0 | BM49: =IFERROR(AL49-AE49,0) -> 0 | CA49: ='FC2+10'!AA48 -> 0 | CC49: =CA49-I49 -> 0 | CN49: =I49-CM49 -> 0
C50: R&D | R50: =F50-K50 -> 0 | AA50: =O50-T50 -> 0 | AE50: 0 | AJ50: =X50-AC50 -> 0 | AS50: =AG50-AL50 -> 0 | AU50: =Act!L49 -> 0 | AV50: =H50-AU50 -> 0 | BE50: =AS50-AX50 -> 0 | BG50: =F50 -> 0 | BK50: =IFERROR(F50-AC50,0) -> 0 | BL50: =IFERROR(G50-AD50,0) -> 0 | BM50: =IFERROR(AL50-AE50,0) -> 0 | BN50: =IFERROR(I50-BJ50,0) -> 0 | BY50: =H50-BR50 -> 0 | CA50: ='FC2+10'!AA49 -> 0 | CC50: =CA50-I50 -> 0 | CL50: =BZ50-CE50 -> 0 | CN50: =I50-CM50 -> 0
C51: RS | R51: =F51-K51 -> 0 | AA51: =O51-T51 -> 0 | AE51: 0 | AJ51: =X51-AC51 -> 0 | AS51: =AG51-AL51 -> 0 | AU51: =Act!L50 -> 0 | AV51: =H51-AU51 -> 0 | BE51: =AS51-AX51 -> 0 | BG51: =F51 -> 0 | BK51: =IFERROR(F51-AC51,0) -> 0 | BL51: =IFERROR(G51-AD51,0) -> 0 | BM51: =IFERROR(AL51-AE51,0) -> 0 | BN51: =IFERROR(I51-BJ51,0) -> 0 | BY51: =H51-BR51 -> 0 | CA51: ='FC2+10'!AA50 -> 0 | CC51: =CA51-I51 -> 0 | CL51: =BZ51-CE51 -> 0 | CN51: =I51-CM51 -> 0
C52: GNX G&A (NML Only) | R52: =F52-K52 -> 0 | AA52: =O52-T52 -> 0 | AE52: 0 | AJ52: =X52-AC52 -> 0 | AS52: =AG52-AL52 -> 0 | AU52: =Act!L51 -> 0 | AV52: =H52-AU52 -> 0 | BE52: =AS52-AX52 -> 0 | BG52: =F52 -> 0 | BK52: =IFERROR(F52-AC52,0) -> 0 | BL52: =IFERROR(G52-AD52,0) -> 0 | BM52: =IFERROR(AL52-AE52,0) -> 0 | BN52: =IFERROR(I52-BJ52,0) -> 0 | BY52: =H52-BR52 -> 0 | CA52: ='FC2+10'!AA51 -> 0 | CC52: =CA52-I52 -> 0 | CL52: =BZ52-CE52 -> 0 | CN52: =I52-CM52 -> 0
B53: Global Function Cost | F53: =SUM(F50:F52) -> 0 | R53: =F53-K53 -> 0 | AA53: =O53-T53 -> 0 | AE53: 0 | AJ53: =X53-AC53 -> 0 | AS53: =AG53-AL53 -> 0 | AU53: =Act!L52 -> 0 | AV53: =H53-AU53 -> 0 | BE53: =AS53-AX53 -> 0 | BG53: =F53 -> 0 | BK53: =IFERROR(F53-AC53,0) -> 0 | BL53: =IFERROR(G53-AD53,0) -> 0 | BM53: =IFERROR(AL53-AE53,0) -> 0 | BN53: =IFERROR(I53-BJ53,0) -> 0 | BY53: =H53-BR53 -> 0 | CA53: ='FC2+10'!AA52 -> 0 | CC53: =CA53-I53 -> 0 | CL53: =BZ53-CE53 -> 0 | CN53: =I53-CM53 -> 0
AE54: 0 | BG54: =F54 -> 0 | BK54: =IFERROR(F54-AC54,0) -> 0 | BL54: =IFERROR(G54-AD54,0) -> 0 | BM54: =IFERROR(AL54-AE54,0) -> 0 | CA54: ='FC2+10'!AA53 -> 0 | CC54: =CA54-I54 -> 0
B55: ROP (PKG) | F55: =IF(Act!S$3=1,Act!S54,"") -> -71.169814 | G55: =IF(Act!T$3=1,Act!T54,"") | H55: =IF(Act!U$3=1,Act!U54,"") | I55: =SUM(F55:H55) -> -71.169814 | K55: =IF(BP!S$3=1,BP!S54,"") -> -88.502036 | L55: =IF(BP!T$3=1,BP!T54,"") | M55: =IF(BP!U$3=1,BP!U54,"") | N55: =SUM(K55:M55) -> -88.502036 | O55: =IFERROR(F55-K55,0) -> 17.332222 | P55: =IFERROR(G55-L55,0) -> 0 | Q55: =IFERROR(H55-M55,0) -> 0 | R55: =I55-N55 -> 17.332222 | T55: =IF('FC2+10'!S$3=1,'FC2+10'!S54,"") -> -71.169814 | U55: =IF('FC2+10'!T$3=1,'FC2+10'!T54,"") | V55: =IF('FC2+10'!U$3=1,'FC2+10'!U54,"") | W55: =SUM(T55:V55) -> -71.169814 | X55: =IFERROR(F55-T55,0) -> 0 | Y55: =IFERROR(G55-U55,0) -> 0 | Z55: =IFERROR(H55-V55,0) -> 0 | AA55: =I55-W55 -> 0 | AC55: =IF(OL!S$3=1,OL!S54,"") -> -14.941574 | AD55: =IF(OL!T$3=1,OL!T54,"") -> -36.937775 | AE55: =IF(OL!U$3=1,OL!U54,"") | AF55: =SUM(AC55:AE55) -> -51.879349 | AG55: =IFERROR(F55-AC55,0) -> -56.22824 | AH55: =IFERROR(G55-AD55,0) -> 0 | AI55: =IFERROR(H55-AE55,0) -> 0 | AJ55: =IFERROR(I55-AF55,0) -> -19.290466 | AL55: =IF(LY!S$3=1,LY!S54,"") -> -36.381776 | AM55: =IF(LY!T$3=1,LY!T54,"") | AN55: =IF(LY!U$3=1,LY!U54,"") | AO55: =SUM(AL55:AN55) -> -36.381776 | AP55: =IFERROR(F55-AL55,0) -> -34.788039 | AQ55: =IFERROR(G55-AM55,0) -> 0 | AR55: =IFERROR(H55-AN55,0) -> 0 | AS55: =IFERROR(I55-AO55,0) -> -34.788039 | AU55: =Act!L54 -> -27.709237 | AV55: =H55-AU55 -> #VALUE! | AX55: =IF('FC5+7'!S$3=1,'FC5+7'!S54,"") -> -71.169814 | AY55: =IF('FC5+7'!T$3=1,'FC5+7'!T54,"") | AZ55: =IF('FC5+7'!U$3=1,'FC5+7'!U54,"") | BA55: =SUM(AX55:AZ55) -> -71.169814 | BB55: =IFERROR(F55-AX55,0) -> 0 | BC55: =IFERROR(G55-AY55,0) -> 0 | BD55: =IFERROR(H55-AZ55,0) -> 0 | BE55: =IFERROR(I55-BA55,0) -> 0 | BG55: =F55 -> -71.169814 | BH55: -1.589126 | BI55: -84.88563 | BJ55: =SUM(BG55:BI55) -> -157.64457 | BK55: =IFERROR(F55-AC55,0) -> -56.22824 | BL55: =IFERROR(G55-AD55,0) -> 0 | BM55: =IFERROR(AL55-AE55,0) -> 0 | BN55: =IFERROR(I55-BJ55,0) -> 86.474756 | BP55: -89.070287 | BQ55: -33.835182 | BR55: -69.825243 | BS55: =SUM(BP55:BR55) -> -192.73071 | BT55: =BP55-AC55 -> -74.128713 | BU55: =BQ55-AD55 -> 3.1025923 | BV55: =BR55-AE55 -> #VALUE! | BW55: =BS55-AF55 -> -140.85136 | BY55: =H55-BR55 -> #VALUE! | CA55: ='FC2+10'!AA54 -> -35.984672 | CC55: =CA55-I55 -> 35.185142 | CE55: =IF('FC7+5'!S$3=1,'FC7+5'!S54,"") -> -71.169814 | CF55: =IF('FC7+5'!T$3=1,'FC7+5'!T54,"") | CG55: =IF('FC7+5'!U$3=1,'FC7+5'!U54,"") | CH55: =SUM(CE55:CG55) -> -71.169814 | CI55: =IFERROR(F55-CE55,0) -> 0 | CJ55: =IFERROR(G55-CF55,0) -> 0 | CK55: =IFERROR(H55-CG55,0) -> 0 | CL55: =IFERROR(I55-CH55,0) -> 0 | CM55: =IF('FC7+5'!AC$3=1,'FC7+5'!AC54,"") -> 101.13467 | CN55: =I55-CM55 -> -172.30449
AE56: =IF(OL!U$3=1,OL!U55,"") | BG56: =F56 -> 0 | BK56: =IFERROR(F56-AC56,0) -> 0 | BL56: =IFERROR(G56-AD56,0) -> 0 | BM56: =IFERROR(AL56-AE56,0) -> 0 | CA56: ='FC2+10'!AA55 -> 0 | CC56: =CA56-I56 -> 0 | CN56: =I56-CM56 -> 0
B57: * ICP (Infiniti Contribution Profit) | F57: =IF(Act!S$3=1,Act!S56,"") -> -0.031056917 | G57: =IF(Act!T$3=1,Act!T56,"") | H57: =IF(Act!U$3=1,Act!U56,"") | I57: =SUM(F57:H57) -> -0.031056917 | K57: =IF(BP!S$3=1,BP!S56,"") -> -0.058145288 | L57: =IF(BP!T$3=1,BP!T56,"") | M57: =IF(BP!U$3=1,BP!U56,"") | N57: =SUM(K57:M57) -> -0.058145288 | O57: =IFERROR(F57-K57,0) -> 0.027088371 | P57: =IFERROR(G57-L57,0) -> 0 | Q57: =IFERROR(H57-M57,0) -> 0 | R57: =I57-N57 -> 0.027088371 | T57: =IF('FC2+10'!S$3=1,'FC2+10'!S56,"") -> -0.031056917 | U57: =IF('FC2+10'!T$3=1,'FC2+10'!T56,"") | V57: =IF('FC2+10'!U$3=1,'FC2+10'!U56,"") | W57: =SUM(T57:V57) -> -0.031056917 | X57: =IFERROR(F57-T57,0) -> 0 | Y57: =IFERROR(G57-U57,0) -> 0 | Z57: =IFERROR(H57-V57,0) -> 0 | AA57: =I57-W57 -> 0 | AC57: =IF(OL!S$3=1,OL!S56,"") -> 0 | AD57: =IF(OL!T$3=1,OL!T56,"") -> 0 | AE57: =IF(OL!U$3=1,OL!U56,"") | AF57: =SUM(AC57:AE57) -> 0 | AG57: =IFERROR(F57-AC57,0) -> -0.031056917 | AH57: =IFERROR(G57-AD57,0) -> 0 | AI57: =IFERROR(H57-AE57,0) -> 0 | AJ57: =IFERROR(I57-AF57,0) -> -0.031056917 | AL57: =IF(LY!S$3=1,LY!S56,"") -> 0.007085071 | AM57: =IF(LY!T$3=1,LY!T56,"") | AN57: =IF(LY!U$3=1,LY!U56,"") | AO57: =SUM(AL57:AN57) -> 0.007085071 | AP57: =IFERROR(F57-AL57,0) -> -0.038141988 | AQ57: =IFERROR(G57-AM57,0) -> 0 | AR57: =IFERROR(H57-AN57,0) -> 0 | AS57: =IFERROR(I57-AO57,0) -> -0.038141988 | AU57: =Act!L56 -> -0.007432957 | AV57: =H57-AU57 -> #VALUE! | AX57: =IF('FC5+7'!S$3=1,'FC5+7'!S56,"") -> -0.031056917 | AY57: =IF('FC5+7'!T$3=1,'FC5+7'!T56,"") | AZ57: =IF('FC5+7'!U$3=1,'FC5+7'!U56,"") | BA57: =SUM(AX57:AZ57) -> -0.031056917 | BB57: =IFERROR(F57-AX57,0) -> 0 | BC57: =IFERROR(G57-AY57,0) -> 0 | BD57: =IFERROR(H57-AZ57,0) -> 0 | BE57: =IFERROR(I57-BA57,0) -> 0 | BG57: =F57 -> -0.031056917 | BH57: 0 | BI57: 0 | BJ57: =SUM(BG57:BI57) -> -0.031056917 | BK57: =IFERROR(F57-AC57,0) -> -0.031056917 | BL57: =IFERROR(G57-AD57,0) -> 0 | BM57: =IFERROR(AL57-AE57,0) -> 0 | BN57: =IFERROR(I57-BJ57,0) -> 0 | BP57: =F57 -> -0.031056917 | BQ57: =G57 | BR57: =#REF! -> #REF! | BS57: =SUM(BP57:BR57) -> #REF! | BT57: =BP57-AC57 -> -0.031056917 | BU57: =BQ57-AD57 -> #VALUE! | BV57: =BR57-AE57 -> #REF! | BW57: =BS57-AF57 -> #REF! | BY57: =H57-BR57 -> #VALUE! | CA57: ='FC2+10'!AA56 -> -0.21429379 | CC57: =CA57-I57 -> -0.18323687 | CE57: =IF('FC7+5'!S$3=1,'FC7+5'!S56,"") -> -0.031056917 | CF57: =IF('FC7+5'!T$3=1,'FC7+5'!T56,"") | CG57: =IF('FC7+5'!U$3=1,'FC7+5'!U56,"") | CH57: =SUM(CE57:CG57) -> -0.031056917 | CI57: =IFERROR(F57-CE57,0) -> 0 | CJ57: =IFERROR(G57-CF57,0) -> 0 | CK57: =IFERROR(H57-CG57,0) -> 0 | CL57: =IFERROR(I57-CH57,0) -> 0 | CM57: =IF('FC7+5'!AC$3=1,'FC7+5'!AC56,"") -> -0.75970874 | CN57: =I57-CM57 -> 0.72865182
AE58: 0 | BG58: =F58 -> 0 | BK58: =IFERROR(F58-AC58,0) -> 0 | BL58: =IFERROR(G58-AD58,0) -> 0 | BM58: =IFERROR(AL58-AE58,0) -> 0 | CA58: ='FC2+10'!AA57 -> 0 | CC58: =CA58-I58 -> 0
D59: CFMI | F59: =IF(Act!S$3=1,Act!S58,"") -> -1.8589675 | G59: =IF(Act!T$3=1,Act!T58,"") | H59: =IF(Act!U$3=1,Act!U58,"") | I59: =SUM(F59:H59) -> -1.8589675 | K59: =IF(BP!S$3=1,BP!S58,"") -> -1.928468 | L59: =IF(BP!T$3=1,BP!T58,"") | M59: =IF(BP!U$3=1,BP!U58,"") | N59: =SUM(K59:M59) -> -1.928468 | O59: =IFERROR(F59-K59,0) -> 0.069500511 | P59: =IFERROR(G59-L59,0) -> 0 | Q59: =IFERROR(H59-M59,0) -> 0 | R59: =SUM(O59:Q59) -> 0.069500511 | T59: =IF('FC2+10'!S$3=1,'FC2+10'!S58,"") -> -1.8589675 | U59: =IF('FC2+10'!T$3=1,'FC2+10'!T58,"") | V59: =IF('FC2+10'!U$3=1,'FC2+10'!U58,"") | W59: =SUM(T59:V59) -> -1.8589675 | X59: =IFERROR(F59-T59,0) -> 0 | Y59: =IFERROR(G59-U59,0) -> 0 | Z59: =IFERROR(H59-V59,0) -> 0 | AA59: =SUM(X59:Z59) -> 0 | AC59: =IF(OL!S$3=1,OL!S58,"") -> -0.861 | AD59: =IF(OL!T$3=1,OL!T58,"") -> -1.0695395 | AE59: =IF(OL!U$3=1,OL!U58,"") | AF59: =SUM(AC59:AE59) -> -1.9305395 | AG59: =IFERROR(F59-AC59,0) -> -0.99796746 | AH59: =IFERROR(G59-AD59,0) -> 0 | AI59: =IFERROR(H59-AE59,0) -> 0 | AJ59: =SUM(AG59:AI59) -> -0.99796746 | AL59: =IF(LY!S$3=1,LY!S58,"") -> -2.080191 | AM59: =IF(LY!T$3=1,LY!T58,"") | AN59: =IF(LY!U$3=1,LY!U58,"") | AO59: =SUM(AL59:AN59) -> -2.080191 | AP59: =IFERROR(F59-AL59,0) -> 0.22122354 | AQ59: =IFERROR(G59-AM59,0) -> 0 | AR59: =IFERROR(H59-AN59,0) -> 0 | AS59: =SUM(AP59:AR59) -> 0.22122354 | AU59: =Act!L58 -> -0.80425389 | AV59: =H59-AU59 -> #VALUE! | AX59: =IF('FC5+7'!S$3=1,'FC5+7'!S58,"") -> -1.8589675 | AY59: =IF('FC5+7'!T$3=1,'FC5+7'!T58,"") | AZ59: =IF('FC5+7'!U$3=1,'FC5+7'!U58,"") | BA59: =SUM(AX59:AZ59) -> -1.8589675 | BB59: =IFERROR(F59-AX59,0) -> 0 | BC59: =IFERROR(G59-AY59,0) -> 0 | BD59: =IFERROR(H59-AZ59,0) -> 0 | BE59: =IFERROR(I59-BA59,0) -> 0 | BG59: =F59 -> -1.8589675 | BH59: -0.93709822 | BI59: -3.3629486 | BJ59: =SUM(BG59:BI59) -> -6.1590143 | BK59: =IFERROR(F59-AC59,0) -> -0.99796746 | BL59: =IFERROR(G59-AD59,0) -> 0 | BM59: =IFERROR(AL59-AE59,0) -> 0 | BN59: =IFERROR(I59-BJ59,0) -> 4.3000469 | BP59: =F59 -> -1.8589675 | BQ59: =G59 | BR59: =#REF! -> #REF! | BS59: =SUM(BP59:BR59) -> #REF! | BT59: =BP59-AC59 -> -0.99796746 | BU59: =BQ59-AD59 -> #VALUE! | BV59: =BR59-AE59 -> #REF! | BW59: =BS59-AF59 -> #REF! | BY59: =H59-BR59 -> #VALUE! | CA59: ='FC2+10'!AA58 -> -4.4879116 | CC59: =CA59-I59 -> -2.6289442 | CE59: =IF('FC7+5'!S$3=1,'FC7+5'!S58,"") -> -1.8589675 | CF59: =IF('FC7+5'!T$3=1,'FC7+5'!T58,"") | CG59: =IF('FC7+5'!U$3=1,'FC7+5'!U58,"") | CH59: =SUM(CE59:CG59) -> -1.8589675 | CI59: =IFERROR(F59-CE59,0) -> 0 | CJ59: =IFERROR(G59-CF59,0) -> 0 | CK59: =IFERROR(H59-CG59,0) -> 0 | CL59: =IFERROR(I59-CH59,0) -> 0 | CM59: =IF('FC7+5'!AC$3=1,'FC7+5'!AC58,"") -> -6.0421471 | CN59: =I59-CM59 -> 4.1831796
D60: FMI- out of function scope | F60: =IF(Act!S$3=1,Act!S59,"") -> -3.0503451 | G60: =IF(Act!T$3=1,Act!T59,"") | H60: =IF(Act!U$3=1,Act!U59,"") | I60: =SUM(F60:H60) -> -3.0503451 | K60: =IF(BP!S$3=1,BP!S59,"") -> -3.20497 | L60: =IF(BP!T$3=1,BP!T59,"") | M60: =IF(BP!U$3=1,BP!U59,"") | N60: =SUM(K60:M60) -> -3.20497 | O60: =IFERROR(F60-K60,0) -> 0.15462498 | P60: =IFERROR(G60-L60,0) -> 0 | Q60: =IFERROR(H60-M60,0) -> 0 | R60: =SUM(O60:Q60) -> 0.15462498 | T60: =IF('FC2+10'!S$3=1,'FC2+10'!S59,"") -> -3.0503451 | U60: =IF('FC2+10'!T$3=1,'FC2+10'!T59,"") | V60: =IF('FC2+10'!U$3=1,'FC2+10'!U59,"") | W60: =SUM(T60:V60) -> -3.0503451 | X60: =IFERROR(F60-T60,0) -> 0 | Y60: =IFERROR(G60-U60,0) -> 0 | Z60: =IFERROR(H60-V60,0) -> 0 | AA60: =SUM(X60:Z60) -> 0 | AC60: =IF(OL!S$3=1,OL!S59,"") -> -4.8946092 | AD60: =IF(OL!T$3=1,OL!T59,"") -> -4.8290944 | AE60: =IF(OL!U$3=1,OL!U59,"") | AF60: =SUM(AC60:AE60) -> -9.7237035 | AG60: =IFERROR(F60-AC60,0) -> 1.8442641 | AH60: =IFERROR(G60-AD60,0) -> 0 | AI60: =IFERROR(H60-AE60,0) -> 0 | AJ60: =SUM(AG60:AI60) -> 1.8442641 | AL60: =IF(LY!S$3=1,LY!S59,"") -> -2.1956719 | AM60: =IF(LY!T$3=1,LY!T59,"") | AN60: =IF(LY!U$3=1,LY!U59,"") | AO60: =SUM(AL60:AN60) -> -2.1956719 | AP60: =IFERROR(F60-AL60,0) -> -0.85467315 | AQ60: =IFERROR(G60-AM60,0) -> 0 | AR60: =IFERROR(H60-AN60,0) -> 0 | AS60: =SUM(AP60:AR60) -> -0.85467315 | AU60: =Act!L59 -> -4.0064316 | AV60: =H60-AU60 -> #VALUE! | AX60: =IF('FC5+7'!S$3=1,'FC5+7'!S59,"") -> -3.0503451 | AY60: =IF('FC5+7'!T$3=1,'FC5+7'!T59,"") | AZ60: =IF('FC5+7'!U$3=1,'FC5+7'!U59,"") | BA60: =SUM(AX60:AZ60) -> -3.0503451 | BB60: =IFERROR(F60-AX60,0) -> 0 | BC60: =IFERROR(G60-AY60,0) -> 0 | BD60: =IFERROR(H60-AZ60,0) -> 0 | BE60: =IFERROR(I60-BA60,0) -> 0 | BG60: =F60 -> -3.0503451 | BH60: -2.9743162 | BI60: -4.4260203 | BJ60: =SUM(BG60:BI60) -> -10.450682 | BK60: =IFERROR(F60-AC60,0) -> 1.8442641 | BL60: =IFERROR(G60-AD60,0) -> 0 | BM60: =IFERROR(AL60-AE60,0) -> 0 | BN60: =IFERROR(I60-BJ60,0) -> 7.4003365 | BP60: =F60 -> -3.0503451 | BQ60: =G60 | BR60: =#REF! -> #REF! | BS60: =SUM(BP60:BR60) -> #REF! | BT60: =BP60-AC60 -> 1.8442641 | BU60: =BQ60-AD60 -> #VALUE! | BV60: =BR60-AE60 -> #REF! | BW60: =BS60-AF60 -> #REF! | BY60: =H60-BR60 -> #VALUE! | CA60: ='FC2+10'!AA59 -> -18.378144 | CC60: =CA60-I60 -> -15.327798 | CE60: =IF('FC7+5'!S$3=1,'FC7+5'!S59,"") -> -3.0503451 | CF60: =IF('FC7+5'!T$3=1,'FC7+5'!T59,"") | CG60: =IF('FC7+5'!U$3=1,'FC7+5'!U59,"") | CH60: =SUM(CE60:CG60) -> -3.0503451 | CI60: =IFERROR(F60-CE60,0) -> 0 | CJ60: =IFERROR(G60-CF60,0) -> 0 | CK60: =IFERROR(H60-CG60,0) -> 0 | CL60: =IFERROR(I60-CH60,0) -> 0 | CM60: =IF('FC7+5'!AC$3=1,'FC7+5'!AC59,"") -> -15.907073 | CN60: =I60-CM60 -> 12.856728
C61: *FMI- out of function scope (CFMI & Other) | F61: =SUM(F59:F60) -> -4.9093125 | G61: =SUM(G59:G60) -> 0 | H61: =SUM(H59:H60) -> 0 | I61: =SUM(F61:H61) -> -4.9093125 | K61: =SUM(K59:K60) -> -5.133438 | L61: =SUM(L59:L60) -> 0 | M61: =SUM(M59:M60) -> 0 | N61: =SUM(K61:M61) -> -5.133438 | O61: =SUM(O59:O60) -> 0.22412549 | P61: =SUM(P59:P60) -> 0 | Q61: =SUM(Q59:Q60) -> 0 | R61: =SUM(O61:Q61) -> 0.22412549 | T61: =SUM(T59:T60) -> -4.9093125 | U61: =SUM(U59:U60) -> 0 | V61: =SUM(V59:V60) -> 0 | W61: =SUM(T61:V61) -> -4.9093125 | X61: =SUM(X59:X60) -> 0 | Y61: =SUM(Y59:Y60) -> 0 | Z61: =SUM(Z59:Z60) -> 0 | AA61: =SUM(X61:Z61) -> 0 | AC61: =SUM(AC59:AC60) -> -5.7556092 | AD61: =SUM(AD59:AD60) -> -5.8986338 | AE61: =SUM(AE59:AE60) -> 0 | AF61: =SUM(AC61:AE61) -> -11.654243 | AG61: =IFERROR(F61-AC61,0) -> 0.84629667 | AH61: =IFERROR(G61-AD61,0) -> 5.8986338 | AI61: =IFERROR(H61-AE61,0) -> 0 | AJ61: =SUM(AG61:AI61) -> 6.7449305 | AL61: =SUM(AL59:AL60) -> -4.2758629 | AM61: =SUM(AM59:AM60) -> 0 | AN61: =SUM(AN59:AN60) -> 0 | AO61: =SUM(AL61:AN61) -> -4.2758629 | AP61: =SUM(AP59:AP60) -> -0.63344961 | AQ61: =SUM(AQ59:AQ60) -> 0 | AR61: =SUM(AR59:AR60) -> 0 | AS61: =SUM(AP61:AR61) -> -0.63344961 | AU61: =Act!L60 -> -4.8106855 | AV61: =H61-AU61 -> 4.8106855 | AX61: =SUM(AX59:AX60) -> -4.9093125 | AY61: =SUM(AY59:AY60) -> 0 | AZ61: =SUM(AZ59:AZ60) -> 0 | BA61: =SUM(AX61:AZ61) -> -4.9093125 | BB61: =IFERROR(F61-AX61,0) -> 0 | BC61: =IFERROR(G61-AY61,0) -> 0 | BD61: =IFERROR(H61-AZ61,0) -> 0 | BE61: =IFERROR(I61-BA61,0) -> 0 | BG61: =F61 -> -4.9093125 | BH61: -3.9114145 | BI61: -7.7889689 | BJ61: =SUM(BG61:BI61) -> -16.609696 | BK61: =IFERROR(F61-AC61,0) -> 0.84629667 | BL61: =IFERROR(G61-AD61,0) -> 5.8986338 | BM61: =IFERROR(AL61-AE61,0) -> -4.2758629 | BN61: =IFERROR(I61-BJ61,0) -> 11.700383 | BP61: =F61 -> -4.9093125 | BQ61: =G61 -> 0 | BR61: =#REF! -> #REF! | BS61: =SUM(BP61:BR61) -> #REF! | BT61: =BP61-AC61 -> 0.84629667 | BU61: =BQ61-AD61 -> 5.8986338 | BV61: =BR61-AE61 -> #REF! | BW61: =BS61-AF61 -> #REF! | BY61: =H61-BR61 -> #REF! | CA61: ='FC2+10'!AA60 -> -22.866055 | CC61: =CA61-I61 -> -17.956743 | CE61: =SUM(CE59:CE60) -> -4.9093125 | CF61: =SUM(CF59:CF60) -> 0 | CG61: =SUM(CG59:CG60) -> 0 | CH61: =SUM(CE61:CG61) -> -4.9093125 | CI61: =IFERROR(F61-CE61,0) -> 0 | CJ61: =IFERROR(G61-CF61,0) -> 0 | CK61: =IFERROR(H61-CG61,0) -> 0 | CL61: =IFERROR(I61-CH61,0) -> 0 | CM61: =SUM(CM59:CM60) -> -21.949221 | CN61: =I61-CM61 -> 17.039908
CA62: ='FC2+10'!AA61 -> 0 | CC62: =CA62-I62 -> 0
A63: Exp | D63: Export OSP (Out) | F63: =IF(Act!S$3=1,Act!S62,"") -> -0.30846767 | G63: =IF(Act!T$3=1,Act!T62,"") | H63: =IF(Act!U$3=1,Act!U62,"") | I63: =SUM(F63:H63) -> -0.30846767 | K63: =IF(BP!S$3=1,BP!S62,"") -> -1.8855914 | L63: =IF(BP!T$3=1,BP!T62,"") | M63: =IF(BP!U$3=1,BP!U62,"") | N63: =SUM(K63:M63) -> -1.8855914 | O63: =IFERROR(F63-K63,0) -> 1.5771238 | P63: =IFERROR(G63-L63,0) -> 0 | Q63: =IFERROR(H63-M63,0) -> 0 | R63: =I63-N63 -> 1.5771238 | T63: =IF('FC2+10'!S$3=1,'FC2+10'!S62,"") -> -0.30846767 | U63: =IF('FC2+10'!T$3=1,'FC2+10'!T62,"") | V63: =IF('FC2+10'!U$3=1,'FC2+10'!U62,"") | W63: =SUM(T63:V63) -> -0.30846767 | X63: =IFERROR(F63-T63,0) -> 0 | Y63: =IFERROR(G63-U63,0) -> 0 | Z63: =IFERROR(H63-V63,0) -> 0 | AA63: =I63-W63 -> 0 | AC63: =IF(OL!S$3=1,OL!S62,"") -> -0.28912091 | AD63: =IF(OL!T$3=1,OL!T62,"") -> -1.0329364 | AE63: =IF(OL!U$3=1,OL!U62,"") | AF63: =SUM(AC63:AE63) -> -1.3220573 | AG63: =IFERROR(F63-AC63,0) -> -0.019346756 | AH63: =IFERROR(G63-AD63,0) -> 0 | AI63: =IFERROR(H63-AE63,0) -> 0 | AJ63: =IFERROR(I63-AF63,0) -> 1.0135896 | AL63: =IF(LY!S$3=1,LY!S62,"") -> -1.9522354 | AM63: =IF(LY!T$3=1,LY!T62,"") | AN63: =IF(LY!U$3=1,LY!U62,"") | AO63: =SUM(AL63:AN63) -> -1.9522354 | AP63: =IFERROR(F63-AL63,0) -> 1.6437677 | AQ63: =IFERROR(G63-AM63,0) -> 0 | AR63: =IFERROR(H63-AN63,0) -> 0 | AS63: =IFERROR(I63-AO63,0) -> 1.6437677 | AU63: =Act!L62 -> -1.1950802 | AV63: =H63-AU63 -> #VALUE! | AX63: =IF('FC5+7'!S$3=1,'FC5+7'!S62,"") -> -0.30846767 | AY63: =IF('FC5+7'!T$3=1,'FC5+7'!T62,"") | AZ63: =IF('FC5+7'!U$3=1,'FC5+7'!U62,"") | BA63: =SUM(AX63:AZ63) -> -0.30846767 | BB63: =IFERROR(F63-AX63,0) -> 0 | BC63: =IFERROR(G63-AY63,0) -> 0 | BD63: =IFERROR(H63-AZ63,0) -> 0 | BE63: =IFERROR(I63-BA63,0) -> 0 | BG63: =F63 -> -0.30846767 | BH63: -1.9370231 | BI63: -2.2181609 | BJ63: =SUM(BG63:BI63) -> -4.4636516 | BK63: =IFERROR(F63-AC63,0) -> -0.019346756 | BL63: =IFERROR(G63-AD63,0) -> 0 | BM63: =IFERROR(AL63-AE63,0) -> 0 | BN63: =IFERROR(I63-BJ63,0) -> 4.155184 | BP63: =F63 -> -0.30846767 | BQ63: =G63 | BR63: =#REF! -> #REF! | BS63: =SUM(BP63:BR63) -> #REF! | BT63: =BP63-AC63 -> -0.019346756 | BU63: =BQ63-AD63 -> #VALUE! | BV63: =BR63-AE63 -> #REF! | BW63: =BS63-AF63 -> #REF! | BY63: =H63-BR63 -> #VALUE! | CA63: ='FC2+10'!AA62 -> -6.0411989 | CC63: =CA63-I63 -> -5.7327313 | CE63: =IF('FC7+5'!S$3=1,'FC7+5'!S62,"") -> -0.30846767 | CF63: =IF('FC7+5'!T$3=1,'FC7+5'!T62,"") | CG63: =IF('FC7+5'!U$3=1,'FC7+5'!U62,"") | CH63: =SUM(CE63:CG63) -> -0.30846767 | CI63: =IFERROR(F63-CE63,0) -> 0 | CJ63: =IFERROR(G63-CF63,0) -> 0 | CK63: =IFERROR(H63-CG63,0) -> 0 | CL63: =IFERROR(I63-CH63,0) -> 0 | CM63: =IF('FC7+5'!AC$3=1,'FC7+5'!AC62,"") -> -4.2715758 | CN63: =I63-CM63 -> 3.9631081
A64: NV | D64: Import OSP (In) | F64: =IF(Act!S$3=1,Act!S63,"") -> 8.7524709 | G64: =IF(Act!T$3=1,Act!T63,"") | H64: =IF(Act!U$3=1,Act!U63,"") | I64: =SUM(F64:H64) -> 8.7524709 | K64: =IF(BP!S$3=1,BP!S63,"") -> 9.9425426 | L64: =IF(BP!T$3=1,BP!T63,"") | M64: =IF(BP!U$3=1,BP!U63,"") | N64: =SUM(K64:M64) -> 9.9425426 | O64: =IFERROR(F64-K64,0) -> -1.1900716 | P64: =IFERROR(G64-L64,0) -> 0 | Q64: =IFERROR(H64-M64,0) -> 0 | R64: =I64-N64 -> -1.1900716 | T64: =IF('FC2+10'!S$3=1,'FC2+10'!S63,"") -> #VALUE! | U64: =IF('FC2+10'!T$3=1,'FC2+10'!T63,"") | V64: =IF('FC2+10'!U$3=1,'FC2+10'!U63,"") | W64: =SUM(T64:V64) -> #VALUE! | X64: =IFERROR(F64-T64,0) -> 0 | Y64: =IFERROR(G64-U64,0) -> 0 | Z64: =IFERROR(H64-V64,0) -> 0 | AA64: =I64-W64 -> #VALUE! | AC64: =IF(OL!S$3=1,OL!S63,"") -> 20.821521 | AD64: =IF(OL!T$3=1,OL!T63,"") -> 21.982158 | AE64: =IF(OL!U$3=1,OL!U63,"") | AF64: =SUM(AC64:AE64) -> 42.803679 | AG64: =IFERROR(F64-AC64,0) -> -12.06905 | AH64: =IFERROR(G64-AD64,0) -> 0 | AI64: =IFERROR(H64-AE64,0) -> 0 | AJ64: =IFERROR(I64-AF64,0) -> -34.051208 | AL64: =IF(LY!S$3=1,LY!S63,"") -> 42.988955 | AM64: =IF(LY!T$3=1,LY!T63,"") | AN64: =IF(LY!U$3=1,LY!U63,"") | AO64: =SUM(AL64:AN64) -> 42.988955 | AP64: =IFERROR(F64-AL64,0) -> -34.236484 | AQ64: =IFERROR(G64-AM64,0) -> 0 | AR64: =IFERROR(H64-AN64,0) -> 0 | AS64: =IFERROR(I64-AO64,0) -> -34.236484 | AU64: =Act!L63 -> 24.881204 | AV64: =H64-AU64 -> #VALUE! | AX64: =IF('FC5+7'!S$3=1,'FC5+7'!S63,"") -> 8.7524709 | AY64: =IF('FC5+7'!T$3=1,'FC5+7'!T63,"") | AZ64: =IF('FC5+7'!U$3=1,'FC5+7'!U63,"") | BA64: =SUM(AX64:AZ64) -> 8.7524709 | BB64: =IFERROR(F64-AX64,0) -> 0 | BC64: =IFERROR(G64-AY64,0) -> 0 | BD64: =IFERROR(H64-AZ64,0) -> 0 | BE64: =IFERROR(I64-BA64,0) -> 0 | BG64: =F64 -> 8.7524709 | BH64: 12.864467 | BI64: 22.950198 | BJ64: =SUM(BG64:BI64) -> 44.567136 | BK64: =IFERROR(F64-AC64,0) -> -12.06905 | BL64: =IFERROR(G64-AD64,0) -> 0 | BM64: =IFERROR(AL64-AE64,0) -> 0 | BN64: =IFERROR(I64-BJ64,0) -> -35.814665 | BP64: =F64 -> 8.7524709 | BQ64: =G64 | BR64: =#REF! -> #REF! | BS64: =SUM(BP64:BR64) -> #REF! | BT64: =BP64-AC64 -> -12.06905 | BU64: =BQ64-AD64 -> #VALUE! | BV64: =BR64-AE64 -> #REF! | BW64: =BS64-AF64 -> #REF! | BY64: =H64-BR64 -> #VALUE! | CA64: ='FC2+10'!AA63 -> #VALUE! | CC64: =CA64-I64 -> #VALUE! | CE64: =IF('FC7+5'!S$3=1,'FC7+5'!S63,"") -> 8.7524709 | CF64: =IF('FC7+5'!T$3=1,'FC7+5'!T63,"") | CG64: =IF('FC7+5'!U$3=1,'FC7+5'!U63,"") | CH64: =SUM(CE64:CG64) -> 8.7524709 | CI64: =IFERROR(F64-CE64,0) -> 0 | CJ64: =IFERROR(G64-CF64,0) -> 0 | CK64: =IFERROR(H64-CG64,0) -> 0 | CL64: =IFERROR(I64-CH64,0) -> 0 | CM64: =IF('FC7+5'!AC$3=1,'FC7+5'!AC63,"") -> 56.820423 | CN64: =I64-CM64 -> -48.067952
A65: R&D | D65: R&D (Functional ROP) | F65: =IF(Act!S$3=1,Act!S64,"") -> 5.6350323 | G65: =IF(Act!T$3=1,Act!T64,"") | H65: =IF(Act!U$3=1,Act!U64,"") | I65: =SUM(F65:H65) -> 5.6350323 | K65: =IF(BP!S$3=1,BP!S64,"") -> 4.8602805 | L65: =IF(BP!T$3=1,BP!T64,"") | M65: =IF(BP!U$3=1,BP!U64,"") | N65: =SUM(K65:M65) -> 4.8602805 | O65: =IFERROR(F65-K65,0) -> 0.77475179 | P65: =IFERROR(G65-L65,0) -> 0 | Q65: =IFERROR(H65-M65,0) -> 0 | R65: =I65-N65 -> 0.77475179 | T65: =IF('FC2+10'!S$3=1,'FC2+10'!S64,"") -> 5.6350323 | U65: =IF('FC2+10'!T$3=1,'FC2+10'!T64,"") | V65: =IF('FC2+10'!U$3=1,'FC2+10'!U64,"") | W65: =SUM(T65:V65) -> 5.6350323 | X65: =IFERROR(F65-T65,0) -> 0 | Y65: =IFERROR(G65-U65,0) -> 0 | Z65: =IFERROR(H65-V65,0) -> 0 | AA65: =I65-W65 -> 0 | AC65: =IF(OL!S$3=1,OL!S64,"") -> 6.4000511 | AD65: =IF(OL!T$3=1,OL!T64,"") -> 3.9334495 | AE65: =IF(OL!U$3=1,OL!U64,"") | AF65: =SUM(AC65:AE65) -> 10.333501 | AG65: =IFERROR(F65-AC65,0) -> -0.76501878 | AH65: =IFERROR(G65-AD65,0) -> 0 | AI65: =IFERROR(H65-AE65,0) -> 0 | AJ65: =IFERROR(I65-AF65,0) -> -4.6984683 | AL65: =IF(LY!S$3=1,LY!S64,"") -> 7.211113 | AM65: =IF(LY!T$3=1,LY!T64,"") | AN65: =IF(LY!U$3=1,LY!U64,"") | AO65: =SUM(AL65:AN65) -> 7.211113 | AP65: =IFERROR(F65-AL65,0) -> -1.5760807 | AQ65: =IFERROR(G65-AM65,0) -> 0 | AR65: =IFERROR(H65-AN65,0) -> 0 | AS65: =IFERROR(I65-AO65,0) -> -1.5760807 | AU65: =Act!L64 -> 4.116395 | AV65: =H65-AU65 -> #VALUE! | AX65: =IF('FC5+7'!S$3=1,'FC5+7'!S64,"") -> 5.6350323 | AY65: =IF('FC5+7'!T$3=1,'FC5+7'!T64,"") | AZ65: =IF('FC5+7'!U$3=1,'FC5+7'!U64,"") | BA65: =SUM(AX65:AZ65) -> 5.6350323 | BB65: =IFERROR(F65-AX65,0) -> 0 | BC65: =IFERROR(G65-AY65,0) -> 0 | BD65: =IFERROR(H65-AZ65,0) -> 0 | BE65: =IFERROR(I65-BA65,0) -> 0 | BG65: =F65 -> 5.6350323 | BH65: 5.2813313 | BI65: 2.5835055 | BJ65: =SUM(BG65:BI65) -> 13.499869 | BK65: =IFERROR(F65-AC65,0) -> -0.76501878 | BL65: =IFERROR(G65-AD65,0) -> 0 | BM65: =IFERROR(AL65-AE65,0) -> 0 | BN65: =IFERROR(I65-BJ65,0) -> -7.8648368 | BP65: =F65 -> 5.6350323 | BQ65: =G65 | BR65: =#REF! -> #REF! | BS65: =SUM(BP65:BR65) -> #REF! | BT65: =BP65-AC65 -> -0.76501878 | BU65: =BQ65-AD65 -> #VALUE! | BV65: =BR65-AE65 -> #REF! | BW65: =BS65-AF65 -> #REF! | BY65: =H65-BR65 -> #VALUE! | CA65: ='FC2+10'!AA64 -> 7.8481605 | CC65: =CA65-I65 -> 2.2131282 | CE65: =IF('FC7+5'!S$3=1,'FC7+5'!S64,"") -> 5.6350323 | CF65: =IF('FC7+5'!T$3=1,'FC7+5'!T64,"") | CG65: =IF('FC7+5'!U$3=1,'FC7+5'!U64,"") | CH65: =SUM(CE65:CG65) -> 5.6350323 | CI65: =IFERROR(F65-CE65,0) -> 0 | CJ65: =IFERROR(G65-CF65,0) -> 0 | CK65: =IFERROR(H65-CG65,0) -> 0 | CL65: =IFERROR(I65-CH65,0) -> 0 | CM65: =IF('FC7+5'!AC$3=1,'FC7+5'!AC64,"") -> 18.178973 | CN65: =I65-CM65 -> -12.54394
A66: ITP | D66: ITP MZ | F66: =IF(Act!S$3=1,Act!S65,"") -> 0 | G66: =IF(Act!T$3=1,Act!T65,"") | H66: =IF(Act!U$3=1,Act!U65,"") | I66: =SUM(F66:H66) -> 0 | K66: =IF(BP!S$3=1,BP!S65,"") -> 0 | L66: =IF(BP!T$3=1,BP!T65,"") | M66: =IF(BP!U$3=1,BP!U65,"") | N66: =SUM(K66:M66) -> 0 | O66: =IFERROR(F66-K66,0) -> 0 | P66: =IFERROR(G66-L66,0) -> 0 | Q66: =IFERROR(H66-M66,0) -> 0 | R66: =I66-N66 -> 0 | T66: =IF('FC2+10'!S$3=1,'FC2+10'!S65,"") -> 0 | U66: =IF('FC2+10'!T$3=1,'FC2+10'!T65,"") | V66: =IF('FC2+10'!U$3=1,'FC2+10'!U65,"") | W66: =SUM(T66:V66) -> 0 | X66: =IFERROR(F66-T66,0) -> 0 | Y66: =IFERROR(G66-U66,0) -> 0 | Z66: =IFERROR(H66-V66,0) -> 0 | AA66: =I66-W66 -> 0 | AC66: =IF(OL!S$3=1,OL!S65,"") -> -1.9876 | AD66: =IF(OL!T$3=1,OL!T65,"") -> -2.926268 | AE66: =IF(OL!U$3=1,OL!U65,"") | AF66: =SUM(AC66:AE66) -> -4.913868 | AG66: =IFERROR(F66-AC66,0) -> 1.9876 | AH66: =IFERROR(G66-AD66,0) -> 0 | AI66: =IFERROR(H66-AE66,0) -> 0 | AJ66: =IFERROR(I66-AF66,0) -> 4.913868 | AL66: =IF(LY!S$3=1,LY!S65,"") -> -7.7550386 | AM66: =IF(LY!T$3=1,LY!T65,"") | AN66: =IF(LY!U$3=1,LY!U65,"") | AO66: =SUM(AL66:AN66) -> -7.7550386 | AP66: =IFERROR(F66-AL66,0) -> 7.7550386 | AQ66: =IFERROR(G66-AM66,0) -> 0 | AR66: =IFERROR(H66-AN66,0) -> 0 | AS66: =IFERROR(I66-AO66,0) -> 7.7550386 | AU66: =Act!L65 -> 5.6592178 | AV66: =H66-AU66 -> #VALUE! | AX66: =IF('FC5+7'!S$3=1,'FC5+7'!S65,"") -> 0 | AY66: =IF('FC5+7'!T$3=1,'FC5+7'!T65,"") | AZ66: =IF('FC5+7'!U$3=1,'FC5+7'!U65,"") | BA66: =SUM(AX66:AZ66) -> 0 | BB66: =IFERROR(F66-AX66,0) -> 0 | BC66: =IFERROR(G66-AY66,0) -> 0 | BD66: =IFERROR(H66-AZ66,0) -> 0 | BE66: =IFERROR(I66-BA66,0) -> 0 | BG66: =F66 -> 0 | BH66: -18.088526 | BI66: -18.835148 | BJ66: =SUM(BG66:BI66) -> -36.923674 | BK66: =IFERROR(F66-AC66,0) -> 1.9876 | BL66: =IFERROR(G66-AD66,0) -> 0 | BM66: =IFERROR(AL66-AE66,0) -> 0 | BN66: =IFERROR(I66-BJ66,0) -> 36.923674 | BP66: =F66 -> 0 | BQ66: =G66 | BR66: =#REF! -> #REF! | BS66: =SUM(BP66:BR66) -> #REF! | BT66: =BP66-AC66 -> 1.9876 | BU66: =BQ66-AD66 -> #VALUE! | BV66: =BR66-AE66 -> #REF! | BW66: =BS66-AF66 -> #REF! | BY66: =H66-BR66 -> #VALUE! | CA66: ='FC2+10'!AA65 -> 0 | CC66: =CA66-I66 -> 0 | CE66: =IF('FC7+5'!S$3=1,'FC7+5'!S65,"") -> 0 | CF66: =IF('FC7+5'!T$3=1,'FC7+5'!T65,"") | CG66: =IF('FC7+5'!U$3=1,'FC7+5'!U65,"") | CH66: =SUM(CE66:CG66) -> 0 | CI66: =IFERROR(F66-CE66,0) -> 0 | CJ66: =IFERROR(G66-CF66,0) -> 0 | CK66: =IFERROR(H66-CG66,0) -> 0 | CL66: =IFERROR(I66-CH66,0) -> 0 | CM66: =IF('FC7+5'!AC$3=1,'FC7+5'!AC65,"") -> -9.0359723 | CN66: =I66-CM66 -> 9.0359723
A67: ITP | D67: ITP Import CBU | F67: =IF(Act!S$3=1,Act!S66,"") -> 0 | G67: =IF(Act!T$3=1,Act!T66,"") | H67: =IF(Act!U$3=1,Act!U66,"") | I67: =SUM(F67:H67) -> 0 | K67: =IF(BP!S$3=1,BP!S66,"") -> 0 | L67: =IF(BP!T$3=1,BP!T66,"") | M67: =IF(BP!U$3=1,BP!U66,"") | N67: =SUM(K67:M67) -> 0 | O67: =IFERROR(F67-K67,0) -> 0 | P67: =IFERROR(G67-L67,0) -> 0 | Q67: =IFERROR(H67-M67,0) -> 0 | R67: =I67-N67 -> 0 | T67: =IF('FC2+10'!S$3=1,'FC2+10'!S66,"") -> 0 | U67: =IF('FC2+10'!T$3=1,'FC2+10'!T66,"") | V67: =IF('FC2+10'!U$3=1,'FC2+10'!U66,"") | W67: =SUM(T67:V67) -> 0 | X67: =IFERROR(F67-T67,0) -> 0 | Y67: =IFERROR(G67-U67,0) -> 0 | Z67: =IFERROR(H67-V67,0) -> 0 | AA67: =I67-W67 -> 0 | AC67: =IF(OL!S$3=1,OL!S66,"") -> 0.48476129 | AD67: =IF(OL!T$3=1,OL!T66,"") -> 0 | AE67: =IF(OL!U$3=1,OL!U66,"") | AF67: =SUM(AC67:AE67) -> 0.48476129 | AG67: =IFERROR(F67-AC67,0) -> -0.48476129 | AH67: =IFERROR(G67-AD67,0) -> 0 | AI67: =IFERROR(H67-AE67,0) -> 0 | AJ67: =IFERROR(I67-AF67,0) -> -0.48476129 | AL67: =IF(LY!S$3=1,LY!S66,"") -> 14.30809 | AM67: =IF(LY!T$3=1,LY!T66,"") | AN67: =IF(LY!U$3=1,LY!U66,"") | AO67: =SUM(AL67:AN67) -> 14.30809 | AP67: =IFERROR(F67-AL67,0) -> -14.30809 | AQ67: =IFERROR(G67-AM67,0) -> 0 | AR67: =IFERROR(H67-AN67,0) -> 0 | AS67: =IFERROR(I67-AO67,0) -> -14.30809 | AU67: =Act!L66 -> 1.4279864 | AV67: =H67-AU67 -> #VALUE! | AX67: =IF('FC5+7'!S$3=1,'FC5+7'!S66,"") -> 0 | AY67: =IF('FC5+7'!T$3=1,'FC5+7'!T66,"") | AZ67: =IF('FC5+7'!U$3=1,'FC5+7'!U66,"") | BA67: =SUM(AX67:AZ67) -> 0 | BB67: =IFERROR(F67-AX67,0) -> 0 | BC67: =IFERROR(G67-AY67,0) -> 0 | BD67: =IFERROR(H67-AZ67,0) -> 0 | BE67: =IFERROR(I67-BA67,0) -> 0 | BG67: =F67 -> 0 | BH67: -0.34 | BI67: -0.63 | BJ67: =SUM(BG67:BI67) -> -0.97 | BK67: =IFERROR(F67-AC67,0) -> -0.48476129 | BL67: =IFERROR(G67-AD67,0) -> 0 | BM67: =IFERROR(AL67-AE67,0) -> 0 | BN67: =IFERROR(I67-BJ67,0) -> 0.97 | BP67: =F67 -> 0 | BQ67: =G67 | BR67: =#REF! -> #REF! | BS67: =SUM(BP67:BR67) -> #REF! | BT67: =BP67-AC67 -> -0.48476129 | BU67: =BQ67-AD67 -> #VALUE! | BV67: =BR67-AE67 -> #REF! | BW67: =BS67-AF67 -> #REF! | BY67: =H67-BR67 -> #VALUE! | CA67: ='FC2+10'!AA66 -> 0 | CC67: =CA67-I67 -> 0 | CE67: =IF('FC7+5'!S$3=1,'FC7+5'!S66,"") -> 0 | CF67: =IF('FC7+5'!T$3=1,'FC7+5'!T66,"") | CG67: =IF('FC7+5'!U$3=1,'FC7+5'!U66,"") | CH67: =SUM(CE67:CG67) -> 0 | CI67: =IFERROR(F67-CE67,0) -> 0 | CJ67: =IFERROR(G67-CF67,0) -> 0 | CK67: =IFERROR(H67-CG67,0) -> 0 | CL67: =IFERROR(I67-CH67,0) -> 0 | CM67: =IF('FC7+5'!AC$3=1,'FC7+5'!AC66,"") -> 0 | CN67: =I67-CM67 -> 0
A68: ITP | D68: ITP Export CBU | F68: =IF(Act!S$3=1,Act!S67,"") -> 0 | G68: =IF(Act!T$3=1,Act!T67,"") | H68: =IF(Act!U$3=1,Act!U67,"") | I68: =SUM(F68:H68) -> 0 | K68: =IF(BP!S$3=1,BP!S67,"") -> 0 | L68: =IF(BP!T$3=1,BP!T67,"") | M68: =IF(BP!U$3=1,BP!U67,"") | N68: =SUM(K68:M68) -> 0 | O68: =IFERROR(F68-K68,0) -> 0 | P68: =IFERROR(G68-L68,0) -> 0 | Q68: =IFERROR(H68-M68,0) -> 0 | R68: =I68-N68 -> 0 | T68: =IF('FC2+10'!S$3=1,'FC2+10'!S67,"") -> 0 | U68: =IF('FC2+10'!T$3=1,'FC2+10'!T67,"") | V68: =IF('FC2+10'!U$3=1,'FC2+10'!U67,"") | W68: =SUM(T68:V68) -> 0 | X68: =IFERROR(F68-T68,0) -> 0 | Y68: =IFERROR(G68-U68,0) -> 0 | Z68: =IFERROR(H68-V68,0) -> 0 | AA68: =I68-W68 -> 0 | AC68: =IF(OL!S$3=1,OL!S67,"") -> 0 | AD68: =IF(OL!T$3=1,OL!T67,"") -> -0.15643375 | AE68: =IF(OL!U$3=1,OL!U67,"") | AF68: =SUM(AC68:AE68) -> -0.15643375 | AG68: =IFERROR(F68-AC68,0) -> 0 | AH68: =IFERROR(G68-AD68,0) -> 0 | AI68: =IFERROR(H68-AE68,0) -> 0 | AJ68: =IFERROR(I68-AF68,0) -> 0.15643375 | AL68: =IF(LY!S$3=1,LY!S67,"") -> -0.003337221 | AM68: =IF(LY!T$3=1,LY!T67,"") | AN68: =IF(LY!U$3=1,LY!U67,"") | AO68: =SUM(AL68:AN68) -> -0.003337221 | AP68: =IFERROR(F68-AL68,0) -> 0.003337221 | AQ68: =IFERROR(G68-AM68,0) -> 0 | AR68: =IFERROR(H68-AN68,0) -> 0 | AS68: =IFERROR(I68-AO68,0) -> 0.003337221 | AU68: =Act!L67 -> 0 | AV68: =H68-AU68 -> #VALUE! | AX68: =IF('FC5+7'!S$3=1,'FC5+7'!S67,"") -> 0 | AY68: =IF('FC5+7'!T$3=1,'FC5+7'!T67,"") | AZ68: =IF('FC5+7'!U$3=1,'FC5+7'!U67,"") | BA68: =SUM(AX68:AZ68) -> 0 | BB68: =IFERROR(F68-AX68,0) -> 0 | BC68: =IFERROR(G68-AY68,0) -> 0 | BD68: =IFERROR(H68-AZ68,0) -> 0 | BE68: =IFERROR(I68-BA68,0) -> 0 | BG68: =F68 -> 0 | BH68: -0.64449135 | BI68: -0.42545938 | BJ68: =SUM(BG68:BI68) -> -1.0699507 | BK68: =IFERROR(F68-AC68,0) -> 0 | BL68: =IFERROR(G68-AD68,0) -> 0 | BM68: =IFERROR(AL68-AE68,0) -> 0 | BN68: =IFERROR(I68-BJ68,0) -> 1.0699507 | BP68: =F68 -> 0 | BQ68: =G68 | BR68: =#REF! -> #REF! | BS68: =SUM(BP68:BR68) -> #REF! | BT68: =BP68-AC68 -> 0 | BU68: =BQ68-AD68 -> #VALUE! | BV68: =BR68-AE68 -> #REF! | BW68: =BS68-AF68 -> #REF! | BY68: =H68-BR68 -> #VALUE! | CA68: ='FC2+10'!AA67 -> 0 | CC68: =CA68-I68 -> 0 | CE68: =IF('FC7+5'!S$3=1,'FC7+5'!S67,"") -> 0 | CF68: =IF('FC7+5'!T$3=1,'FC7+5'!T67,"") | CG68: =IF('FC7+5'!U$3=1,'FC7+5'!U67,"") | CH68: =SUM(CE68:CG68) -> 0 | CI68: =IFERROR(F68-CE68,0) -> 0 | CJ68: =IFERROR(G68-CF68,0) -> 0 | CK68: =IFERROR(H68-CG68,0) -> 0 | CL68: =IFERROR(I68-CH68,0) -> 0 | CM68: =IF('FC7+5'!AC$3=1,'FC7+5'!AC67,"") -> -0.212413 | CN68: =I68-CM68 -> 0.212413
A69: NV | D69: Royalty NV | F69: =IF(Act!S$3=1,Act!S68,"") -> 11.986581 | G69: =IF(Act!T$3=1,Act!T68,"") | H69: =IF(Act!U$3=1,Act!U68,"") | I69: =SUM(F69:H69) -> 11.986581 | K69: =IF(BP!S$3=1,BP!S68,"") -> 12.788908 | L69: =IF(BP!T$3=1,BP!T68,"") | M69: =IF(BP!U$3=1,BP!U68,"") | N69: =SUM(K69:M69) -> 12.788908 | O69: =IFERROR(F69-K69,0) -> -0.8023265 | P69: =IFERROR(G69-L69,0) -> 0 | Q69: =IFERROR(H69-M69,0) -> 0 | R69: =I69-N69 -> -0.8023265 | T69: =IF('FC2+10'!S$3=1,'FC2+10'!S68,"") -> 11.986581 | U69: =IF('FC2+10'!T$3=1,'FC2+10'!T68,"") | V69: =IF('FC2+10'!U$3=1,'FC2+10'!U68,"") | W69: =SUM(T69:V69) -> 11.986581 | X69: =IFERROR(F69-T69,0) -> 0 | Y69: =IFERROR(G69-U69,0) -> 0 | Z69: =IFERROR(H69-V69,0) -> 0 | AA69: =I69-W69 -> 0 | AC69: =IF(OL!S$3=1,OL!S68,"") -> 12.553013 | AD69: =IF(OL!T$3=1,OL!T68,"") -> 14.512 | AE69: =IF(OL!U$3=1,OL!U68,"") | AF69: =SUM(AC69:AE69) -> 27.065013 | AG69: =IFERROR(F69-AC69,0) -> -0.5664318 | AH69: =IFERROR(G69-AD69,0) -> 0 | AI69: =IFERROR(H69-AE69,0) -> 0 | AJ69: =IFERROR(I69-AF69,0) -> -15.078432 | AL69: =IF(LY!S$3=1,LY!S68,"") -> 11.46263 | AM69: =IF(LY!T$3=1,LY!T68,"") | AN69: =IF(LY!U$3=1,LY!U68,"") | AO69: =SUM(AL69:AN69) -> 11.46263 | AP69: =IFERROR(F69-AL69,0) -> 0.52395163 | AQ69: =IFERROR(G69-AM69,0) -> 0 | AR69: =IFERROR(H69-AN69,0) -> 0 | AS69: =IFERROR(I69-AO69,0) -> 0.52395163 | AU69: =Act!L68 -> 17.910946 | AV69: =H69-AU69 -> #VALUE! | AX69: =IF('FC5+7'!S$3=1,'FC5+7'!S68,"") -> 11.986581 | AY69: =IF('FC5+7'!T$3=1,'FC5+7'!T68,"") | AZ69: =IF('FC5+7'!U$3=1,'FC5+7'!U68,"") | BA69: =SUM(AX69:AZ69) -> 11.986581 | BB69: =IFERROR(F69-AX69,0) -> 0 | BC69: =IFERROR(G69-AY69,0) -> 0 | BD69: =IFERROR(H69-AZ69,0) -> 0 | BE69: =IFERROR(I69-BA69,0) -> 0 | BG69: =F69 -> 11.986581 | BH69: 13.502 | BI69: 14.537 | BJ69: =SUM(BG69:BI69) -> 40.025581 | BK69: =IFERROR(F69-AC69,0) -> -0.5664318 | BL69: =IFERROR(G69-AD69,0) -> 0 | BM69: =IFERROR(AL69-AE69,0) -> 0 | BN69: =IFERROR(I69-BJ69,0) -> -28.039 | BP69: =F69 -> 11.986581 | BQ69: =G69 | BR69: =#REF! -> #REF! | BS69: =SUM(BP69:BR69) -> #REF! | BT69: =BP69-AC69 -> -0.5664318 | BU69: =BQ69-AD69 -> #VALUE! | BV69: =BR69-AE69 -> #REF! | BW69: =BS69-AF69 -> #REF! | BY69: =H69-BR69 -> #VALUE! | CA69: ='FC2+10'!AA68 -> 37.564026 | CC69: =CA69-I69 -> 25.577444 | CE69: =IF('FC7+5'!S$3=1,'FC7+5'!S68,"") -> 11.986581 | CF69: =IF('FC7+5'!T$3=1,'FC7+5'!T68,"") | CG69: =IF('FC7+5'!U$3=1,'FC7+5'!U68,"") | CH69: =SUM(CE69:CG69) -> 11.986581 | CI69: =IFERROR(F69-CE69,0) -> 0 | CJ69: =IFERROR(G69-CF69,0) -> 0 | CK69: =IFERROR(H69-CG69,0) -> 0 | CL69: =IFERROR(I69-CH69,0) -> 0 | CM69: =IF('FC7+5'!AC$3=1,'FC7+5'!AC68,"") -> 45.667585 | CN69: =I69-CM69 -> -33.681004
A70: Export | D70: Royalty Export | F70: =IF(Act!S$3=1,Act!S69,"") -> 0 | G70: =IF(Act!T$3=1,Act!T69,"") | H70: =IF(Act!U$3=1,Act!U69,"") | I70: =SUM(F70:H70) -> 0 | K70: =IF(BP!S$3=1,BP!S69,"") -> 0 | L70: =IF(BP!T$3=1,BP!T69,"") | M70: =IF(BP!U$3=1,BP!U69,"") | N70: =SUM(K70:M70) -> 0 | O70: =IFERROR(F70-K70,0) -> 0 | P70: =IFERROR(G70-L70,0) -> 0 | Q70: =IFERROR(H70-M70,0) -> 0 | R70: =I70-N70 -> 0 | T70: =IF('FC2+10'!S$3=1,'FC2+10'!S69,"") -> 0 | U70: =IF('FC2+10'!T$3=1,'FC2+10'!T69,"") | V70: =IF('FC2+10'!U$3=1,'FC2+10'!U69,"") | W70: =SUM(T70:V70) -> 0 | X70: =IFERROR(F70-T70,0) -> 0 | Y70: =IFERROR(G70-U70,0) -> 0 | Z70: =IFERROR(H70-V70,0) -> 0 | AA70: =I70-W70 -> 0 | AC70: =IF(OL!S$3=1,OL!S69,"") -> 0 | AD70: =IF(OL!T$3=1,OL!T69,"") -> 0 | AE70: =IF(OL!U$3=1,OL!U69,"") | AF70: =SUM(AC70:AE70) -> 0 | AG70: =IFERROR(F70-AC70,0) -> 0 | AH70: =IFERROR(G70-AD70,0) -> 0 | AI70: =IFERROR(H70-AE70,0) -> 0 | AJ70: =IFERROR(I70-AF70,0) -> 0 | AL70: =IF(LY!S$3=1,LY!S69,"") -> 0 | AM70: =IF(LY!T$3=1,LY!T69,"") | AN70: =IF(LY!U$3=1,LY!U69,"") | AO70: =SUM(AL70:AN70) -> 0 | AP70: =IFERROR(F70-AL70,0) -> 0 | AQ70: =IFERROR(G70-AM70,0) -> 0 | AR70: =IFERROR(H70-AN70,0) -> 0 | AS70: =IFERROR(I70-AO70,0) -> 0 | AU70: =Act!L69 -> 0 | AV70: =H70-AU70 -> #VALUE! | AX70: =IF('FC5+7'!S$3=1,'FC5+7'!S69,"") -> 0 | AY70: =IF('FC5+7'!T$3=1,'FC5+7'!T69,"") | AZ70: =IF('FC5+7'!U$3=1,'FC5+7'!U69,"") | BA70: =SUM(AX70:AZ70) -> 0 | BB70: =IFERROR(F70-AX70,0) -> 0 | BC70: =IFERROR(G70-AY70,0) -> 0 | BD70: =IFERROR(H70-AZ70,0) -> 0 | BE70: =IFERROR(I70-BA70,0) -> 0 | BG70: =F70 -> 0 | BH70: 0 | BI70: 0 | BJ70: =SUM(BG70:BI70) -> 0 | BK70: =IFERROR(F70-AC70,0) -> 0 | BL70: =IFERROR(G70-AD70,0) -> 0 | BM70: =IFERROR(AL70-AE70,0) -> 0 | BN70: =IFERROR(I70-BJ70,0) -> 0 | BP70: =F70 -> 0 | BQ70: =G70 | BR70: =#REF! -> #REF! | BS70: =SUM(BP70:BR70) -> #REF! | BT70: =BP70-AC70 -> 0 | BU70: =BQ70-AD70 -> #VALUE! | BV70: =BR70-AE70 -> #REF! | BW70: =BS70-AF70 -> #REF! | BY70: =H70-BR70 -> #VALUE! | CA70: ='FC2+10'!AA69 -> 0 | CC70: =CA70-I70 -> 0 | CE70: =IF('FC7+5'!S$3=1,'FC7+5'!S69,"") -> 0 | CF70: =IF('FC7+5'!T$3=1,'FC7+5'!T69,"") | CG70: =IF('FC7+5'!U$3=1,'FC7+5'!U69,"") | CH70: =SUM(CE70:CG70) -> 0 | CI70: =IFERROR(F70-CE70,0) -> 0 | CJ70: =IFERROR(G70-CF70,0) -> 0 | CK70: =IFERROR(H70-CG70,0) -> 0 | CL70: =IFERROR(I70-CH70,0) -> 0 | CM70: =IF('FC7+5'!AC$3=1,'FC7+5'!AC69,"") -> 0 | CN70: =I70-CM70 -> 0
A71: Others | D71: CCS | F71: =IF(Act!S$3=1,Act!S70,"") -> 2.2744157 | G71: =IF(Act!T$3=1,Act!T70,"") | H71: =IF(Act!U$3=1,Act!U70,"") | I71: =SUM(F71:H71) -> 2.2744157 | K71: =IF(BP!S$3=1,BP!S70,"") -> 1.9631086 | L71: =IF(BP!T$3=1,BP!T70,"") | M71: =IF(BP!U$3=1,BP!U70,"") | N71: =SUM(K71:M71) -> 1.9631086 | O71: =IFERROR(F71-K71,0) -> 0.3113071 | P71: =IFERROR(G71-L71,0) -> 0 | Q71: =IFERROR(H71-M71,0) -> 0 | R71: =I71-N71 -> 0.3113071 | T71: =IF('FC2+10'!S$3=1,'FC2+10'!S70,"") -> 2.2744157 | U71: =IF('FC2+10'!T$3=1,'FC2+10'!T70,"") | V71: =IF('FC2+10'!U$3=1,'FC2+10'!U70,"") | W71: =SUM(T71:V71) -> 2.2744157 | X71: =IFERROR(F71-T71,0) -> 0 | Y71: =IFERROR(G71-U71,0) -> 0 | Z71: =IFERROR(H71-V71,0) -> 0 | AA71: =I71-W71 -> 0 | AC71: =IF(OL!S$3=1,OL!S70,"") -> 3.267382 | AD71: =IF(OL!T$3=1,OL!T70,"") -> 4.3610229 | AE71: =IF(OL!U$3=1,OL!U70,"") | AF71: =SUM(AC71:AE71) -> 7.6284049 | AG71: =IFERROR(F71-AC71,0) -> -0.99296628 | AH71: =IFERROR(G71-AD71,0) -> 0 | AI71: =IFERROR(H71-AE71,0) -> 0 | AJ71: =IFERROR(I71-AF71,0) -> -5.3539892 | AL71: =IF(LY!S$3=1,LY!S70,"") -> 2.4191639 | AM71: =IF(LY!T$3=1,LY!T70,"") | AN71: =IF(LY!U$3=1,LY!U70,"") | AO71: =SUM(AL71:AN71) -> 2.4191639 | AP71: =IFERROR(F71-AL71,0) -> -0.1447482 | AQ71: =IFERROR(G71-AM71,0) -> 0 | AR71: =IFERROR(H71-AN71,0) -> 0 | AS71: =IFERROR(I71-AO71,0) -> -0.1447482 | AU71: =Act!L70 -> 3.532067 | AV71: =H71-AU71 -> #VALUE! | AX71: =IF('FC5+7'!S$3=1,'FC5+7'!S70,"") -> 2.2744157 | AY71: =IF('FC5+7'!T$3=1,'FC5+7'!T70,"") | AZ71: =IF('FC5+7'!U$3=1,'FC5+7'!U70,"") | BA71: =SUM(AX71:AZ71) -> 2.2744157 | BB71: =IFERROR(F71-AX71,0) -> 0 | BC71: =IFERROR(G71-AY71,0) -> 0 | BD71: =IFERROR(H71-AZ71,0) -> 0 | BE71: =IFERROR(I71-BA71,0) -> 0 | BG71: =F71 -> 2.2744157 | BH71: 2.4110575 | BI71: 4.2274965 | BJ71: =SUM(BG71:BI71) -> 8.9129697 | BK71: =IFERROR(F71-AC71,0) -> -0.99296628 | BL71: =IFERROR(G71-AD71,0) -> 0 | BM71: =IFERROR(AL71-AE71,0) -> 0 | BN71: =IFERROR(I71-BJ71,0) -> -6.638554 | BP71: =F71 -> 2.2744157 | BQ71: =G71 | BR71: =#REF! -> #REF! | BS71: =SUM(BP71:BR71) -> #REF! | BT71: =BP71-AC71 -> -0.99296628 | BU71: =BQ71-AD71 -> #VALUE! | BV71: =BR71-AE71 -> #REF! | BW71: =BS71-AF71 -> #REF! | BY71: =H71-BR71 -> #VALUE! | CA71: ='FC2+10'!AA70 -> 9.3317245 | CC71: =CA71-I71 -> 7.0573088 | CE71: =IF('FC7+5'!S$3=1,'FC7+5'!S70,"") -> 2.2744157 | CF71: =IF('FC7+5'!T$3=1,'FC7+5'!T70,"") | CG71: =IF('FC7+5'!U$3=1,'FC7+5'!U70,"") | CH71: =SUM(CE71:CG71) -> 2.2744157 | CI71: =IFERROR(F71-CE71,0) -> 0 | CJ71: =IFERROR(G71-CF71,0) -> 0 | CK71: =IFERROR(H71-CG71,0) -> 0 | CL71: =IFERROR(I71-CH71,0) -> 0 | CM71: =IF('FC7+5'!AC$3=1,'FC7+5'!AC70,"") -> 14.256555 | CN71: =I71-CM71 -> -11.98214
A72: RS | D72: RS | F72: =IF(Act!S$3=1,Act!S71,"") -> -1.953547 | G72: =IF(Act!T$3=1,Act!T71,"") | H72: =IF(Act!U$3=1,Act!U71,"") | I72: =SUM(F72:H72) -> -1.953547 | K72: =IF(BP!S$3=1,BP!S71,"") -> 0 | L72: =IF(BP!T$3=1,BP!T71,"") | M72: =IF(BP!U$3=1,BP!U71,"") | N72: =SUM(K72:M72) -> 0 | O72: =IFERROR(F72-K72,0) -> -1.953547 | P72: =IFERROR(G72-L72,0) -> 0 | Q72: =IFERROR(H72-M72,0) -> 0 | R72: =I72-N72 -> -1.953547 | T72: =IF('FC2+10'!S$3=1,'FC2+10'!S71,"") -> -1.953547 | U72: =IF('FC2+10'!T$3=1,'FC2+10'!T71,"") | V72: =IF('FC2+10'!U$3=1,'FC2+10'!U71,"") | W72: =SUM(T72:V72) -> -1.953547 | X72: =IFERROR(F72-T72,0) -> 0 | Y72: =IFERROR(G72-U72,0) -> 0 | Z72: =IFERROR(H72-V72,0) -> 0 | AA72: =I72-W72 -> 0 | AC72: =IF(OL!S$3=1,OL!S71,"") -> 0.88185 | AD72: =IF(OL!T$3=1,OL!T71,"") -> 0 | AE72: =IF(OL!U$3=1,OL!U71,"") | AF72: =SUM(AC72:AE72) -> 0.88185 | AG72: =IFERROR(F72-AC72,0) -> -2.835397 | AH72: =IFERROR(G72-AD72,0) -> 0 | AI72: =IFERROR(H72-AE72,0) -> 0 | AJ72: =IFERROR(I72-AF72,0) -> -2.835397 | AL72: =IF(LY!S$3=1,LY!S71,"") -> 0.1199799 | AM72: =IF(LY!T$3=1,LY!T71,"") | AN72: =IF(LY!U$3=1,LY!U71,"") | AO72: =SUM(AL72:AN72) -> 0.1199799 | AP72: =IFERROR(F72-AL72,0) -> -2.0735269 | AQ72: =IFERROR(G72-AM72,0) -> 0 | AR72: =IFERROR(H72-AN72,0) -> 0 | AS72: =IFERROR(I72-AO72,0) -> -2.0735269 | AU72: =Act!L71 -> 0.6104712 | AV72: =H72-AU72 -> #VALUE! | AX72: =IF('FC5+7'!S$3=1,'FC5+7'!S71,"") -> -1.953547 | AY72: =IF('FC5+7'!T$3=1,'FC5+7'!T71,"") | AZ72: =IF('FC5+7'!U$3=1,'FC5+7'!U71,"") | BA72: =SUM(AX72:AZ72) -> -1.953547 | BB72: =IFERROR(F72-AX72,0) -> 0 | BC72: =IFERROR(G72-AY72,0) -> 0 | BD72: =IFERROR(H72-AZ72,0) -> 0 | BE72: =IFERROR(I72-BA72,0) -> 0 | BG72: =F72 -> -1.953547 | BH72: 0 | BI72: 0 | BJ72: =SUM(BG72:BI72) -> -1.953547 | BK72: =IFERROR(F72-AC72,0) -> -2.835397 | BL72: =IFERROR(G72-AD72,0) -> 0 | BM72: =IFERROR(AL72-AE72,0) -> 0 | BN72: =IFERROR(I72-BJ72,0) -> 0 | BP72: =F72 -> -1.953547 | BQ72: =G72 | BR72: =#REF! -> #REF! | BS72: =SUM(BP72:BR72) -> #REF! | BT72: =BP72-AC72 -> -2.835397 | BU72: =BQ72-AD72 -> #VALUE! | BV72: =BR72-AE72 -> #REF! | BW72: =BS72-AF72 -> #REF! | BY72: =H72-BR72 -> #VALUE! | CA72: ='FC2+10'!AA71 -> 0 | CC72: =CA72-I72 -> 1.953547 | CE72: =IF('FC7+5'!S$3=1,'FC7+5'!S71,"") -> -1.953547 | CF72: =IF('FC7+5'!T$3=1,'FC7+5'!T71,"") | CG72: =IF('FC7+5'!U$3=1,'FC7+5'!U71,"") | CH72: =SUM(CE72:CG72) -> -1.953547 | CI72: =IFERROR(F72-CE72,0) -> 0 | CJ72: =IFERROR(G72-CF72,0) -> 0 | CK72: =IFERROR(H72-CG72,0) -> 0 | CL72: =IFERROR(I72-CH72,0) -> 0 | CM72: =IF('FC7+5'!AC$3=1,'FC7+5'!AC71,"") -> 0 | CN72: =I72-CM72 -> -1.953547
A73: AS | D73: NII | F73: =IF(Act!S$3=1,Act!S72,"") -> 0.141 | G73: =IF(Act!T$3=1,Act!T72,"") | H73: =IF(Act!U$3=1,Act!U72,"") | I73: =SUM(F73:H73) -> 0.141 | K73: =IF(BP!S$3=1,BP!S72,"") -> 0.41616 | L73: =IF(BP!T$3=1,BP!T72,"") | M73: =IF(BP!U$3=1,BP!U72,"") | N73: =SUM(K73:M73) -> 0.41616 | O73: =IFERROR(F73-K73,0) -> -0.27516 | P73: =IFERROR(G73-L73,0) -> 0 | Q73: =IFERROR(H73-M73,0) -> 0 | R73: =I73-N73 -> -0.27516 | T73: =IF('FC2+10'!S$3=1,'FC2+10'!S72,"") -> 0.141 | U73: =IF('FC2+10'!T$3=1,'FC2+10'!T72,"") | V73: =IF('FC2+10'!U$3=1,'FC2+10'!U72,"") | W73: =SUM(T73:V73) -> 0.141 | X73: =IFERROR(F73-T73,0) -> 0 | Y73: =IFERROR(G73-U73,0) -> 0 | Z73: =IFERROR(H73-V73,0) -> 0 | AA73: =I73-W73 -> 0 | AC73: =IF(OL!S$3=1,OL!S72,"") -> 1.6693 | AD73: =IF(OL!T$3=1,OL!T72,"") -> 0.123 | AE73: =IF(OL!U$3=1,OL!U72,"") | AF73: =SUM(AC73:AE73) -> 1.7923 | AG73: =IFERROR(F73-AC73,0) -> -1.5283 | AH73: =IFERROR(G73-AD73,0) -> 0 | AI73: =IFERROR(H73-AE73,0) -> 0 | AJ73: =IFERROR(I73-AF73,0) -> -1.6513 | AL73: =IF(LY!S$3=1,LY!S72,"") -> 0.938 | AM73: =IF(LY!T$3=1,LY!T72,"") | AN73: =IF(LY!U$3=1,LY!U72,"") | AO73: =SUM(AL73:AN73) -> 0.938 | AP73: =IFERROR(F73-AL73,0) -> -0.797 | AQ73: =IFERROR(G73-AM73,0) -> 0 | AR73: =IFERROR(H73-AN73,0) -> 0 | AS73: =IFERROR(I73-AO73,0) -> -0.797 | AU73: =Act!L72 -> 0.554 | AV73: =H73-AU73 -> #VALUE! | AX73: =IF('FC5+7'!S$3=1,'FC5+7'!S72,"") -> 0.141 | AY73: =IF('FC5+7'!T$3=1,'FC5+7'!T72,"") | AZ73: =IF('FC5+7'!U$3=1,'FC5+7'!U72,"") | BA73: =SUM(AX73:AZ73) -> 0.141 | BB73: =IFERROR(F73-AX73,0) -> 0 | BC73: =IFERROR(G73-AY73,0) -> 0 | BD73: =IFERROR(H73-AZ73,0) -> 0 | BE73: =IFERROR(I73-BA73,0) -> 0 | BG73: =F73 -> 0.141 | BH73: 0.44816 | BI73: 0.48116 | BJ73: =SUM(BG73:BI73) -> 1.07032 | BK73: =IFERROR(F73-AC73,0) -> -1.5283 | BL73: =IFERROR(G73-AD73,0) -> 0 | BM73: =IFERROR(AL73-AE73,0) -> 0 | BN73: =IFERROR(I73-BJ73,0) -> -0.92932 | BP73: =F73 -> 0.141 | BQ73: =G73 | BR73: =#REF! -> #REF! | BS73: =SUM(BP73:BR73) -> #REF! | BT73: =BP73-AC73 -> -1.5283 | BU73: =BQ73-AD73 -> #VALUE! | BV73: =BR73-AE73 -> #REF! | BW73: =BS73-AF73 -> #REF! | BY73: =H73-BR73 -> #VALUE! | CA73: ='FC2+10'!AA72 -> 1.68148 | CC73: =CA73-I73 -> 1.54048 | CE73: =IF('FC7+5'!S$3=1,'FC7+5'!S72,"") -> 0.141 | CF73: =IF('FC7+5'!T$3=1,'FC7+5'!T72,"") | CG73: =IF('FC7+5'!U$3=1,'FC7+5'!U72,"") | CH73: =SUM(CE73:CG73) -> 0.141 | CI73: =IFERROR(F73-CE73,0) -> 0 | CJ73: =IFERROR(G73-CF73,0) -> 0 | CK73: =IFERROR(H73-CG73,0) -> 0 | CL73: =IFERROR(I73-CH73,0) -> 0 | CM73: =IF('FC7+5'!AC$3=1,'FC7+5'!AC72,"") -> 1.743 | CN73: =I73-CM73 -> -1.602
A74: G&A | D74: G&A reclass | F74: =IF(Act!S$3=1,Act!S73,"") -> 2.254644 | G74: =IF(Act!T$3=1,Act!T73,"") | H74: =IF(Act!U$3=1,Act!U73,"") | I74: =SUM(F74:H74) -> 2.254644 | K74: =IF(BP!S$3=1,BP!S73,"") -> 2.4651424 | L74: =IF(BP!T$3=1,BP!T73,"") | M74: =IF(BP!U$3=1,BP!U73,"") | N74: =SUM(K74:M74) -> 2.4651424 | O74: =IFERROR(F74-K74,0) -> -0.21049839 | P74: =IFERROR(G74-L74,0) -> 0 | Q74: =IFERROR(H74-M74,0) -> 0 | R74: =I74-N74 -> -0.21049839 | T74: =IF('FC2+10'!S$3=1,'FC2+10'!S73,"") -> 2.254644 | U74: =IF('FC2+10'!T$3=1,'FC2+10'!T73,"") | V74: =IF('FC2+10'!U$3=1,'FC2+10'!U73,"") | W74: =SUM(T74:V74) -> 2.254644 | X74: =IFERROR(F74-T74,0) -> 0 | Y74: =IFERROR(G74-U74,0) -> 0 | Z74: =IFERROR(H74-V74,0) -> 0 | AA74: =I74-W74 -> 0 | AC74: =IF(OL!S$3=1,OL!S73,"") -> 1.3988883 | AD74: =IF(OL!T$3=1,OL!T73,"") -> 1.5284343 | AE74: =IF(OL!U$3=1,OL!U73,"") | AF74: =SUM(AC74:AE74) -> 2.9273226 | AG74: =IFERROR(F74-AC74,0) -> 0.85575567 | AH74: =IFERROR(G74-AD74,0) -> 0 | AI74: =IFERROR(H74-AE74,0) -> 0 | AJ74: =IFERROR(I74-AF74,0) -> -0.6726786 | AL74: =IF(LY!S$3=1,LY!S73,"") -> 2.2146807 | AM74: =IF(LY!T$3=1,LY!T73,"") | AN74: =IF(LY!U$3=1,LY!U73,"") | AO74: =SUM(AL74:AN74) -> 2.2146807 | AP74: =IFERROR(F74-AL74,0) -> 0.039963339 | AQ74: =IFERROR(G74-AM74,0) -> 0 | AR74: =IFERROR(H74-AN74,0) -> 0 | AS74: =IFERROR(I74-AO74,0) -> 0.039963339 | AU74: =Act!L73 -> 0.90222124 | AV74: =H74-AU74 -> #VALUE! | AX74: =IF('FC5+7'!S$3=1,'FC5+7'!S73,"") -> 2.254644 | AY74: =IF('FC5+7'!T$3=1,'FC5+7'!T73,"") | AZ74: =IF('FC5+7'!U$3=1,'FC5+7'!U73,"") | BA74: =SUM(AX74:AZ74) -> 2.254644 | BB74: =IFERROR(F74-AX74,0) -> 0 | BC74: =IFERROR(G74-AY74,0) -> 0 | BD74: =IFERROR(H74-AZ74,0) -> 0 | BE74: =IFERROR(I74-BA74,0) -> 0 | BG74: =F74 -> 2.254644 | BH74: 2.5 | BI74: 2.5 | BJ74: =SUM(BG74:BI74) -> 7.254644 | BK74: =IFERROR(F74-AC74,0) -> 0.85575567 | BL74: =IFERROR(G74-AD74,0) -> 0 | BM74: =IFERROR(AL74-AE74,0) -> 0 | BN74: =IFERROR(I74-BJ74,0) -> -5 | BP74: =F74 -> 2.254644 | BQ74: =G74 | BR74: =#REF! -> #REF! | BS74: =SUM(BP74:BR74) -> #REF! | BT74: =BP74-AC74 -> 0.85575567 | BU74: =BQ74-AD74 -> #VALUE! | BV74: =BR74-AE74 -> #REF! | BW74: =BS74-AF74 -> #REF! | BY74: =H74-BR74 -> #VALUE! | CA74: ='FC2+10'!AA73 -> 4.9592228 | CC74: =CA74-I74 -> 2.7045788 | CE74: =IF('FC7+5'!S$3=1,'FC7+5'!S73,"") -> 2.254644 | CF74: =IF('FC7+5'!T$3=1,'FC7+5'!T73,"") | CG74: =IF('FC7+5'!U$3=1,'FC7+5'!U73,"") | CH74: =SUM(CE74:CG74) -> 2.254644 | CI74: =IFERROR(F74-CE74,0) -> 0 | CJ74: =IFERROR(G74-CF74,0) -> 0 | CK74: =IFERROR(H74-CG74,0) -> 0 | CL74: =IFERROR(I74-CH74,0) -> 0 | CM74: =IF('FC7+5'!AC$3=1,'FC7+5'!AC73,"") -> 4.5991936 | CN74: =I74-CM74 -> -2.3445496
A75: MZ now | D75: Legacy Claims | F75: =IF(Act!S$3=1,Act!S74,"") -> 0 | G75: =IF(Act!T$3=1,Act!T74,"") | H75: =IF(Act!U$3=1,Act!U74,"") | I75: =SUM(F75:H75) -> 0 | K75: =IF(BP!S$3=1,BP!S74,"") -> 0 | L75: =IF(BP!T$3=1,BP!T74,"") | M75: =IF(BP!U$3=1,BP!U74,"") | N75: =SUM(K75:M75) -> 0 | O75: =IFERROR(F75-K75,0) -> 0 | P75: =IFERROR(G75-L75,0) -> 0 | Q75: =IFERROR(H75-M75,0) -> 0 | R75: =I75-N75 -> 0 | T75: =IF('FC2+10'!S$3=1,'FC2+10'!S74,"") -> 0 | U75: =IF('FC2+10'!T$3=1,'FC2+10'!T74,"") | V75: =IF('FC2+10'!U$3=1,'FC2+10'!U74,"") | W75: =SUM(T75:V75) -> 0 | X75: =IFERROR(F75-T75,0) -> 0 | Y75: =IFERROR(G75-U75,0) -> 0 | Z75: =IFERROR(H75-V75,0) -> 0 | AA75: =I75-W75 -> 0 | AC75: =IF(OL!S$3=1,OL!S74,"") -> 0 | AD75: =IF(OL!T$3=1,OL!T74,"") -> 17.9 | AE75: =IF(OL!U$3=1,OL!U74,"") | AF75: =SUM(AC75:AE75) -> 17.9 | AG75: =IFERROR(F75-AC75,0) -> 0 | AH75: =IFERROR(G75-AD75,0) -> 0 | AI75: =IFERROR(H75-AE75,0) -> 0 | AJ75: =IFERROR(I75-AF75,0) -> -17.9 | AL75: =IF(LY!S$3=1,LY!S74,"") -> 0 | AM75: =IF(LY!T$3=1,LY!T74,"") | AN75: =IF(LY!U$3=1,LY!U74,"") | AO75: =SUM(AL75:AN75) -> 0 | AP75: =IFERROR(F75-AL75,0) -> 0 | AQ75: =IFERROR(G75-AM75,0) -> 0 | AR75: =IFERROR(H75-AN75,0) -> 0 | AS75: =IFERROR(I75-AO75,0) -> 0 | AU75: =Act!L74 -> 0 | AV75: =H75-AU75 -> #VALUE! | AX75: =IF('FC5+7'!S$3=1,'FC5+7'!S74,"") -> 0 | AY75: =IF('FC5+7'!T$3=1,'FC5+7'!T74,"") | AZ75: =IF('FC5+7'!U$3=1,'FC5+7'!U74,"") | BA75: =SUM(AX75:AZ75) -> 0 | BB75: =IFERROR(F75-AX75,0) -> 0 | BC75: =IFERROR(G75-AY75,0) -> 0 | BD75: =IFERROR(H75-AZ75,0) -> 0 | BE75: =IFERROR(I75-BA75,0) -> 0 | BG75: =F75 -> 0 | BH75: 0 | BI75: 0 | BJ75: =SUM(BG75:BI75) -> 0 | BK75: =IFERROR(F75-AC75,0) -> 0 | BL75: =IFERROR(G75-AD75,0) -> 0 | BM75: =IFERROR(AL75-AE75,0) -> 0 | BN75: =IFERROR(I75-BJ75,0) -> 0 | BS75: =SUM(BP75:BR75) -> 0 | BT75: =BP75-AC75 -> 0 | BU75: =BQ75-AD75 -> -17.9 | BV75: =BR75-AE75 -> #VALUE! | BW75: =BS75-AF75 -> -17.9 | BY75: =H75-BR75 -> #VALUE! | CA75: ='FC2+10'!AA74 -> 0 | CC75: =CA75-I75 -> 0 | CE75: =IF('FC7+5'!S$3=1,'FC7+5'!S74,"") -> 0 | CF75: =IF('FC7+5'!T$3=1,'FC7+5'!T74,"") | CG75: =IF('FC7+5'!U$3=1,'FC7+5'!U74,"") | CH75: =SUM(CE75:CG75) -> 0 | CI75: =IFERROR(F75-CE75,0) -> 0 | CJ75: =IFERROR(G75-CF75,0) -> 0 | CK75: =IFERROR(H75-CG75,0) -> 0 | CL75: =IFERROR(I75-CH75,0) -> 0 | CM75: =IF('FC7+5'!AC$3=1,'FC7+5'!AC74,"") -> 0 | CN75: =I75-CM75 -> 0
A76: OCS TdC | D76: Compact EV/VT Impairment | F76: =IF(Act!S$3=1,Act!S75,"") -> 0 | G76: =IF(Act!T$3=1,Act!T75,"") | H76: =IF(Act!U$3=1,Act!U75,"") | I76: =SUM(F76:H76) -> 0 | K76: =IF(BP!S$3=1,BP!S75,"") -> 0 | L76: =IF(BP!T$3=1,BP!T75,"") | M76: =IF(BP!U$3=1,BP!U75,"") | N76: =SUM(K76:M76) -> 0 | O76: =IFERROR(F76-K76,0) -> 0 | P76: =IFERROR(G76-L76,0) -> 0 | Q76: =IFERROR(H76-M76,0) -> 0 | R76: =I76-N76 -> 0 | T76: =IF('FC2+10'!S$3=1,'FC2+10'!S75,"") -> 0 | U76: =IF('FC2+10'!T$3=1,'FC2+10'!T75,"") | V76: =IF('FC2+10'!U$3=1,'FC2+10'!U75,"") | W76: =SUM(T76:V76) -> 0 | X76: =IFERROR(F76-T76,0) -> 0 | Y76: =IFERROR(G76-U76,0) -> 0 | Z76: =IFERROR(H76-V76,0) -> 0 | AA76: =I76-W76 -> 0 | AE76: =IF(OL!U$3=1,OL!U75,"") | AF76: =SUM(AC76:AE76) -> 0 | AG76: =IFERROR(F76-AC76,0) -> 0 | AH76: =IFERROR(G76-AD76,0) -> 0 | AI76: =IFERROR(H76-AE76,0) -> 0 | AJ76: =IFERROR(I76-AF76,0) -> 0 | AL76: =IF(LY!S$3=1,LY!S75,"") -> 0 | AM76: =IF(LY!T$3=1,LY!T75,"") | AN76: =IF(LY!U$3=1,LY!U75,"") | AO76: =SUM(AL76:AN76) -> 0 | AP76: =IFERROR(F76-AL76,0) -> 0 | AQ76: =IFERROR(G76-AM76,0) -> 0 | AR76: =IFERROR(H76-AN76,0) -> 0 | AS76: =IFERROR(I76-AO76,0) -> 0 | AU76: =Act!L75 -> 0 | AV76: =H76-AU76 -> #VALUE! | AX76: =IF('FC5+7'!S$3=1,'FC5+7'!S75,"") -> 0 | AY76: =IF('FC5+7'!T$3=1,'FC5+7'!T75,"") | AZ76: =IF('FC5+7'!U$3=1,'FC5+7'!U75,"") | BA76: =SUM(AX76:AZ76) -> 0 | BB76: =IFERROR(F76-AX76,0) -> 0 | BC76: =IFERROR(G76-AY76,0) -> 0 | BD76: =IFERROR(H76-AZ76,0) -> 0 | BE76: =IFERROR(I76-BA76,0) -> 0 | BG76: =F76 -> 0 | BH76: 0 | BI76: 0 | BJ76: =SUM(BG76:BI76) -> 0 | BK76: =IFERROR(F76-AC76,0) -> 0 | BL76: =IFERROR(G76-AD76,0) -> 0 | BM76: =IFERROR(AL76-AE76,0) -> 0 | BN76: =IFERROR(I76-BJ76,0) -> 0 | BS76: =SUM(BP76:BR76) -> 0 | BT76: =BP76-AC76 -> 0 | BU76: =BQ76-AD76 -> 0 | BV76: =BR76-AE76 -> #VALUE! | BW76: =BS76-AF76 -> 0 | BY76: =H76-BR76 -> #VALUE! | CA76: ='FC2+10'!AA75 -> 0 | CC76: =CA76-I76 -> 0 | CE76: =IF('FC7+5'!S$3=1,'FC7+5'!S75,"") -> 0 | CF76: =IF('FC7+5'!T$3=1,'FC7+5'!T75,"") | CG76: =IF('FC7+5'!U$3=1,'FC7+5'!U75,"") | CH76: =SUM(CE76:CG76) -> 0 | CI76: =IFERROR(F76-CE76,0) -> 0 | CJ76: =IFERROR(G76-CF76,0) -> 0 | CK76: =IFERROR(H76-CG76,0) -> 0 | CL76: =IFERROR(I76-CH76,0) -> 0 | CM76: =IF('FC7+5'!AC$3=1,'FC7+5'!AC75,"") -> 0 | CN76: =I76-CM76 -> 0
D77: MZ impairment | F77: =IF(Act!S$3=1,Act!S76,"") -> 0 | G77: =IF(Act!T$3=1,Act!T76,"") | H77: =IF(Act!U$3=1,Act!U76,"") | I77: =SUM(F77:H77) -> 0 | K77: =IF(BP!S$3=1,BP!S76,"") -> 0 | L77: =IF(BP!T$3=1,BP!T76,"") | M77: =IF(BP!U$3=1,BP!U76,"") | N77: =SUM(K77:M77) -> 0 | O77: =IFERROR(F77-K77,0) -> 0 | P77: =IFERROR(G77-L77,0) -> 0 | Q77: =IFERROR(H77-M77,0) -> 0 | R77: =I77-N77 -> 0 | T77: =IF('FC2+10'!S$3=1,'FC2+10'!S76,"") -> 0 | U77: =IF('FC2+10'!T$3=1,'FC2+10'!T76,"") | V77: =IF('FC2+10'!U$3=1,'FC2+10'!U76,"") | W77: =SUM(T77:V77) -> 0 | X77: =IFERROR(F77-T77,0) -> 0 | Y77: =IFERROR(G77-U77,0) -> 0 | Z77: =IFERROR(H77-V77,0) -> 0 | AA77: =I77-W77 -> 0 | AE77: =IF(OL!U$3=1,OL!U76,"") | AF77: =SUM(AC77:AE77) -> 0 | AG77: =IFERROR(F77-AC77,0) -> 0 | AH77: =IFERROR(G77-AD77,0) -> 0 | AI77: =IFERROR(H77-AE77,0) -> 0 | AJ77: =IFERROR(I77-AF77,0) -> 0 | AL77: =IF(LY!S$3=1,LY!S76,"") -> 0 | AM77: =IF(LY!T$3=1,LY!T76,"") | AN77: =IF(LY!U$3=1,LY!U76,"") | AO77: =SUM(AL77:AN77) -> 0 | AP77: =IFERROR(F77-AL77,0) -> 0 | AQ77: =IFERROR(G77-AM77,0) -> 0 | AR77: =IFERROR(H77-AN77,0) -> 0 | AS77: =IFERROR(I77-AO77,0) -> 0 | AU77: =Act!L76 -> 0 | AV77: =H77-AU77 -> #VALUE! | AX77: 0 | AY77: 0 | AZ77: 0 | BA77: =SUM(AX77:AZ77) -> 0 | BB77: 0 | BC77: 0 | BD77: 0 | BE77: 0 | BG77: =F77 -> 0 | BH77: 0 | BI77: 0 | BJ77: =SUM(BG77:BI77) -> 0 | BK77: =IFERROR(F77-AC77,0) -> 0 | BL77: =IFERROR(G77-AD77,0) -> 0 | BM77: =IFERROR(AL77-AE77,0) -> 0 | BN77: =IFERROR(I77-BJ77,0) -> 0 | BS77: =SUM(BP77:BR77) -> 0 | BT77: =BP77-AC77 -> 0 | BU77: =BQ77-AD77 -> 0 | BV77: =BR77-AE77 -> #VALUE! | BW77: =BS77-AF77 -> 0 | BY77: =H77-BR77 -> #VALUE! | CA77: ='FC2+10'!AA76 -> 0 | CC77: =CA77-I77 -> 0 | CE77: 0 | CF77: 0 | CG77: 0 | CH77: =SUM(CE77:CG77) -> 0 | CI77: =IFERROR(F77-CE77,0) -> 0 | CJ77: =IFERROR(G77-CF77,0) -> 0 | CK77: =IFERROR(H77-CG77,0) -> 0 | CL77: =IFERROR(I77-CH77,0) -> 0 | CM77: 0 | CN77: =I77-CM77 -> 0
D78: G&A Impairment | F78: =IF(Act!S$3=1,Act!S77,"") -> 0 | G78: =IF(Act!T$3=1,Act!T77,"") | H78: =IF(Act!U$3=1,Act!U77,"") | I78: =SUM(F78:H78) -> 0 | K78: =IF(BP!S$3=1,BP!S77,"") -> 0 | L78: =IF(BP!T$3=1,BP!T77,"") | M78: =IF(BP!U$3=1,BP!U77,"") | N78: =SUM(K78:M78) -> 0 | O78: =IFERROR(F78-K78,0) -> 0 | P78: =IFERROR(G78-L78,0) -> 0 | Q78: =IFERROR(H78-M78,0) -> 0 | R78: =I78-N78 -> 0 | T78: =IF('FC2+10'!S$3=1,'FC2+10'!S77,"") -> 0 | U78: =IF('FC2+10'!T$3=1,'FC2+10'!T77,"") | V78: =IF('FC2+10'!U$3=1,'FC2+10'!U77,"") | W78: =SUM(T78:V78) -> 0 | X78: =IFERROR(F78-T78,0) -> 0 | Y78: =IFERROR(G78-U78,0) -> 0 | Z78: =IFERROR(H78-V78,0) -> 0 | AA78: =I78-W78 -> 0 | AE78: =IF(OL!U$3=1,OL!U77,"") | AF78: =SUM(AC78:AE78) -> 0 | AG78: =IFERROR(F78-AC78,0) -> 0 | AH78: =IFERROR(G78-AD78,0) -> 0 | AI78: =IFERROR(H78-AE78,0) -> 0 | AJ78: =IFERROR(I78-AF78,0) -> 0 | AL78: =IF(LY!S$3=1,LY!S77,"") -> 0 | AM78: =IF(LY!T$3=1,LY!T77,"") | AN78: =IF(LY!U$3=1,LY!U77,"") | AO78: =SUM(AL78:AN78) -> 0 | AP78: =IFERROR(F78-AL78,0) -> 0 | AQ78: =IFERROR(G78-AM78,0) -> 0 | AR78: =IFERROR(H78-AN78,0) -> 0 | AS78: =IFERROR(I78-AO78,0) -> 0 | AU78: =Act!L77 -> 0 | AV78: =H78-AU78 -> #VALUE! | AX78: 0 | AY78: 0 | AZ78: 0 | BA78: =SUM(AX78:AZ78) -> 0 | BB78: 0 | BC78: 0 | BD78: 0 | BE78: 0 | BG78: =F78 -> 0 | BH78: 0 | BI78: 0 | BJ78: =SUM(BG78:BI78) -> 0 | BK78: =IFERROR(F78-AC78,0) -> 0 | BL78: =IFERROR(G78-AD78,0) -> 0 | BM78: =IFERROR(AL78-AE78,0) -> 0 | BN78: =IFERROR(I78-BJ78,0) -> 0 | BP78: 0 | BQ78: -2.9959 | BS78: =SUM(BP78:BR78) -> -2.9959 | BT78: =BP78-AC78 -> 0 | BU78: =BQ78-AD78 -> -2.9959 | BV78: =BR78-AE78 -> #VALUE! | BW78: =BS78-AF78 -> -2.9959 | BY78: =H78-BR78 -> #VALUE! | CA78: ='FC2+10'!AA77 -> 0 | CC78: =CA78-I78 -> 0 | CE78: 0 | CF78: 0 | CG78: 0 | CH78: =SUM(CE78:CG78) -> 0 | CI78: =IFERROR(F78-CE78,0) -> 0 | CJ78: =IFERROR(G78-CF78,0) -> 0 | CK78: =IFERROR(H78-CG78,0) -> 0 | CL78: =IFERROR(I78-CH78,0) -> 0 | CM78: 0 | CN78: =I78-CM78 -> 0
B79: MZ | D79: Others | W79: =SUM(T79:V79) -> 0 | X79: =IFERROR(F79-T79,0) -> 0 | Y79: =IFERROR(G79-U79,0) -> 0 | Z79: =IFERROR(H79-V79,0) -> 0 | AA79: =I79-W79 -> 0 | AE79: =IF(OL!U$3=1,OL!U78,"") | AO79: =SUM(AL79:AN79) -> 0 | AP79: =IFERROR(F79-AL79,0) -> 0 | AQ79: =IFERROR(G79-AM79,0) -> 0 | AR79: =IFERROR(H79-AN79,0) -> 0 | AS79: =IFERROR(I79-AO79,0) -> 0 | AU79: =Act!L78 -> 0 | AV79: =H79-AU79 -> 0 | CC79: =CA79-I79 -> 0 | CN79: =I79-CM79 -> 0
E81: check | F81: =IFERROR(F47-SUM(F63:F78)-F55,0) -> 2.8421709e-14 | G81: =IFERROR(G47-SUM(G63:G78)-G55,0) -> 0 | H81: =IFERROR(H47-SUM(H63:H78)-H55,0) -> 0 | I81: =IFERROR(I47-SUM(I63:I78)-I55,0) -> 2.8421709e-14 | J81: =IFERROR(J47-SUM(J63:J75)-J55,0) -> 0 | K81: =IFERROR(K47-SUM(K63:K78)-K55,0) -> -5.6843419e-14 | L81: =IFERROR(L47-SUM(L63:L78)-L55,0) -> 0 | M81: =IFERROR(M47-SUM(M63:M78)-M55,0) -> 0 | N81: =IFERROR(N47-SUM(N63:N78)-N55,0) -> -5.6843419e-14 | O81: =IFERROR(O47-SUM(O63:O78)-O55,0) -> 8.1712415e-14 | P81: =IFERROR(P47-SUM(P63:P78)-P55,0) -> 0 | Q81: =IFERROR(Q47-SUM(Q63:Q78)-Q55,0) -> 0 | R81: =IFERROR(R47-SUM(R63:R78)-R55,0) -> 8.1712415e-14 | S81: =IFERROR(S47-SUM(S63:S75)-S55,0) -> 0 | T81: =IFERROR(T47-SUM(T63:T79)-T55,0) -> 0 | U81: =IFERROR(U47-SUM(U63:U79)-U55,0) -> 0 | V81: =IFERROR(V47-SUM(V63:V79)-V55,0) -> 0 | W81: =IFERROR(W47-SUM(W63:W79)-W55,0) -> 0 | X81: =IFERROR(X47-SUM(X63:X79)-X55,0) -> 0 | Y81: =IFERROR(Y47-SUM(Y63:Y79)-Y55,0) -> 0 | Z81: =IFERROR(Z47-SUM(Z63:Z79)-Z55,0) -> 0 | AA81: =IFERROR(AA47-SUM(AA63:AA79)-AA55,0) -> 0 | AB81: =IFERROR(AB47-SUM(AB63:AB75)-AB55,0) -> 0 | AC81: =IFERROR(AC47-SUM(AC63:AC75)-AC55,0) -> 0 | AD81: =IFERROR(AD47-SUM(AD63:AD75)-AD55,0) -> 0 | AE81: =IFERROR(AE47-SUM(AE63:AE75)-AE55,0) -> 0 | AF81: =IFERROR(AF47-SUM(AF63:AF75)-AF55,0) -> 7.1054274e-15 | AG81: =IFERROR(AG47-SUM(AG63:AG75)-AG55,0) -> 2.8421709e-14 | AH81: =IFERROR(AH47-SUM(AH63:AH75)-AH55,0) -> -23.286652 | AI81: =IFERROR(AI47-SUM(AI63:AI75)-AI55,0) -> 0 | ... AK81: =IFERROR(AK47-SUM(AK63:AK75)-AK55,0) -> 0 | AL81: =IFERROR(AL47-SUM(AL63:AL78)-AL55,0) -> -5.6843419e-14 | AM81: =IFERROR(AM47-SUM(AM63:AM78)-AM55,0) -> 0 | AN81: =IFERROR(AN47-SUM(AN63:AN78)-AN55,0) -> 0 | AO81: =IFERROR(AO47-SUM(AO63:AO78)-AO55,0) -> -5.6843419e-14 | AP81: =IFERROR(AP47-SUM(AP63:AP78)-AP55,0) -> 7.1054274e-14 | AQ81: =IFERROR(AQ47-SUM(AQ63:AQ78)-AQ55,0) -> 0 | AR81: =IFERROR(AR47-SUM(AR63:AR78)-AR55,0) -> 0 | AS81: =IFERROR(AS47-SUM(AS63:AS78)-AS55,0) -> 7.1054274e-14 | AU81: =IFERROR(AU47-SUM(AU63:AU78)-AU55,0) -> 7.1054274e-14 | AV81: =IFERROR(AV47-SUM(AV63:AV78)-AV55,0) -> 0 | AW81: =IFERROR(AW47-SUM(AW63:AW78)-AW55,0) -> 0 | AX81: =IFERROR(AX47-SUM(AX63:AX77)-AX55,0) -> 0 | AY81: =IFERROR(AY47-SUM(AY63:AY77)-AY55,0) -> 0 | AZ81: =IFERROR(AZ47-SUM(AZ63:AZ77)-AZ55,0) -> 0 | BA81: =IFERROR(BA47-SUM(BA63:BA77)-BA55,0) -> 0 | BB81: =IFERROR(BB47-SUM(BB63:BB77)-BB55,0) -> 2.8421709e-14 | BC81: =IFERROR(BC47-SUM(BC63:BC77)-BC55,0) -> 0 | BD81: =IFERROR(BD47-SUM(BD63:BD77)-BD55,0) -> 0 | BE81: =IFERROR(BE47-SUM(BE63:BE77)-BE55,0) -> 2.8421709e-14 | BF81: =IFERROR(BF47-SUM(BF63:BF78)-BF55,0) -> 0 | BG81: =IFERROR(BG47-SUM(BG63:BG78)-BG55,0) -> 2.8421709e-14 | BH81: =IFERROR(BH47-SUM(BH63:BH78)-BH55,0) -> 1.4210855e-14 | BI81: =IFERROR(BI47-SUM(BI63:BI78)-BI55,0) -> 0 | BJ81: =IFERROR(BJ47-SUM(BJ63:BJ78)-BJ55,0) -> 2.8421709e-14 | BK81: =IFERROR(BK47-SUM(BK63:BK78)-BK55,0) -> 2.8421709e-14 | BL81: =IFERROR(BL47-SUM(BL63:BL78)-BL55,0) -> -23.286652 | BM81: =IFERROR(BM47-SUM(BM63:BM78)-BM55,0) -> 35.570225 | BN81: =IFERROR(BN47-SUM(BN63:BN78)-BN55,0) -> -1.4210855e-14 | BP81: =IFERROR(BP47-SUM(BP63:BP78)-BP55,0) -> 17.900473 | BQ81: =IFERROR(BQ47-SUM(BQ63:BQ78)-BQ55,0) -> 36.831082 | BR81: =IFERROR(BR47-SUM(BR63:BR78)-BR55,0) -> 0 | BS81: =IFERROR(BS47-SUM(BS63:BS78)-BS55,0) -> 0 | BT81: =IFERROR(BT47-SUM(BT63:BT78)-BT55,0) -> 17.900473 | BU81: =IFERROR(BU47-SUM(BU63:BU78)-BU55,0) -> 0 | BV81: =IFERROR(BV47-SUM(BV63:BV78)-BV55,0) -> 0 | BW81: =IFERROR(BW47-SUM(BW63:BW78)-BW55,0) -> 0 | BY81: =IFERROR(BY47-SUM(BY63:BY78)-BY55,0) -> 0 | CA81: =IFERROR(CA47-SUM(CA63:CA78)-CA55,0) -> 0 | CC81: =IFERROR(CC47-SUM(CC63:CC78)-CC55,0) -> 0 | CE81: =IFERROR(CE47-SUM(CE63:CE77)-CE55,0) -> 2.8421709e-14 | CF81: =IFERROR(CF47-SUM(CF63:CF77)-CF55,0) -> 0 | CG81: =IFERROR(CG47-SUM(CG63:CG77)-CG55,0) -> 0 | CH81: =IFERROR(CH47-SUM(CH63:CH77)-CH55,0) -> 2.8421709e-14 | CI81: =IFERROR(CI47-SUM(CI63:CI77)-CI55,0) -> 0 | CJ81: =IFERROR(CJ47-SUM(CJ63:CJ77)-CJ55,0) -> 0 | CK81: =IFERROR(CK47-SUM(CK63:CK77)-CK55,0) -> 0 | CL81: =IFERROR(CL47-SUM(CL63:CL77)-CL55,0) -> 0 | ... CN81: =IFERROR(CN47-SUM(CN63:CN77)-CN55,0) -> -2.2737368e-13
E82: CMPI | F82: =IFERROR(F27-SUM(F63:F64,F66:F71,F73),0) -> 63.237619 | G82: =IFERROR(G27-SUM(G63:G64,G66:G71,G73),0) -> 0 | H82: =IFERROR(H27-SUM(H63:H64,H66:H71,H73),0) -> 0 | I82: =IFERROR(I27-SUM(I63:I64,I66:I71,I73),0) -> 63.237619 | J82: =IFERROR(J27-SUM(J63:J64,J66:J71,J73),0) -> 0 | K82: =IFERROR(K27-SUM(K63:K64,K66:K71,K73),0) -> 64.2915 | L82: =IFERROR(L27-SUM(L63:L64,L66:L71,L73),0) -> 0 | M82: =IFERROR(M27-SUM(M63:M64,M66:M71,M73),0) -> 0 | ... S82: =IFERROR(S27-SUM(S63:S64,S66:S71,S73),0) -> 0 | T82: =IFERROR(T27-SUM(T63:T64,T66:T71,T73,T79),0) -> 0 | U82: =IFERROR(U27-SUM(U63:U64,U66:U71,U73,U79),0) -> 0 | V82: =IFERROR(V27-SUM(V63:V64,V66:V71,V73,V79),0) -> 0 | W82: =IFERROR(W27-SUM(W63:W64,W66:W71,W73,W79),0) -> 0 | X82: =IFERROR(X27-SUM(X63:X64,X66:X71,X73,X79),0) -> 0 | Y82: =IFERROR(Y27-SUM(Y63:Y64,Y66:Y71,Y73,Y79),0) -> 0 | Z82: =IFERROR(Z27-SUM(Z63:Z64,Z66:Z71,Z73,Z79),0) -> 0 | AA82: =IFERROR(AA27-SUM(AA63:AA64,AA66:AA71,AA73,AA79),0) -> 0 | AB82: =IFERROR(AB27-SUM(AB63:AB64,AB66:AB71,AB73),0) -> 0 | AC82: =IFERROR(AC27-SUM(AC63:AC64,AC66:AC71,AC73),0) -> 107.76376 | AD82: =IFERROR(AD27-SUM(AD63:AD64,AD66:AD71,AD73),0) -> 104.28659 | AE82: =IFERROR(AE27-SUM(AE63:AE64,AE66:AE71,AE73),0) -> 0 | AF82: =IFERROR(AF27-SUM(AF63:AF64,AF66:AF71,AF73),0) -> 212.05035 | AG82: =IFERROR(AG27-SUM(AG63:AG64,AG66:AG71,AG73),0) -> -44.526136 | AH82: =IFERROR(AH27-SUM(AH63:AH64,AH66:AH71,AH73),0) -> -141.14914 | AI82: =IFERROR(AI27-SUM(AI63:AI64,AI66:AI71,AI73),0) -> 0 | ... AO82: =IFERROR(AO27-SUM(AO63:AO64,AO66:AO71,AO73),0) -> 94.16159 | AP82: =IFERROR(AP27-SUM(AP63:AP64,AP66:AP71,AP73,AP76),0) -> -30.923971 | AQ82: =IFERROR(AQ27-SUM(AQ63:AQ64,AQ66:AQ71,AQ73,AQ76),0) -> 0 | AR82: =IFERROR(AR27-SUM(AR63:AR64,AR66:AR71,AR73,AR76),0) -> 0 | AS82: =IFERROR(AS27-SUM(AS63:AS64,AS66:AS71,AS73,AS76),0) -> -30.923971 | AT82: =IFERROR(AT27-SUM(AT63:AT64,AT66:AT71,AT73),0) -> 0 | AU82: =IFERROR(AU27-SUM(AU63:AU64,AU66:AU71,AU73),0) -> 83.804547 | AV82: =IFERROR(AV27-SUM(AV63:AV64,AV66:AV71,AV73),0) -> 0 | AW82: =IFERROR(AW27-SUM(AW63:AW64,AW66:AW71,AW73),0) -> 0 | AX82: =IFERROR(AX27-SUM(AX63:AX64,AX66:AX71,AX73),0) -> 63.237619 | AY82: =IFERROR(AY27-SUM(AY63:AY64,AY66:AY71,AY73),0) -> 0 | AZ82: =IFERROR(AZ27-SUM(AZ63:AZ64,AZ66:AZ71,AZ73),0) -> 0 | BA82: =IFERROR(BA27-SUM(BA63:BA64,BA66:BA71,BA73),0) -> 63.237619 | ... CC82: =IFERROR(CC27-SUM(CC63:CC64,CC66:CC71,CC73),0) -> 0 | CE82: =IFERROR(CE27-SUM(CE63:CE64,CE66:CE71,CE73),0) -> 63.237619 | CF82: =IFERROR(CF27-SUM(CF63:CF64,CF66:CF71,CF73),0) -> 0 | CG82: =IFERROR(CG27-SUM(CG63:CG64,CG66:CG71,CG73),0) -> 0 | CH82: =IFERROR(CH27-SUM(CH63:CH64,CH66:CH71,CH73),0) -> 63.237619 | CI82: =IFERROR(CI27-SUM(CI63:CI64,CI66:CI71,CI73),0) -> 0 | CJ82: =IFERROR(CJ27-SUM(CJ63:CJ64,CJ66:CJ71,CJ73),0) -> 0 | CK82: =IFERROR(CK27-SUM(CK63:CK64,CK66:CK71,CK73),0) -> 0 | CL82: =IFERROR(CL27-SUM(CL63:CL64,CL66:CL71,CL73),0) -> 0 | ... CN82: =IFERROR(CN27-SUM(CN63:CN64,CN66:CN71,CN73),0) -> -391.57209
E83: FC | F83: =IFERROR(F46-F65-F72-F74-F75-F76-F77-F78,0) -> -134.40743 | G83: =IFERROR(G46-G65-G72-G74-G75-G76-G77-G78,0) -> 0 | H83: =IFERROR(H46-H65-H72-H74-H75-H76-H77-H78,0) -> 0 | I83: =IFERROR(I46-I65-I72-I74-I75-I76-I77-I78,0) -> -134.40743 | J83: =IFERROR(J46-J65-J72-J74-J75-J76-J77-J78,0) -> 0 | K83: =IFERROR(K46-K65-K72-K74-K75-K76-K77-K78,0) -> -152.79354 | L83: =IFERROR(L46-L65-L72-L74-L75-L76-L77-L78,0) -> 0 | M83: =IFERROR(M46-M65-M72-M74-M75-M76-M77-M78,0) -> 0 | ... AK83: =IFERROR(AK46-AK65-AK72-AK74-AK75-AK76-AK77-AK78,0) -> 0 | AL83: =IFERROR(AL46-AL65-AL72-AL74-AL75-AL77-AL78,0) -> -130.54337 | AM83: =IFERROR(AM46-AM65-AM72-AM74-AM75-AM77-AM78,0) -> 0 | AN83: =IFERROR(AN46-AN65-AN72-AN74-AN75-AN77-AN78,0) -> 0 | AO83: =IFERROR(AO46-AO65-AO72-AO74-AO75-AO77-AO78,0) -> -130.54337 | AP83: =IFERROR(AP46-AP65-AP72-AP74-AP75-AP77-AP78,0) -> -3.8640681 | AQ83: =IFERROR(AQ46-AQ65-AQ72-AQ74-AQ75-AQ77-AQ78,0) -> 0 | AR83: =IFERROR(AR46-AR65-AR72-AR74-AR75-AR77-AR78,0) -> 0 | AS83: =IFERROR(AS46-AS65-AS72-AS74-AS75-AS77-AS78,0) -> -3.8640681 | AU83: =IFERROR(AU46-AU65-AU72-AU74-AU75-AU76-AU77-AU78,0) -> -111.51378 | AV83: =IFERROR(AV46-AV65-AV72-AV74-AV75-AV76-AV77-AV78,0) -> 0 | AW83: =IFERROR(AW46-AW65-AW72-AW74-AW75-AW76-AW77-AW78,0) -> 0 | AX83: =IFERROR(AX46-AX65-AX72-AX74-AX75-AX76-AX77-AX78,0) -> -134.40743 | AY83: =IFERROR(AY46-AY65-AY72-AY74-AY75-AY76-AY77-AY78,0) -> 0 | AZ83: =IFERROR(AZ46-AZ65-AZ72-AZ74-AZ75-AZ76-AZ77-AZ78,0) -> 0 | BA83: =IFERROR(BA46-BA65-BA72-BA74-BA75-BA76-BA77-BA78,0) -> -134.40743 | BB83: =IFERROR(BB46-BB65-BB72-BB74-BB75-BB76-BB77-BB78,0) -> 2.8421709e-14 | ... BN83: =IFERROR(BN46-BN65-BN72-BN74-BN75-BN76-BN77-BN78,0) -> 251.27395 | BP83: =IFERROR(BP46-BP65-BP72-BP74-BP75-BP76-BP77-BP78,0) -> -134.40743 | BQ83: =IFERROR(BQ46-BQ65-BQ72-BQ74-BQ75-BQ76-BQ77-BQ78,0) -> 0 | BR83: =IFERROR(BR46-BR65-BR72-BR74-BR75-BR76-BR77-BR78,0) -> 0 | BS83: =IFERROR(BS46-BS65-BS72-BS74-BS75-BS76-BS77-BS78,0) -> 0 | BT83: =IFERROR(BT46-BT65-BT72-BT74-BT75-BT76-BT77-BT78,0) -> -11.702104 | BU83: =IFERROR(BU46-BU65-BU72-BU74-BU75-BU76-BU77-BU78,0) -> 0 | BV83: =IFERROR(BV46-BV65-BV72-BV74-BV75-BV76-BV77-BV78,0) -> 0 | BW83: =IFERROR(BW46-BW65-BW72-BW74-BW75-BW76-BW77-BW78,0) -> 0 | BY83: =IFERROR(BY46-BY65-BY72-BY74-BY75-BY76-BY77-BY78,0) -> 0 | CA83: =IFERROR(CA46-CA65-CA72-CA74-CA75-CA76-CA77-CA78,0) -> -346.09166 | CC83: =IFERROR(CC46-CC65-CC72-CC74-CC75-CC76-CC77-CC78,0) -> -211.68423 | CE83: =IFERROR(CE46-CE65-CE72-CE74-CE75-CE76-CE77-CE78,0) -> -134.40743 | CF83: =IFERROR(CF46-CF65-CF72-CF74-CF75-CF76-CF77-CF78,0) -> 0 | CG83: =IFERROR(CG46-CG65-CG72-CG74-CG75-CG76-CG77-CG78,0) -> 0 | CH83: =IFERROR(CH46-CH65-CH72-CH74-CH75-CH76-CH77-CH78,0) -> -134.40743 | CI83: =IFERROR(CI46-CI65-CI72-CI74-CI75-CI76-CI77-CI78,0) -> 0 | CJ83: =IFERROR(CJ46-CJ65-CJ72-CJ74-CJ75-CJ76-CJ77-CJ78,0) -> 0 | CK83: =IFERROR(CK46-CK65-CK72-CK74-CK75-CK76-CK77-CK78,0) -> 0 | CL83: =IFERROR(CL46-CL65-CL72-CL74-CL75-CL76-CL77-CL78,0) -> 0 | ... CN83: =IFERROR(CN46-CN65-CN72-CN74-CN75-CN76-CN77-CN78,0) -> 219.2676
E84: Check RMPI | F84: =IFERROR(SUM(F82:F83)-F55,0) -> 1.4210855e-14 | G84: =IFERROR(SUM(G82:G83)-G55,0) -> 0 | H84: =IFERROR(SUM(H82:H83)-H55,0) -> 0 | I84: =IFERROR(SUM(I82:I83)-I55,0) -> 1.4210855e-14 | J84: =IFERROR(SUM(J82:J83)-J55,0) -> 0 | K84: =IFERROR(SUM(K82:K83)-K55,0) -> -7.1054274e-14 | L84: =IFERROR(SUM(L82:L83)-L55,0) -> 0 | M84: =IFERROR(SUM(M82:M83)-M55,0) -> 0 | ... AS84: =IFERROR(SUM(AS82:AS83)-AS55,0) -> 7.8159701e-14 | AU84: =IFERROR(SUM(AU82:AU83)-AU55,0) -> 6.3948846e-14 | AV84: =IFERROR(SUM(AV82:AV83)-AV55,0) -> 0 | AW84: =IFERROR(SUM(AW82:AW83)-AW55,0) -> 0 | AX84: =IFERROR(SUM(AX82:AX83)-AX55,0) -> -1.4210855e-14 | AY84: =IFERROR(SUM(AY82:AY83)-AY55,0) -> 0 | AZ84: =IFERROR(SUM(AZ82:AZ83)-AZ55,0) -> 0 | BA84: =IFERROR(SUM(BA82:BA83)-BA55,0) -> -1.4210855e-14 | BB84: =IFERROR(SUM(BB82:BB83)-BB55,0) -> 2.8421709e-14 | ... BN84: =IFERROR(SUM(BN82:BN83)-BN55,0) -> -1.4210855e-14 | BP84: =IFERROR(SUM(BP82:BP83)-BP55,0) -> 17.900473 | BQ84: =IFERROR(SUM(BQ82:BQ83)-BQ55,0) -> 33.835182 | BR84: =IFERROR(SUM(BR82:BR83)-BR55,0) -> 69.825243 | BS84: =IFERROR(SUM(BS82:BS83)-BS55,0) -> 192.73071 | BT84: =IFERROR(SUM(BT82:BT83)-BT55,0) -> 17.900473 | BU84: =IFERROR(SUM(BU82:BU83)-BU55,0) -> -3.1025923 | BV84: =IFERROR(SUM(BV82:BV83)-BV55,0) -> 0 | BW84: =IFERROR(SUM(BW82:BW83)-BW55,0) -> 140.85136 | BY84: =IFERROR(SUM(BY82:BY83)-BY55,0) -> 0 | CA84: =IFERROR(SUM(CA82:CA83)-CA55,0) -> -310.10699 | CC84: =IFERROR(SUM(CC82:CC83)-CC55,0) -> -246.86937 | CE84: =IFERROR(SUM(CE82:CE83)-CE55,0) -> 1.4210855e-14 | CF84: =IFERROR(SUM(CF82:CF83)-CF55,0) -> 0 | CG84: =IFERROR(SUM(CG82:CG83)-CG55,0) -> 0 | CH84: =IFERROR(SUM(CH82:CH83)-CH55,0) -> 1.4210855e-14 | CI84: =IFERROR(SUM(CI82:CI83)-CI55,0) -> 0 | CJ84: =IFERROR(SUM(CJ82:CJ83)-CJ55,0) -> 0 | CK84: =IFERROR(SUM(CK82:CK83)-CK55,0) -> 0 | CL84: =IFERROR(SUM(CL82:CL83)-CL55,0) -> 0 | ... CN84: =IFERROR(SUM(CN82:CN83)-CN55,0) -> -2.8421709e-13
BY87: =BY55-SUM(BY82:BY83) -> #VALUE! | CC87: =CC55-SUM(CC82:CC83) -> 246.86937

Sheet MTD VA vs LY
B1: ='Summary month'!E2 -> Apr | C1: =VLOOKUP(B1,mapping!$A$2:$C$13,3,0) -> M01
B3: [ROP] Variance Analysis | N3: Feb Link | O3: ='[1]P&L Actual'!$Q$6 -> 0 | S3: Completed
C5: =B10 -> LY MTD | D5: =C10 -> Act MTD | E5: var. | F5: FX | G5: Perf. | H5: check | L5: ='[2]YTD VA LY'!$I$25 -> 0
B6: RMP-i | C6: =INDEX('Summary month'!$AL$82:$AN$82,1,MATCH($C$1,'Summary month'!$O$6:$Q$6,0)) -> 94.16159 | D6: =INDEX('Summary month'!$F$82:$H$82,1,MATCH($C$1,'Summary month'!$O$6:$Q$6,0)) -> 63.237619 | E6: =+D6-C6 -> -30.923971 | F6: =B19 -> -5.4219768 | G6: =SUM(C19:S19) -> #REF! | H6: =E6-F6-G6 -> #REF!
B7: Fixed Cost | C7: ='Summary month'!AM83 -> 0 | D7: ='Summary month'!G83 -> 0 | E7: =+D7-C7 -> 0 | F7: =T19 -> 2.6826352 | G7: =SUM(U19:AH19) -> -6.5467033 | H7: =E7-F7-G7 -> 3.8640681
B8: Total | C8: =+C6+C7 -> 94.16159 | D8: =+D6+D7 -> 63.237619 | E8: =+D8-C8 -> -30.923971 | F8: =+E8-G8 -> #REF! | G8: =+G6+G7 -> #REF! | H8: =E8-F8-G8 -> #REF! | N8: The rest CMPI | O8: Royalty | P8: Export | Q8: Fixed plugged | R8: Plug between Fixed and var
G9: M EUR | K9: =SUM(K10:K11)-E12 -> 0 | N9: ='[1]New KPI vs BP'!$CA$34-P9-Q9-O9 -> -2.0765823 | O9: ='[1]New KPI vs BP'!$CA$19 -> 0.70969704 | P9: ='[1]New KPI vs BP'!$CA$15 -> -1.5175597 | Q9: =L10-AJ76+AA20 -> 0.14510341 | R9: =L9-(Q9) -> -0.14510341
B10: LY MTD | C10: Act MTD | J10: FX var | K10: =SUM(E13:E15,G13:G15) -> -5.4219768
E11: FX | F11: RMP-i | G11: Fixed Cost | I11: Check | J11: FX fixed | K11: =SUM(U20:AH20) -> 2.6826352 | AC11: Capacity reserv | AD11: ='[3]MTD vs LY'!$E$5 -> 1.0408928 | AE11: MFG out fo function
B12: =INDEX('Summary month'!$AL$55:$AN$55,1,MATCH($C$1,'Summary month'!$O$6:$Q$6,0)) -> -36.381776 | C12: =INDEX('Summary month'!$F$55:$H$55,1,MATCH($C$1,'Summary month'!$O$6:$Q$6,0)) -> -71.169814 | D12: =C12-B12 -> -34.788039 | E12: ='[1]New KPI vs BP'!$CA$34 -> -2.7393416 | F12: =INDEX('Summary month'!$AP$82:$AR$82,1,MATCH($C$1,'Summary month'!$O$6:$Q$6,0))-K10 -> -25.501994 | G12: =INDEX('Summary month'!$AP$83:$AR$83,1,MATCH($C$1,'Summary month'!$O$6:$Q$6,0))-K11 -> -6.5467033 | I12: =SUM(E12:G12)-D12 -> 7.8159701e-14 | AC12: X-badge/Micra | AD12: =-3568/1000 -> -3.568 | AE12: Nga's emails for Fixed Cost
D13: NV | E13: ='[1]New KPI vs BP'!$CA$471+'[1]New KPI vs BP'!$CA$472+'[1]New KPI vs BP'!$CA$509 -> -3.2114267 | F13: Export | G13: ='[1]New KPI vs BP'!$CA$479 -> -1.5175597 | N13: ITP MZ | O13: ='Summary month'!AQ66 -> 0 | W13: AS | X13: ='[1]P&L vs BP'!$AP$166-Y13 -> 0.1175723 | Y13: ='[1]New KPI vs BP'!$CA$494 -> 0 | AC13: R&D | AD13: ='[3]MTD vs LY'!$E$9 -> -0.52825604 | AE13: MGD out of function
D14: MZ | E14: ='[1]New KPI vs BP'!$CA$478 -> -0.15883615 | F14: Others | G14: ='[1]New KPI vs BP'!$CA$19 -> 0.70969704 | N14: ITP Import CBU | O14: ='Summary month'!AQ67 -> 0 | W14: UC | X14: ='[1]P&L vs BP'!$AP$134-Y14 -> -0.061806024 | Y14: ='[1]New KPI vs BP'!$CA$492+'[1]New KPI vs BP'!$CA$517 -> 0.006262989 | AC14: Other | AD14: =AD19-SUM(AD11:AD13) -> 2.9432113
B15: Detailed Analysis | D15: AS | E15: ='[1]New KPI vs BP'!$CA$475 -> -1.1488051 | F15: UC | G15: ='[1]New KPI vs BP'!$CA$473 -> -0.095046107 | N15: ITP Export CBU | O15: ='Summary month'!AQ68 -> 0 | R15: NII | W15: Others | X15: =X19-SUM(X13:X14) -> -0.91670241 | AA15: R&D (Functional ROP) | AB15: RS | AH15: M EUR | CE15: #NAME?
C16: RMP-I | U16: Fixed Cost
B17: FX | C17: M&S | H17: FNFR Revenue | I17: TdC | O17: ITP Change | P17: Royalty rate change | Q17: SF | R17: AS | S17: Others | T17: FX | U17: FMI | Y17: TdC | AE17: SF | AF17: AS | AH17: Others
C18: Vol. & Mix | D18: Export | E18: VME | F18: Grade Mix | G18: Pricing | I18: CR | J18: RM | K18: MFG variable | L18: SCM | M18: Others | N18: FNFR Cost | U18: FMI (M&S) | V18: CFMI | W18: Remktg | X18: FMI- out of function scope | Y18: MFG | Z18: VT | AA18: R&D *except for function | AB18: *RS (Global Function Cost) | AC18: Warranty | AD18: MFG - out of function scope | AG18: G&A (region)
B19: =K10 -> -5.4219768 | C19: ='[1]New KPI vs BP'!$CB$5+'[1]New KPI vs BP'!$CB$26-U19-V19-SUM(E19:G19) -> #REF! | D19: ='[1]New KPI vs BP'!$CB$15-O15 -> 0.89735419 | E19: =#REF!-'[2]YTD VA LY'!$E$19 -> #REF! | G19: =#REF!-'[2]YTD VA LY'!$G$19 -> #REF! | I19: =I23 -> 17.322003 | J19: =J23 -> 0.011421721 | K19: =K23 -> 2.6593172 | L19: =L23 -> -2.4193085 | M19: =M23+SUM(M39:M41) -> -13.656326 | O19: =SUM(O13:O15) -> 0 | R19: ='[1]New KPI vs BP'!$CB$9-X13 -> -0.85073942 | S19: =F12-SUM(C19:R19) -> #REF! | T19: =K11 -> 2.6826352 | U19: =INDEX('Summary month'!$AP$17:$AR$74,MATCH(U18,'Summary month'!$D$17:$D$74,0),MATCH($C$1,'Summary month'!$AP$6:$AR$6,0))-U20 -> 8.0679959 | V19: =INDEX('Summary month'!$AP$17:$AR$74,MATCH(V18,'Summary month'!$D$17:$D$74,0),MATCH($C$1,'Summary month'!$AP$6:$AR$6,0))-V20 -> 0.22122354 | X19: =INDEX('Summary month'!$AP$17:$AR$74,MATCH(X18,'Summary month'!$D$17:$D$74,0),MATCH($C$1,'Summary month'!$AP$6:$AR$6,0))-X20 -> -0.86093614 | Y19: =INDEX('Summary month'!$AP$17:$AR$74,MATCH(Y18,'Summary month'!$D$17:$D$74,0),MATCH($C$1,'Summary month'!$AP$6:$AR$6,0))-Y20 -> -1.8210009 | Z19: =INDEX('Summary month'!$AP$17:$AR$74,MATCH(Z18,'Summary month'!$D$17:$D$74,0),MATCH($C$1,'Summary month'!$AP$6:$AR$6,0))-Z20 -> 1.3616213 | AA19: =INDEX('Summary month'!$AP$17:$AR$74,MATCH(AA18,'Summary month'!$D$17:$D$74,0),MATCH($C$1,'Summary month'!$AP$6:$AR$6,0))-INDEX('Summary month'!$AP$17:$AR$74,MATCH(AA15,'Summary month'!$D$17:$D$74,0),MATCH($C$1,'Summary month'!$O$6:$Q$6,0))-AA20 -> 1.4309773 | AB19: =-INDEX('Summary month'!$AP$17:$AR$74,MATCH(AB15,'Summary month'!$D$17:$D$74,0),MATCH($C$1,'Summary month'!$O$6:$Q$6,0))-AB20 -> 2.0735269 | AC19: =INDEX('Summary month'!$AP$17:$AR$74,MATCH(AC18,'Summary month'!$D$17:$D$74,0),MATCH($C$1,'Summary month'!$AP$6:$AR$6,0))-AC20 -> -14.926453 | AD19: =INDEX('Summary month'!$AP$17:$AR$74,MATCH(AD18,'Summary month'!$D$17:$D$74,0),MATCH($C$1,'Summary month'!$AP$6:$AR$6,0))-AD20 -> -0.11215198 | AG19: =INDEX('Summary month'!$AP$17:$AR$74,MATCH(AG18,'Summary month'!$D$17:$D$74,0),MATCH($C$1,'Summary month'!$AP$6:$AR$6,0))-AG20 -> -1.9203219 | AH19: =G12-SUM(U19:AG19) -> -0.061184341
G20: Only Link to PM Var Master YTD tab file | K20: ='[1]New KPI vs BP'!$CA$10+'[1]New KPI vs BP'!$CA$12 -> -0.15883615 | U20: ='[1]New KPI vs BP'!$CA$490+'[1]New KPI vs BP'!$CA$491+'[1]New KPI vs BP'!$CA$516 -> 0.47775322 | X20: =SUM(Y13:Y14) -> 0.006262989 | Y20: ='[1]New KPI vs BP'!$CA$495 -> 1.1739771 | AA20: ='[1]New KPI vs BP'!$CA$502 -> 0.14510341 | AE20: G&A reclass | AG20: ='[1]New KPI vs BP'!$CA$496+'[1]New KPI vs BP'!$CA$518 -> 0.87953847
B22: Nissan NV | C22: ='[1]New KPI vs BP'!$CB$5 -> 16.778267 | D22: ='[1]New KPI vs BP'!$CB$15 -> 0.89735419 | E22: =#REF! -> #REF! | F22: Not Applicable | G22: =#REF! -> #REF! | I22: Comes From LIAM | O22: Summary | AN22: MZ impairment | AP22: 7.59
B23: Datsun NV | C23: ='[1]New KPI vs BP'!$CB$6 -> 0 | D23: =O15 -> 0 | E23: -66.717973 | G23: 44.993039 | I23: ='[4]vs PY MTD'!I54 -> 17.322003 | J23: ='[4]vs PY MTD'!J54 -> 0.011421721 | K23: ='[4]vs PY MTD'!K54 -> 2.6593172 | L23: ='[4]vs PY MTD'!L54 -> -2.4193085 | M23: ='[4]vs PY MTD'!M54 -> -19.504274 | O23: Month | AN23: G&A Impairment | AP23: 0.84326312
B24: Infiniti NV | C24: ='[1]New KPI vs BP'!$CB$26 -> -0.076822924 | O24: Tab
C25: =-SUM(E19:G19,U19:V19) -> #REF! | O25: See formula on O19 | AF25: 1.349717
C26: =SUM(C22:C25) -> #REF! | D26: =D22-D23 -> 0.89735419 | E26: =E22-E23 -> #REF! | G26: =G22-G23 -> #REF!
G32: OCS TdC VA supporting file
G33: X-badges TP | H33: ='[5]Vs LY'!$F$21-AD12 -> 5.7185438 | I33: TdC Others | M33: =M19 -> -13.656326 | P33: RMP-i Others | S33: =S19 -> #REF! | X33: TdC Others | AA33: =AD19 -> -0.11215198 | AE33: Fixed Cost Others | AH33: =AH19 -> -0.061184341 | AI33: G&A reclass | AJ33: ='Summary month'!AQ74 -> 0
E34: 2.1505438 | G34: Duties for CBUs | H34: ='[5]Vs LY'!$F$22 -> 0.1880751 | I34: 1 | J34: ='[4]vs PY MTD'!J59 -> Supplier Claims | M34: ='[4]vs PY MTD'!M59 -> 0 | P34: 1 | Q34: UC | S34: ='[1]New KPI vs BP'!$BY$7+'[1]New KPI vs BP'!$BY$27-X14 -> -0.35972331 | X34: 1 | Y34: Capacity Reservation | AA34: =AD11 -> 1.0408928 | AE34: 1 | AF34: G&A out of function scope | AH34: ='Summary month'!AQ44-'Summary month'!AQ74 -> 0 | AI34: HFM diff | AJ34: =-90957/10^6 -> -0.090957
G35: Outbound logistics | H35: ='[5]Vs LY'!$F$23 -> -0.058671505 | I35: 2 | J35: ='[4]vs PY MTD'!J60 -> OMP | M35: ='[4]vs PY MTD'!M60 -> -3.8308434 | P35: 2 | Q35: NRV | S35: =U43 -> -14.752834 | X35: 2 | Y35: NAE | AA35: ='[3]MTD vs LY'!$E$11 -> -3.5985595 | AE35: 2
G36: Micra SC | H36: ='[5]Vs LY'!$F$25 -> -0.237365 | I36: 3 | J36: ='[4]vs PY MTD'!J61 -> Inflation claims | M36: ='[4]vs PY MTD'!M61 -> -12.852132 | P36: 3 | Q36: UP | S36: =U44 -> -4.0539674 | X36: 3 | Y36: R&D | AA36: =AD13 -> -0.52825604 | AE36: 3 | AJ36: ='Summary month'!AQ44-'Summary month'!AQ74 -> 0
I37: 4 | J37: ='[4]vs PY MTD'!J62 -> Renault & ACI Price | M37: ='[4]vs PY MTD'!M62 -> 1.7189989 | P37: 4 | Q37: OCS No TdC | S37: 8.9 | X37: 4 | Y37: Plant AS | AA37: ='[3]MTD vs LY'!$E$7 -> 0.48269299 | AE37: 4
I38: 5 | J38: MZ Others | M38: ='[4]vs PY MTD'!$M$67--0.237365 -> -4.3029325 | P38: 5 | Q38: UED | S38: =V42 -> 19.370084 | X38: 5 | Y38: NMPC + RBU west | AA38: ='[3]MTD vs LY'!$E$6+'[3]MTD vs LY'!$E$8 -> -0.2022523 | AE38: 5 | AF38: Others | AH38: =AH33-SUM(AH34:AH37) -> -0.061184341
I39: 6 | J39: =G33 -> X-badges TP | M39: 5.7185438 | P39: 6 | Q39: Energy | S39: =U45 -> -0.38548447 | X39: 6
H40: -0.237365 | I40: 7 | J40: =G34 -> Duties for CBUs | M40: 0.1880751 | P40: 7 | Q40: SCOS | S40: =U48 -> -0.71133663 | T40: HQ supporting file source | X40: 7 | Y40: Others | AA40: =AA33-SUM(AA34:AA39) -> 2.6933301 | AB40: Volume mix
F41: (units) | I41: 8 | J41: =G35 -> Outbound logistics | M41: -0.058671505 | P41: 8 | Q41: NANO | S41: =U47 -> 0.22031469 | AB41: Service costs
D42: LY | E42: Act | F42: Var. | I42: 9 | J42: Micra SC | M42: =H36 -> -0.237365 | P42: 9 | T42: UED | V42: ='[1]New KPI vs BP'!$BY$23 -> 19.370084 | AB42: HFM
C43: WS | D43: ='[1]P&L vs BP'!$AO$28 -> 34258 | E43: ='[1]P&L vs BP'!AN28 -> 29345 | F43: =E43-D43 -> -4913 | I43: 10 | P43: 10 | Q43: Others | S43: =S33-SUM(S34:S42) -> #REF! | T43: NRV | U43: ='[6]MTD vs LY'!$F$8 -> -14.752834
C44: Export | D44: ='[1]P&L vs BP'!AO27 -> 850 | E44: ='[1]P&L vs BP'!AN27 -> 727 | F44: =E44-D44 -> -123 | I44: 11 | T44: UP | U44: ='[6]MTD vs LY'!$F$18 -> -4.0539674
I45: 12 | S45: =S43-S44 -> #REF! | T45: Energy business | U45: ='[6]MTD vs LY'!$F$17 -> -0.38548447
C46: Prod. | D46: ='[1]P&L vs BP'!AO18 -> 25782 | E46: ='[1]P&L vs BP'!AN18 -> 25381 | F46: =E46-D46 -> -401 | I46: 13 | J46: Others | M46: =M33-SUM(M34:M42) -> 0 | T46: G2I Deferred | U46: ='[6]MTD vs LY'!$F$13 -> 0.15833333 | V46: =SUM('[1]New KPI vs BP'!$BY$21:$BY$22,'[1]New KPI vs BP'!$BY$32)-SUM(U42:U45) -> 0.11703855
T47: NANO | U47: ='[6]MTD vs LY'!$F$23 -> 0.22031469
T48: SCOS reclass | U48: ='[6]MTD vs LY'!$F$22 -> -0.71133663
T49: OCS no TdC
T57: Other fixed | U57: =-X15-AD14-AH34 -> -2.0265088
T58: MZ | V58: As per current gap.
S59: ='[1]P&L vs BP'!$AP$238+'[1]New KPI vs BP'!$BY$500-AC19-AB19 -> 14.31705 | T59: Warranty
T62: OCS no TdC | U62: ='[1]New KPI vs BP'!$CG$19+'[1]New KPI vs BP'!$CG$30-O14 -> -216.84169 | X62: =U62-SUM(U63:U65) -> -236.74547 | Y62: FX balance in OCS no Tdc to be added to Royalty
T63: CBUs | U63: =17.7957989236187-O14 -> 17.795799
T64: Royalty | U64: 2.3017818
T65: Others | U65: -0.19379367

Sheet MTD VA vs BP
B1: ='Summary month'!E2 -> Apr | C1: =VLOOKUP(B1,mapping!$A$2:$C$13,3,0) -> M01
B3: [ROP] Variance Analysis
C5: =B10 -> BP MTD | D5: =C10 -> Act MTD | E5: var. | F5: FX | G5: Perf. | H5: check | N5: ='[7]P&L BP'!$M$353 -> 0
B6: RMP-i | C6: =INDEX('Summary month'!$K$82:$M$82,1,MATCH($C$1,'Summary month'!$O$6:$Q$6,0)) -> 64.2915 | D6: =INDEX('Summary month'!$F$82:$H$82,1,MATCH($C$1,'Summary month'!$O$6:$Q$6,0)) -> 63.237619 | E6: =+D6-C6 -> -1.0538805 | F6: =B19 -> -0.65442293 | G6: =SUM(C19:S19) -> -0.39945759 | H6: =E6-F6-G6 -> 1.2212453e-14
B7: Fixed Cost | C7: =INDEX('Summary month'!$K$83:$M$83,1,MATCH($C$1,'Summary month'!$O$6:$Q$6,0)) -> -152.79354 | D7: =INDEX('Summary month'!$F$83:$H$83,1,MATCH($C$1,'Summary month'!$O$6:$Q$6,0)) -> -134.40743 | E7: =+D7-C7 -> 18.386102 | F7: =T19 -> 0.65442293 | G7: =SUM(U19:AH19) -> 17.731679 | H7: =E7-F7-G7 -> 0
B8: Total | C8: =+C6+C7 -> -88.502036 | D8: =+D6+D7 -> -71.169814 | E8: =+D8-C8 -> 17.332222 | F8: =+E8-G8 -> 0 | G8: =+G6+G7 -> 17.332222 | H8: =E8-F8-G8 -> 0 | J8: The rest CMPI | K8: Export | L8: Fixed | N8: The rest CMPI | O8: Export | P8: Fixed plugged | Q8: Plug between Fixed and var
D9: =D12-D54 -> 1.7684209 | E9: =E12-E54 -> -0.40699341 | F9: =F12-F54 -> 0.99661906 | G9: =G12-G54 -> 1.1787952 | I9: ROP | J9: ='[7]New KPI vs BP'!$I$34-K9-L9 -> 0 | K9: ='[7]New KPI vs BP'!$I$15 -> 0 | L9: ='[7]New KPI vs BP'!$I$507+'[7]New KPI vs BP'!$I$523 -> 0 | N9: ='[7]New KPI vs BP'!$I$34-O9-P9 -> -0.65442293 | O9: =K9 -> 0 | P9: =L10-AJ76+AA20 -> 0.65442293 | Q9: =L9-(P9) -> -0.65442293
B10: BP MTD | C10: Act MTD | I10: CMPI | J10: =M52 -> -0.03693114 | K10: 0 | L10: =M53 -> 0.44392455
E11: FX | F11: RMP-i | G11: Fixed Cost | I11: Check
B12: =INDEX('Summary month'!$K$55:$M$55,1,MATCH($C$1,'Summary month'!$O$6:$Q$6,0)) -> -88.502036 | C12: =INDEX('Summary month'!$F$55:$H$55,1,MATCH($C$1,'Summary month'!$O$6:$Q$6,0)) -> -71.169814 | D12: =C12-B12 -> 17.332222 | E12: ='[7]New KPI vs BP'!$I$34 -> 0 | F12: =INDEX('Summary month'!$O$82:$Q$82,1,MATCH($C$1,'Summary month'!$O$6:$Q$6,0))-E13 -> -0.39945759 | G12: =INDEX('Summary month'!$O$83:$Q$83,1,MATCH($C$1,'Summary month'!$O$6:$Q$6,0))-E14 -> 17.731679 | I12: =SUM(E12:G12)-D12 -> 8.8817842e-14
E13: =SUM(N9:O9) -> -0.65442293 | F13: RMPI | O13: ITP MZ | P13: =-INDEX('Summary month'!$O$17:$Q$73,MATCH(O13,'Summary month'!$D$17:$D$74,0),MATCH($C$1,'Summary month'!$O$6:$Q$6,0)) -> 0
C14: Import OSP (In) | D14: Export OSP (Out) | E14: =P9 -> 0.65442293 | F14: Fixed C | O14: ITP Import CBU | P14: =-INDEX('Summary month'!$O$17:$Q$73,MATCH(O14,'Summary month'!$D$17:$D$74,0),MATCH($C$1,'Summary month'!$O$6:$Q$6,0)) -> 0
B15: Detailed Analysis | C15: Royalty NV | D15: Royalty Export | O15: ITP Export CBU | P15: =-INDEX('Summary month'!$O$17:$Q$73,MATCH(O15,'Summary month'!$D$17:$D$74,0),MATCH($C$1,'Summary month'!$O$6:$Q$6,0)) -> 0 | R15: NII | AA15: R&D (Functional ROP) | AB15: RS | AH15: M EUR
C16: RMP-I | U16: Fixed Cost
B17: FX | C17: M&S | H17: FNFR Revenue | I17: TdC | O17: ITP Change | P17: Royalty rate change | Q17: SF | R17: AS | S17: Others | T17: FX | U17: FMI | Y17: TdC | AE17: SF | AF17: AS | AH17: Others
C18: Vol. & Mix | D18: Export | E18: VME | F18: Grade Mix | G18: Pricing | I18: CR | J18: RM | K18: MFG variable | L18: SCM | M18: Others | N18: FNFR Cost | U18: FMI (M&S) | V18: CFMI | W18: Remktg | X18: FMI- out of function scope | Y18: MFG | Z18: VT | AA18: R&D *except for function | AB18: *RS (Global Function Cost) | AC18: Warranty | AD18: MFG - out of function scope | AG18: G&A (region)
B19: =E13 -> -0.65442293 | C19: =C61-INDEX('Summary month'!$O$17:$Q$74,MATCH(C14,'Summary month'!$D$17:$D$74,0),MATCH($C$1,'Summary month'!$O$6:$Q$6,0))-INDEX('Summary month'!$O$17:$Q$74,MATCH(C15,'Summary month'!$D$17:$D$74,0),MATCH($C$1,'Summary month'!$O$6:$Q$6,0))+J10-N9 -> 2.6098899 | D19: =S77-INDEX('Summary month'!$O$17:$Q$74,MATCH(D14,'Summary month'!$D$17:$D$74,0),MATCH($C$1,'Summary month'!$O$6:$Q$6,0))-INDEX('Summary month'!$O$17:$Q$74,MATCH(D15,'Summary month'!$D$17:$D$74,0),MATCH($C$1,'Summary month'!$O$6:$Q$6,0))-O9 -> -2.3177678 | E19: =E61 -> 0 | F19: =F61 -> 0 | G19: =G61 -> 0 | H19: =H61 -> 0 | O19: =SUM(P13:P15) -> 0 | R19: =R61-INDEX('Summary month'!$O$17:$Q$74,MATCH(R15,'Summary month'!$D$17:$D$74,0),MATCH($C$1,'Summary month'!$O$6:$Q$6,0)) -> -2.7507092 | S19: =F12-SUM(C19:R19) -> 2.0591296 | T19: =E14 -> 0.65442293 | U19: =U61 -> 3.1916236 | V19: =V61 -> 0.069500511 | X19: =X61 -> 0.024426873 | Y19: =Y61 -> 1.4947648 | Z19: =Z61 -> -0.1420389 | AA19: =AA61-INDEX('Summary month'!$O$17:$Q$74,MATCH(AA15,'Summary month'!$D$17:$D$74,0),MATCH($C$1,'Summary month'!$O$6:$Q$6,0))-AA20 -> -0.763957 | AB19: =-INDEX('Summary month'!$O$17:$Q$74,MATCH(AB15,'Summary month'!$D$17:$D$74,0),MATCH($C$1,'Summary month'!$O$6:$Q$6,0)) -> 1.953547 | AC19: =AC61 -> -1.5355154 | AD19: =AD61 -> 18.340846 | AG19: =AG61 -> -4.4020679 | AH19: =G12-SUM(U19:AG19) -> -0.49945011
B20: =B19-B61 -> -0.61749179 | C20: =C19-C61 -> 2.6098899 | D20: =D19-D61 -> -2.3177678 | E20: =E19-E61 -> 0 | F20: =F19-F61 -> 0 | G20: =G19-G61 -> 0 | H20: =H19-H61 -> 0 | I20: =I19-I61 -> 0 | ... S20: =S19-S61 -> 0.42933699 | AA20: ='[7]New KPI vs BP'!$I$502 -> 0
U22: =-S77+S26 -> 12.889111 | AF22: G&A reclass
B23: CMPI vol mix | C23: =C61 -> 0 | E23: Volu | F23: FX | I23: TdC Others | M23: =SUM(M24:M32) -> 0.47844348 | P23: RMP-i Others | S23: =S19 -> 2.0591296 | X23: TdC Others | AA23: =AD19 -> 18.340846 | AE23: Fixed Cost Others | AH23: =AH19 -> -0.49945011
B24: Profit-in | C24: =-INDEX('Summary month'!$O$17:$Q$74,MATCH(C14,'Summary month'!$D$17:$D$74,0),MATCH($C$1,'Summary month'!$O$6:$Q$6,0)) -> 1.1900716 | E24: =C24-F24 -> 9.7505726 | F24: -8.560501 | I24: 1 | J24: =J76 -> Supplier claims | M24: =M76 -> 0 | P24: 1 | Q24: =Q76 -> UC | S24: =S76 -> -0.10293934 | X24: 1 | Y24: =Y76 -> Cap res | AA24: 1.1 | AE24: 1 | AF24: G&A out of function | AH24: =AH76 -> -0.49945011
B25: Royalty | C25: =-INDEX('Summary month'!$O$17:$Q$74,MATCH(C15,'Summary month'!$D$17:$D$74,0),MATCH($C$1,'Summary month'!$O$6:$Q$6,0)) -> 0.8023265 | I25: 2 | J25: =J77 -> ILN business | M25: =M77 -> 0 | P25: 2 | Q25: =Q77 -> Export | S25: =S77 -> -0.74064409 | X25: 2 | Y25: Others | AA25: 0.70257314 | AE25: 2 | AF25: MZ impairment | AH25: 7.59
B26: FX diff | C26: =(M52-N9) -> 0.61749179 | I26: 3 | J26: =J78 -> KD ITPs | M26: =M78 -> 0 | P26: 3 | Q26: =Q78 -> NRV | S26: =S78 -> 12.148467 | X26: 3 | AE26: 3 | AF26: G&A Impairment | AH26: 0.84326312
I27: 4 | J27: =J79 -> X-badges TP | M27: =M79 -> 0.51162766 | P27: 4 | Q27: =Q79 -> CAFÉ | S27: =S79 -> 71.200542 | X27: 4 | AE27: 4
I28: 5 | J28: =J80 -> Duties for CBUs | M28: =M80 -> 0.19645217 | P28: 5 | Q28: BT | S28: -52 | X28: 5 | Y28: Others | AA28: =AA23-SUM(AA24:AA27) -> 16.538273 | AE28: 5 | AF28: Others | AH28: =AH23-SUM(AH24:AH27) -> -8.4332631
I29: 6 | J29: =J81 -> Outbound logistics | M29: =M81 -> -0.22963635 | P29: 6 | AH29: =AH28-AH80 -> 0
I30: 7 | P30: 7 | AA30: =AA28-AA80 -> -2.1638822
F31: (units) | I31: 8 | P31: 8
D32: BP | E32: Act | F32: Var. | I32: 9 | P32: 9
C33: WS | D33: ='[7]P&L vs BP'!$I$24 -> 29656 | E33: ='[7]P&L vs BP'!$H$24 -> 22727 | F33: =E33-D33 -> -6929 | I33: 10 | J33: =J85 -> Others | M33: =M23-SUM(M24:M32) -> 0 | P33: 10 | Q33: Others | S33: =S23-SUM(S24:S32) -> -28.446296
C34: Export | D34: ='[7]P&L vs BP'!$I$27 -> 1135 | E34: ='[7]P&L vs BP'!$H$27 -> 601 | F34: =E34-D34 -> -534 | M34: =M33-M85 -> 0.47844348 | S34: =S33-S85 -> 52.429337
C36: Prod. | D36: ='[7]P&L vs BP'!$I$18 -> 31133 | E36: ='[7]P&L vs BP'!$H$18 -> 27586 | F36: =E36-D36 -> -3547
B44: [CMP-i + Fixed Cost] Variance Analysis
N46: Sep Link | O46: ='[7]New KPI vs BP'!$CE$2 -> 0 | Q46: Master file link | R46: =[8]ACT_VOL!$N$5 -> 0
C47: =B52 -> BP MTD | D47: =C52 -> Act MTD | E47: var. | F47: FX | G47: Perf. | H47: check
B48: CMP-i | C48: =INDEX('Summary month'!$K$27:$M$27,1,MATCH($C$1,'Summary month'!$O$6:$Q$6,0)) -> 87.516627 | D48: =INDEX('Summary month'!$F$27:$H$27,1,MATCH($C$1,'Summary month'!$O$6:$Q$6,0)) -> 86.08362 | E48: =+D48-C48 -> -1.4330078 | F48: =B61 -> -0.03693114 | G48: =SUM(C61:S61) -> -1.3960766 | H48: =E48-F48-G48 -> 0
B49: Fixed Cost | C49: =INDEX('Summary month'!$K$46:$M$46,1,MATCH($C$1,'Summary month'!$O$6:$Q$6,0)) -> -145.46811 | D49: =INDEX('Summary month'!$F$46:$H$46,1,MATCH($C$1,'Summary month'!$O$6:$Q$6,0)) -> -128.4713 | E49: =+D49-C49 -> 16.996808 | F49: =T61 -> 0.44392455 | G49: =SUM(U61:AH61) -> 16.552884 | H49: =E49-F49-G49 -> 0
B50: Total | C50: =+C48+C49 -> -57.951486 | D50: =+D48+D49 -> -42.387685 | E50: =+D50-C50 -> 15.563801 | F50: =+E50-G50 -> 0.40699341 | G50: =+G48+G49 -> 15.156807 | H50: =E50-F50-G50 -> 0
G51: M EUR
B52: BP MTD | C52: Act MTD | L52: FX var | M52: =SUM(E55:E57,G55) -> -0.03693114
E53: FX | F53: CMP-i | G53: Fixed Cost | I53: Check | L53: FX fixed | M53: =SUM(U62:AH62,AJ76:AK76) -> 0.44392455 | AC53: CR | AD53: -0.36130901 | AE53: MFG out of function file
B54: =INDEX('Summary month'!$K$47:$M$47,1,MATCH($C$1,'Summary month'!$O$6:$Q$6,0)) -> -57.951486 | C54: =INDEX('Summary month'!$F$47:$H$47,1,MATCH($C$1,'Summary month'!$O$6:$Q$6,0)) -> -42.387685 | D54: =C54-B54 -> 15.563801 | E54: =SUM(M52:M53) -> 0.40699341 | F54: =INDEX('Summary month'!$O$27:$Q$27,1,MATCH($C$1,'Summary month'!$O$6:$Q$6,0))-M52 -> -1.3960766 | G54: =INDEX('Summary month'!$O$46:$Q$46,1,MATCH($C$1,'Summary month'!$O$6:$Q$6,0))-M53 -> 16.552884 | I54: =SUM(E54:G54)-D54 -> 0 | AC54: NISA/NMUK | AD54: =-2407/1000 -> -2.407 | AE54: Fixed variance OCS TdC from Nga's email
D55: NV | E55: =[8]CMOR_MTD_vsBP!$I$154+[8]CMOR_MTD_vsBP!$I$156+[8]CMOR_MTD_vsBP!$I$168 -> 0 | F55: UC | G55: =[8]CMOR_MTD_vsBP!$I$169+[8]CMOR_MTD_vsBP!$I$157+[8]CMOR_MTD_vsBP!$I$159 -> 0 | W55: AS | X55: 0.31749184 | Y55: 0.13019811 | AC55: R&D | AD55: 0.076442068 | AE55: MFG out of function file
D56: MZ | E56: =[8]CMOR_MTD_vsBP!$I$164+[8]CMOR_MTD_vsBP!$I$165 -> -0.03693114 | W56: UC | X56: 0.52690562 | Y56: 0 | AC56: Others | AD56: =AD61-SUM(AD53:AD55) -> 21.032713
B57: Detailed Analysis | D57: AS | E57: =[8]CMOR_MTD_vsBP!$I$160+[8]CMOR_MTD_vsBP!$I$162+[8]CMOR_MTD_vsBP!$I$170 -> 0 | W57: Others | X57: =X61-SUM(X55:X56) -> -0.81997058 | AH57: M EUR
C58: CMP-I | U58: Fixed Cost
B59: FX | C59: M&S | H59: FNFR Revenue | I59: TdC | O59: ITP Change | P59: Royalty rate change | Q59: SF | R59: AS | S59: Others | T59: FX | U59: FMI | Y59: TdC | AE59: SF | AF59: AS | AH59: Others
C60: Vol. & Mix | D60: Export | E60: VME | F60: Grade Mix | G60: Pricing | I60: CR | J60: RM | K60: MFG | L60: SCM | M60: Others | N60: FNFR Cost | U60: FMI (M&S) | V60: CFMI | W60: Remktg | X60: FMI- out of function scope | Y60: MFG | Z60: VT | AA60: R&D *except for function | AB60: *RS (Global Function Cost) | AC60: Warranty | AD60: MFG - out of function scope | AG60: G&A (region)
B61: =M52 -> -0.03693114 | C61: =SUM([8]CMOR_MTD_vsBP!$J$22+[8]CMOR_MTD_vsBP!$K$22) -> 0 | E61: =[8]CMOR_MTD_vsBP!$N$22 -> 0 | F61: =[8]CMOR_MTD_vsBP!$M$22+[8]CMOR_MTD_vsBP!$L$22 -> 0 | R61: =[8]CMOR_MTD_vsBP!$Q$22 -> -3.0258692 | S61: =F54-SUM(C61:R61) -> 1.6297926 | T61: =M53 -> 0.44392455 | U61: =INDEX('Summary month'!$O$17:$Q$74,MATCH(U60,'Summary month'!$D$17:$D$74,0),MATCH($C$1,'Summary month'!$O$6:$Q$6,0))-U62 -> 3.1916236 | V61: =INDEX('Summary month'!$O$17:$Q$74,MATCH(V60,'Summary month'!$D$17:$D$74,0),MATCH($C$1,'Summary month'!$O$6:$Q$6,0))-V62 -> 0.069500511 | X61: =INDEX('Summary month'!$O$17:$Q$74,MATCH(X60,'Summary month'!$D$17:$D$74,0),MATCH($C$1,'Summary month'!$O$6:$Q$6,0))-X62 -> 0.024426873 | Y61: =INDEX('Summary month'!$O$17:$Q$74,MATCH(Y60,'Summary month'!$D$17:$D$74,0),MATCH($C$1,'Summary month'!$O$6:$Q$6,0))-Y62 -> 1.4947648 | Z61: =INDEX('Summary month'!$O$17:$Q$74,MATCH(Z60,'Summary month'!$D$17:$D$74,0),MATCH($C$1,'Summary month'!$O$6:$Q$6,0))-Z62 -> -0.1420389 | AA61: =INDEX('Summary month'!$O$17:$Q$74,MATCH(AA60,'Summary month'!$D$17:$D$74,0),MATCH($C$1,'Summary month'!$O$6:$Q$6,0))-AA62 -> 0.010794793 | AC61: =INDEX('Summary month'!$O$17:$Q$74,MATCH(AC60,'Summary month'!$D$17:$D$74,0),MATCH($C$1,'Summary month'!$O$6:$Q$6,0))-AC62 -> -1.5355154 | AD61: =INDEX('Summary month'!$O$17:$Q$74,MATCH(AD60,'Summary month'!$D$17:$D$74,0),MATCH($C$1,'Summary month'!$O$6:$Q$6,0))-AD62 -> 18.340846 | AG61: =INDEX('Summary month'!$O$17:$Q$74,MATCH(AG60,'Summary month'!$D$17:$D$74,0),MATCH($C$1,'Summary month'!$O$6:$Q$6,0))-AG62 -> -4.4020679 | AH61: =G54-SUM(U61:AG61) -> -0.49945011
U62: =[8]CMOR_MTD_vsBP!$I$155 -> 0 | X62: =SUM(Y55:Y56) -> 0.13019811 | Y62: =[8]CMOR_MTD_vsBP!$I$163-Z62 -> 0.11203816 | Z62: =[8]VA_MZ_MTD!$W$10 -> 0.0015629365 | AC62: =[8]CMOR_MTD_vsBP!$I$167 -> 0 | AG62: =[8]CMOR_MTD_vsBP!$I$166-AJ76-AK76 -> 0.45725273
U63: =[8]CMOR_MTD_vsBP!$T$22 -> 0.78981124
B74: Need this compare for S&M (BP to derive gap as technical challenge)
C75: BP2 | D75: BP3 | G75: OCS TdC VA supporting file | I75: TdC Others | M75: =M61 -> 0 | P75: RMP-i Others | S75: =S61 -> 1.6297926 | X75: TdC Others | AA75: =AD61 -> 18.340846 | AE75: Fixed Cost Others | AH75: =AH61 -> -0.49945011 | AK75: HFM diff
B76: S&M | G76: X-badges TP | H76: =-1.895372337-AD54 -> 0.51162766 | I76: 1 | J76: Supplier claims | P76: 1 | Q76: UC | S76: =[8]CMOR_MTD_vsBP!$O$22 -> -0.10293934 | X76: 1 | Y76: Cap res | AA76: =AD53 -> -0.36130901 | AE76: 1 | AF76: G&A out of function scope | AH76: =INDEX('Summary month'!$O$17:$Q$74,MATCH(AF76,'Summary month'!$D$17:$D$44,0),MATCH($C$1,'Summary month'!$O$6:$Q$6,0))-AJ76-AK76 -> -0.49945011 | AI76: G&A reclass | AJ76: =INDEX('Summary month'!$O$17:$Q$74,MATCH(AI76,'Summary month'!$D$17:$D$74,0),MATCH($C$1,'Summary month'!$O$6:$Q$6,0)) -> -0.21049839 | AK76: =-46629/10^6 -> -0.046629
G77: Duties for CBUs | H77: 0.19645217 | I77: 2 | J77: ILN business | P77: 2 | Q77: Export | S77: =SUM('[7]New KPI vs BP'!$H$449) -> -0.74064409 | X77: 2 | AE77: 2 | AF77: MZ impairment | AH77: 7.59 | AI77: Others | AJ77: =AH76 -> -0.49945011
G78: Outbound logistics | H78: -0.22963635 | I78: 3 | J78: KD ITPs | P78: 3 | Q78: NRV | S78: 12.148467 | X78: 3 | AE78: 3 | AF78: G&A Impairment | AH78: 0.84326312
G79: Micra SC | I79: 4 | J79: X-badges TP | M79: 0.51162766 | P79: 4 | Q79: CAFÉ | S79: 71.200542 | X79: 4 | AE79: 4
I80: 5 | J80: Duties for CBUs | M80: 0.19645217 | P80: 5 | X80: 5 | Y80: Others | AA80: =AA75-SUM(AA76:AA79) -> 18.702155 | AE80: 5 | AF80: Others | AH80: =AH75-SUM(AH76:AH79) -> -8.4332631
I81: 6 | J81: Outbound logistics | M81: -0.22963635 | P81: 6 | T81: HQ supporting file source
I82: 7 | P82: 7
I83: 8 | P83: 8 | T83: NRV | U83: 12.148467
I84: 9 | P84: 9 | T84: Insurance
I85: 10 | J85: Others | M85: =M75-SUM(M76:M84) -> -0.47844348 | P85: 10 | Q85: Others | S85: =S75-SUM(S76:S84) -> -80.875633 | T85: Energy Business
T86: UP | U86: 11.346037
Q87: =SUM(S77:S85)+SUM(H76:H79)-H78 -> 2.4408117 | S87: =S85-S86 -> -80.875633 | T87: Contingency | U87: -68.012133 | V87: Blind task | W87: -52.736101
P88: NRV | Q88: 12.1 | T88: NANO
P89: Mgt Task | Q89: -52.7 | T89: HQ items | V89: =SUM('[7]New KPI vs BP'!$H$455:$H$456,'[7]New KPI vs BP'!$H$466)-SUM(U83:U88) -> 13.362932
P90: Technical challenge S&M | Q90: -22 | T90: UED
J91: Supplier claims | M91: 10.2 | T91: OCS no TdC | U91: =SUM('[7]New KPI vs BP'!$H$453+'[7]New KPI vs BP'!$H$464) -> 13.03484
J92: ILN business | M92: -0.8
J93: KD ITPs | M93: -4.8
Q95: =Q87-SUM(Q88:Q93) -> 65.040812
T99: Methodology diff | U99: =SUM(U100:U102) -> -19.666663
T100: Warr | V100: ='[7]P&L vs BP'!$H$238-'[7]New KPI vs BP'!$H$437-AC61-AB61 -> -3.3636703
T101: Others | U101: =-AJ77-AD56-X57-AK76 -> -19.666663
T102: MZ

Sheet YTD VA vs BP
B1: ='Summary month'!E2 -> Apr | C1: =VLOOKUP(B1,mapping!$A$2:$C$13,3,0) -> M01
B3: [ROP] Variance Analysis
K4: ='[7]New KPI vs BP'!$L$1 -> 0
C5: =B10 -> BP YTD | D5: =C10 -> Act YTD | E5: var. | F5: FX | G5: Perf. | H5: check
B6: RMP-i | C6: =#REF! -> #REF! | D6: =#REF! -> #REF! | E6: =+D6-C6 -> #REF! | F6: =B19 -> #REF! | G6: =SUM(C19:S19) -> #REF! | H6: =E6-F6-G6 -> #REF!
B7: Fixed Cost | C7: =#REF! -> #REF! | D7: =#REF! -> #REF! | E7: =+D7-C7 -> #REF! | F7: =T19 -> #REF! | G7: =SUM(U19:AH19) -> #REF! | H7: =E7-F7-G7 -> #REF!
B8: Total | C8: =+C6+C7 -> #REF! | D8: =+D6+D7 -> #REF! | E8: =+D8-C8 -> #REF! | F8: =+E8-G8 -> #REF! | G8: =+G6+G7 -> #REF! | H8: =E8-F8-G8 -> #REF! | J8: The rest CMPI | K8: Export | L8: Fixed | N8: The rest CMPI | O8: Royalty | P8: Export | Q8: Fixed plugged | R8: Plug between Fixed and var
D9: =D12-D54 -> #REF! | E9: =E12-E54 -> #REF! | F9: =F12-F54 -> #REF! | G9: =G12-G54 -> #REF! | I9: ROP | J9: ='[7]New KPI vs BP'!$O$34-K9-L9 -> 0.24901363 | K9: ='[7]New KPI vs BP'!$O$15 -> -4.3801575 | L9: ='[7]New KPI vs BP'!$O$507+'[7]New KPI vs BP'!$O$523 -> -1.0929637 | N9: ='[7]New KPI vs BP'!$O$34-P9-Q9-O9 -> #REF! | O9: ='[7]New KPI vs BP'!$O$19 -> -0.65156485 | P9: =K9 -> -4.3801575 | Q9: =L10-AJ78+AA20 -> #REF! | R9: =L9-(Q9) -> #REF!
B10: BP YTD | C10: Act YTD | I10: CMPI | J10: =M52 -> 0.24924717 | K10: 0 | L10: =M53 -> #REF!
E11: FX | F11: RMP-i | G11: Fixed Cost | I11: Check | N11: =SUM(N9:P9) -> #REF!
B12: =#REF! -> #REF! | C12: =#REF! -> #REF! | D12: =C12-B12 -> #REF! | E12: ='[7]New KPI vs BP'!$O$34 -> -5.2241075 | F12: =#REF!-E13 -> #REF! | G12: =#REF!-E14 -> #REF! | I12: =SUM(E12:G12)-D12 -> #REF!
E13: =SUM(N9:P9) -> #REF! | F13: RMPI | G13: =E13-M52 -> #REF! | O13: ITP MZ | P13: =-#REF! -> #REF!
C14: Import OSP (In) | D14: Export OSP (Out) | E14: =Q9 -> #REF! | F14: Fixed C | G14: =E14-M53 -> #REF! | O14: ITP Import CBU | P14: =-#REF! -> #REF!
B15: Detailed Analysis | C15: Royalty NV | D15: Royalty Export | O15: ITP Export CBU | P15: =-#REF! -> #REF! | R15: NII | AA15: R&D (Functional ROP) | AB15: RS | AH15: M EUR
C16: RMP-I | U16: Fixed Cost
B17: FX | C17: M&S | H17: FNFR Revenue | I17: TdC | O17: ITP Change | P17: Royalty rate change | Q17: SF | R17: AS | S17: Others | T17: FX | U17: FMI | Y17: TdC | AE17: SF | AF17: AS | AH17: Others
C18: Vol. & Mix | D18: Export | E18: VME | F18: Grade Mix | G18: Pricing | I18: CR | J18: RM | K18: MFG variable | L18: SCM | M18: Others | N18: FNFR Cost | U18: FMI (M&S) | V18: CFMI | W18: Remktg | X18: FMI- out of function scope | Y18: MFG | Z18: VT | AA18: R&D *except for function | AB18: *RS (Global Function Cost) | AC18: Warranty | AD18: MFG - out of function scope | AG18: G&A (region)
B19: =E13 -> #REF! | C19: =C61-#REF!-#REF!+M52-N9-O9 -> #REF! | D19: =S79-#REF!-#REF!-P9 -> #REF! | E19: =E61 -> 0 | F19: =F61 -> 0 | H19: =H61 -> 0 | I19: =I61 -> 0 | J19: =J61 -> 0 | K19: =K61 -> 0 | L19: =L61 -> 0 | M19: =M61 -> 11.089002 | O19: =-SUM(#REF!) -> #REF! | R19: =R61-#REF! -> #REF! | S19: =F12-SUM(C19:R19) -> #REF! | T19: =E14 -> #REF! | U19: =U61 -> #REF! | V19: =V61 -> #REF! | X19: =X61 -> #REF! | Y19: =Y61 -> #REF! | Z19: =Z61 -> #REF! | AA19: =AA61-#REF!-AA20 -> #REF! | AB19: =-#REF! -> #REF! | AC19: =AC61 -> #REF! | AD19: =AD61 -> #REF! | AG19: =AG61 -> #REF! | AH19: =G12-SUM(U19:AG19) -> #REF!
B20: =B19-B61 -> #REF! | C20: =C19-C61 -> #REF! | D20: =D19-D61 -> #REF! | E20: =E19-E61 -> 0 | F20: =F19-F61 -> 0 | G20: =G19-G61 -> 0 | H20: =H19-H61 -> 0 | I20: =I19-I61 -> 0 | ... S20: =S19-S61 -> #REF! | AA20: ='[7]New KPI vs BP'!$O$20 -> -0.10829058 | AE20: G&A reclass
E21: Vol&model mix | F21: ctry mix
B23: CMPI vol mix | C23: =C61 -> 0 | E23: Volu | F23: FX | I23: TdC Others | M23: =M19 -> 11.089002 | P23: RMP-i Others | S23: =S19 -> #REF! | X23: TdC Others | AA23: =AD19 -> #REF! | AC23: Fixed Cost Others | AH23: =AH19 -> #REF!
B24: Profit-in | C24: =-#REF! -> #REF! | E24: =C24-F24 -> #REF! | F24: -18.955471 | I24: 1 | J24: =J78 -> Supplier claims | M24: =M78 -> 0 | P24: 1 | Q24: UC | S24: =S78 -> 1.3132448 | X24: 1 | Y24: Pension interest | AA24: 1 | AC24: 1 | AD24: G&A out of function | AH24: =AH78 -> #REF!
B25: Royalty | C25: =-#REF!-O9 -> #REF! | I25: 2 | J25: =J79 -> Legacy claims | M25: =M79 -> 0 | P25: 2 | Q25: =Q80 -> NRV | S25: =S80 -> 32.423303 | X25: 2 | Y25: Cap reservation | AA25: 5.3 | AC25: 2 | AD25: Compact EV | AH25: 17.900473
B26: FX diff | C26: =(M52-N9) -> #REF! | I26: 3 | J26: =J80 -> ILN parts business | M26: =M80 -> 0 | P26: 3 | Q26: =Q81 -> UP | S26: =S81 -> -1.6228608 | X26: 3 | AC26: 3 | AD26: MZ Impairment | AH26: 34.243265
I27: 4 | J27: =J81 -> P33B ePwr Step 2 | M27: =M81 -> 0 | P27: 4 | Q27: CCS | S27: =-#REF! -> #REF! | U27: =-S79+S27 -> #REF! | X27: 4 | AC27: 4 | AD27: G&A Impairment | AH27: 4.0699013
I28: 5 | J28: =J82 -> MZ Others | M28: =M82 -> 0 | P28: 5 | Q28: =Q82 -> UED | S28: =S82 -> -3.9732329 | X28: 5 | Y28: Others | AA28: =AA23-SUM(AA24:AA27) -> #REF! | AC28: 5 | AD28: Others | AH28: =AH23-SUM(AH24:AH27) -> #REF!
I29: 6 | J29: =J83 -> X-badges TP | M29: =M83 -> 4.5191856 | P29: 6 | AA29: =AA28-AA82 -> #REF! | AH29: =AH28-AH82 -> #REF!
I30: 7 | J30: =J84 -> Duties for CBUs | M30: =M84 -> 0.14771901 | P30: 7
F31: (units) | I31: 8 | P31: 8
D32: BP | E32: Act | F32: Var. | I32: 9 | P32: 9
C33: WS | D33: ='[7]P&L vs BP'!$M$24 -> 177129 | E33: ='[7]P&L vs BP'!$L$24 -> 170974 | F33: =E33-D33 -> -6155 | I33: 10 | P33: 10 | Q33: Others | S33: =S23-SUM(S24:S32) -> #REF!
C34: Export | D34: ='[7]P&L vs BP'!$M$27 -> 8139 | E34: ='[7]P&L vs BP'!$L$27 -> 4870 | F34: =E34-D34 -> -3269 | I34: 11 | S34: =S33-S87 -> #REF!
I35: 12 | J35: Others | M35: =M23-SUM(M24:M34) -> 6.4220974
C36: Prod. | D36: ='[7]P&L vs BP'!$M$18 -> 160906 | E36: ='[7]P&L vs BP'!$L$18 -> 154758 | F36: =E36-D36 -> -6148 | M36: =M35-M89 -> 6.4220974
B44: [CMP-i + Fixed Cost] Variance Analysis
AM45: 167
AM46: =4*AM45/1000 -> 0.668
C47: =B52 -> BP YTD | D47: =C52 -> Act YTD | E47: var. | F47: FX | G47: Perf. | H47: check | N47: =[8]CMOR_MTD_vsBP!$N$20 -> 0
B48: CMP-i | C48: =#REF! -> #REF! | D48: =#REF! -> #REF! | E48: =+D48-C48 -> #REF! | F48: =B61 -> 0.24924717 | G48: =SUM(C61:S61) -> #REF! | H48: =E48-F48-G48 -> #REF!
B49: Fixed Cost | C49: =#REF! -> #REF! | D49: =#REF! -> #REF! | E49: =+D49-C49 -> #REF! | F49: =T61 -> #REF! | G49: =SUM(U61:AH61) -> #REF! | H49: =E49-F49-G49 -> #REF!
B50: Total | C50: =+C48+C49 -> #REF! | D50: =+D48+D49 -> #REF! | E50: =+D50-C50 -> #REF! | F50: =+E50-G50 -> #REF! | G50: =+G48+G49 -> #REF! | H50: =E50-F50-G50 -> #REF!
G51: M EUR
B52: BP YTD | C52: Act YTD | L52: FX var | M52: =SUM(E55:E57,G55) -> 0.24924717
E53: FX | F53: CMP-i | G53: Fixed Cost | I53: Check | L53: FX fixed | M53: =SUM(U62:AH62,AJ78:AK78) -> #REF! | AC53: Capacity Reserve | AD53: -0.48010669 | AE53: MFG out of function file
B54: =#REF! -> #REF! | C54: =#REF! -> #REF! | D54: =C54-B54 -> #REF! | E54: =SUM(M52:M53) -> #REF! | F54: =#REF!-M52 -> #REF! | G54: =#REF!-M53 -> #REF! | I54: =SUM(E54:G54)-D54 -> #REF! | AC54: NISA/NMUK | AD54: =23856/1000 -> 23.856 | AE54: Fixed variance OCS TdC from Nga's email
D55: NV | E55: =[8]CMOR_YTD_vsBP!$I$154+[8]CMOR_YTD_vsBP!$I$156+[8]CMOR_YTD_vsBP!$I$168 -> 0 | F55: UC | G55: =[8]CMOR_YTD_vsBP!$I$169+[8]CMOR_YTD_vsBP!$I$157+[8]CMOR_YTD_vsBP!$I$159 -> 0 | W55: AS | X55: 1.3642545 | Y55: 0.2493639 | AC55: R&D | AD55: -17.149127 | AE55: MFG out of function file
D56: MZ | E56: =[8]CMOR_YTD_vsBP!$I$164+[8]CMOR_YTD_vsBP!$I$165 -> 0.24924717 | W56: UC | X56: 1.1356576 | Y56: 0 | AC56: Others | AD56: =AD61-SUM(AD53:AD55) -> #REF!
B57: Detailed Analysis | D57: AS | E57: =[8]CMOR_YTD_vsBP!$I$160+[8]CMOR_YTD_vsBP!$I$162+[8]CMOR_YTD_vsBP!$I$170 -> 0 | W57: Others | X57: =X61-SUM(X55:X56) -> #REF! | AH57: M EUR
C58: CMP-I | U58: Fixed Cost
B59: FX | C59: M&S | H59: FNFR Revenue | I59: TdC | O59: ITP Change | P59: Royalty rate change | Q59: SF | R59: AS | S59: Others | T59: FX | U59: FMI | Y59: TdC | AE59: SF | AF59: AS | AH59: Others
C60: Vol. & Mix | D60: Export | E60: VME | F60: Grade Mix | G60: Pricing | I60: CR | J60: RM | K60: MFG | L60: SCM | M60: Others | N60: FNFR Cost | U60: FMI (M&S) | V60: CFMI | W60: Remktg | X60: FMI- out of function scope | Y60: MFG | Z60: VT | AA60: R&D *except for function | AB60: *RS (Global Function Cost) | AC60: Warranty | AD60: MFG - out of function scope | AG60: G&A (region)
B61: =M52 -> 0.24924717 | C61: =[8]CMOR_YTD_vsBP!$J$22+[8]CMOR_YTD_vsBP!$K$22 -> 0 | E61: =[8]CMOR_YTD_vsBP!$N$22 -> 0 | F61: =[8]CMOR_YTD_vsBP!$M$22+[8]CMOR_YTD_vsBP!$L$22 -> 0 | I61: =I65 -> 0 | J61: =J65 -> 0 | K61: =K65 -> 0 | L61: =L65 -> 0 | M61: =M65+SUM(M83:M85) -> 11.089002 | R61: =[8]CMOR_YTD_vsBP!$Q$22 -> -23.002553 | S61: =F54-SUM(C61:R61) -> #REF! | T61: =M53 -> #REF! | U61: =#REF!-U62 -> #REF! | V61: =#REF!-V62 -> #REF! | X61: =#REF!-X62 -> #REF! | Y61: =#REF!-Y62 -> #REF! | Z61: =#REF!-Z62 -> #REF! | AA61: =#REF! -> #REF! | AC61: =#REF!-AC62 -> #REF! | AD61: =#REF! -> #REF! | AG61: =#REF!-AG62 -> #REF! | AH61: =G54-SUM(U61:AG61) -> #REF!
U62: =[8]CMOR_YTD_vsBP!$I$155 -> 0 | X62: =SUM(Y55:Y56) -> 0.2493639 | Y62: =[8]CMOR_YTD_vsBP!$I$163-Z62 -> -0.84143031 | Z62: =[8]VA_MZ_MTD!$W$10 -> 0.0015629365 | AC62: =[8]CMOR_YTD_vsBP!$I$167 -> 0 | AG62: =[8]CMOR_YTD_vsBP!$I$166-AJ78-AK78 -> #REF!
I64: Elena's Input
G77: OCS TdC VA supporting file | I77: TdC Others | M77: =M61 -> 11.089002 | P77: RMP-i Others | S77: =S61 -> #REF! | X77: TdC Others | AA77: =AD61 -> #REF! | AE77: Fixed Cost Others | AH77: =AH61 -> #REF! | AK77: HFM diff
G78: X-badges TP | H78: =28.375185578-AD54 -> 4.5191856 | I78: 1 | J78: Supplier claims | P78: 1 | Q78: UC | S78: =[8]CMOR_YTD_vsBP!$O$22 -> 1.3132448 | X78: 1 | Y78: Pension interest | AA78: 1 | AE78: 1 | AF78: G&A out of function scope | AH78: =#REF!-AJ78-AK78 -> #REF! | AI78: G&A reclass | AJ78: =#REF! -> #REF! | AK78: =-166643/10^6 -> -0.166643
G79: Duties for CBUs | H79: 0.14771901 | I79: 2 | J79: Legacy claims | P79: 2 | Q79: Export | S79: =SUM('[7]New KPI vs BP'!$N$449+'[7]New KPI vs BP'!$N$460) -> -7.7900944 | X79: 2 | Y79: Other | AA79: 1.5366604 | AE79: 2 | AF79: MZ Impairment | AH79: 34.243265 | AI79: Others | AJ79: =AH78 -> #REF!
G80: Outbound logistics | H80: 6.4220974 | I80: 3 | J80: ILN parts business | P80: 3 | Q80: NRV | S80: 32.423303 | X80: 3 | AE80: 3 | AF80: G&A Impairment | AH80: 4.0699013
I81: 4 | J81: P33B ePwr Step 2 | P81: 4 | Q81: UP | S81: -1.6228608 | X81: 4 | AE81: 4
G82: Micra SC | I82: 5 | J82: MZ Others | P82: 5 | Q82: UED | S82: -3.9732329 | X82: 5 | Y82: Others | AA82: =AA77-SUM(AA78:AA81) -> #REF! | AE82: 5 | AF82: Others | AH82: =AH77-SUM(AH78:AH81) -> #REF!
H83: 30.270558 | I83: 6 | J83: X-badges TP | M83: 4.5191856 | P83: 6 | Q83: NANO | S83: -1.0496378
H84: 0.14771901 | I84: 7 | J84: Duties for CBUs | M84: 0.14771901 | P84: 7
H85: 6.4220974 | I85: 8 | J85: Outbound logistics | M85: 6.4220974 | P85: 8 | T85: HQ supporting file source
I86: 9 | P86: 9 | T86: NRV | U86: 32.423303
I87: 10 | P87: 10 | Q87: Others | S87: =S77-SUM(S78:S86) -> #REF! | T87: Contingency | V87: Blind Task | W87: -138.9946 | X87: =U87-W87 -> 138.9946 | Y87: Say it Reserve
I88: 11 | T88: UP
I89: 12 | J89: Others | M89: =M77-SUM(M78:M87) -> 0 | Q89: =SUM(S79:S87)+SUM(H78:H81)-H80 -> #REF! | S89: =S87-S88 -> #REF! | T89: CAFÉ | U89: 91.752578
P90: CAFÉ | Q90: 20.552035 | T90: NANO
P91: Mgt Task | Q91: =W87 -> -138.9946 | T91: HQ Other | V91: =SUM('[7]New KPI vs BP'!$N$455:$N$456,'[7]New KPI vs BP'!$N$466)-SUM(U86:U90) -> -255.55299 | W91: Energy Bus | X91: 0.76235757
P92: NRV | Q92: =U86 -> 32.423303 | T92: UED | V92: ='[7]New KPI vs BP'!$N$457 -> -11.96579
T94: OCS no Tdc | V94: =SUM('[7]New KPI vs BP'!$N$453+'[7]New KPI vs BP'!$N$464) -> 59.399716
Q95: =Q89-SUM(Q90:Q94) -> #REF!
T96: CAFÉ
W99: =U88+U91+U92+U103 -> #REF!
T103: Methdology diff | U103: =SUM(U104:U106) -> #REF!
T104: warr | U104: -0.81197906 | V104: ='[7]P&L vs BP'!$N$238-'[7]New KPI vs BP'!$N$437-AC61-AB61 -> #REF!
T105: Others(Fixed Cost) | U105: =-AD56-AJ79-X57-AK78 -> #REF!
T106: MZ and S&M | U106: 6.8768868 | V106: ='[7]New KPI vs BP'!$P$447 -> -26.049091

Sheet Q2 Act VA vs Q2 FC2+10
B1: ='Summary month'!E2 -> Apr | C1: =VLOOKUP(B1,mapping!$A$2:$C$13,3,0) -> M01
R2: CONVERT THIS TO FC2+10
B3: [ROP] Variance Analysis | DZ3: #N/A
C5: =B10 -> Q2 FC2+10 | D5: =C10 -> Act QTD | E5: var. | F5: FX | G5: Perf. | H5: check
B6: RMP-i | C6: ='Summary month'!N82 -> 64.2915 | D6: ='Summary month'!I82 -> 63.237619 | E6: =+D6-C6 -> -1.0538805 | F6: =B19 -> -18.286443 | G6: =SUM(C19:S19) -> 18.286443 | H6: =E6-F6-G6 -> -1.0538805
B7: Fixed Cost | C7: ='Summary month'!N83 -> -152.79354 | D7: ='Summary month'!I83 -> -134.40743 | E7: =+D7-C7 -> 18.386102 | F7: =T19 -> -0.27649333 | G7: =SUM(U19:AH19) -> -134.13094 | H7: =E7-F7-G7 -> 152.79354
B8: Total | C8: =+C6+C7 -> -88.502036 | D8: =+D6+D7 -> -71.169814 | E8: =+D8-C8 -> 17.332222 | F8: =+E8-G8 -> 133.17672 | G8: =+G6+G7 -> -115.8445 | H8: =E8-F8-G8 -> 0 | J8: The rest CMPI | K8: Export | L8: Fixed | N8: The rest CMPI | O8: Export | P8: Fixed plugged | Q8: Plug between Fixed and var
D9: =D12-D54 -> #VALUE! | E9: =E12-E54 -> -26.646039 | F9: =F12-F54 -> #VALUE! | G9: =G12-G54 -> -134.61793 | I9: ROP | J9: ='[9]New KPI vs BP'!$U$34-K9-L9 -> 8.5339838 | K9: ='[9]New KPI vs BP'!$U$15 -> -1.1661104 | L9: ='[9]New KPI vs BP'!$U$507+'[9]New KPI vs BP'!$U$523 -> -25.93081 | N9: ='[9]New KPI vs BP'!$U$34-O9-P9 -> -17.120333 | O9: =K9 -> -1.1661104 | P9: =L10-AJ73 -> -0.27649333 | Q9: =L9-(P9) -> -25.654316
B10: Q2 FC2+10 | C10: Act QTD | I10: CMPI | J10: =M52 -> 16.472865 | K10: 0 | L10: =M53 -> -0.48699172
E11: FX | F11: RMP-i | G11: Fixed Cost | I11: Check
B12: ='Summary month'!W55 -> -71.169814 | C12: ='Summary month'!I55 -> -71.169814 | D12: =C12-B12 -> 0 | E12: -10.660166 | F12: ='Summary month'!W82-E13 -> 18.286443 | G12: ='Summary month'!W83-E14 -> -134.13094 | I12: =SUM(E12:G12)-D12 -> -126.50466
E13: =SUM(N9:O9) -> -18.286443 | F13: RMPI | O13: ITP MZ | P13: =-'Summary month'!R66 -> 0
C14: Import OSP (In) | D14: Export OSP (Out) | E14: =P9 -> -0.27649333 | F14: Fixed C | O14: ITP Import CBU | P14: =-'Summary month'!R67 -> 0
B15: Detailed Analysis | C15: Royalty NV | D15: Royalty Export | O15: ITP Export CBU | P15: =-'Summary month'!R68 -> 0 | R15: NII | AA15: R&D (Functional ROP) | AB15: RS | AH15: M EUR
C16: RMP-I | U16: Fixed Cost
B17: FX | C17: M&S | H17: FNFR Revenue | I17: TdC | O17: ITP Change | P17: Royalty rate change | Q17: SF | R17: AS | S17: Others | T17: FX | U17: FMI | Y17: TdC | AE17: SF | AF17: AS | AH17: Others
C18: Vol. & Mix | D18: Export | E18: VME | F18: Grade Mix | G18: Pricing | I18: CR | J18: RM | K18: MFG variable | L18: SCM | M18: Others | N18: FNFR Cost | U18: FMI (M&S) | V18: CFMI | W18: Remktg | X18: FMI- out of function scope | Y18: MFG | Z18: VT | AA18: R&D *except for function | AB18: *RS (Global Function Cost) | AC18: Warranty | AD18: MFG - out of function scope | AG18: G&A (region)
